{
  "schema_version": "1.0",
  "events": [
    {
      "event": "RBC Heritage",
      "event_id": 12,
      "year": 2026,
      "completed": "2026-04-19",
      "graded_at_utc": "2026-04-29T01:56:02Z",
      "thresholds": {
        "cash_line": 340,
        "top_1_pct": 410,
        "top_001_pct": 500
      },
      "portfolio": {
        "n_lineups": 12,
        "avg_proj": 459.03,
        "avg_actual": 488.46,
        "n_below_cash": 0,
        "n_cash": 0,
        "n_top_1pct": 9,
        "n_top_001pct": 3,
        "best_lineup_id": "L1",
        "best_lineup_actual": 513.0,
        "worst_lineup_id": "G2",
        "worst_lineup_actual": 444.5,
        "delta_pct": 6.41
      },
      "lineups": [
        {
          "lineup_id": "C1",
          "kind": "Core",
          "title": "Scheffler + Harbour Town Specialists",
          "label": "Core #1 \u2014 Scheffler + Harbour Town Specialists",
          "salary": 48200,
          "proj_total": 473.1,
          "players": [
            {
              "dg_id": 18417,
              "name": "Scheffler, Scottie",
              "salary": 13500
            },
            {
              "dg_id": 10419,
              "name": "Noren, Alex",
              "salary": 7100
            },
            {
              "dg_id": 21554,
              "name": "Poston, J.T.",
              "salary": 7200
            },
            {
              "dg_id": 8825,
              "name": "Harman, Brian",
              "salary": 7000
            },
            {
              "dg_id": 23475,
              "name": "Novak, Andrew",
              "salary": 6700
            },
            {
              "dg_id": 17488,
              "name": "Im, Sungjae",
              "salary": 6700
            }
          ],
          "actual_total": 491.5,
          "delta_pct": 3.89,
          "verdict": "top_1_pct"
        },
        {
          "lineup_id": "C2",
          "kind": "Core",
          "title": "Scheffler + Contrarian Value Stack",
          "label": "Core #2 \u2014 Scheffler + Contrarian Value Stack",
          "salary": 48100,
          "proj_total": 461.6,
          "players": [
            {
              "dg_id": 18417,
              "name": "Scheffler, Scottie",
              "salary": 13500
            },
            {
              "dg_id": 17606,
              "name": "Berger, Daniel",
              "salary": 7300
            },
            {
              "dg_id": 17576,
              "name": "Conners, Corey",
              "salary": 7000
            },
            {
              "dg_id": 13872,
              "name": "Bradley, Keegan",
              "salary": 6900
            },
            {
              "dg_id": 23475,
              "name": "Novak, Andrew",
              "salary": 6700
            },
            {
              "dg_id": 17488,
              "name": "Im, Sungjae",
              "salary": 6700
            }
          ],
          "actual_total": 497.0,
          "delta_pct": 7.67,
          "verdict": "top_1_pct"
        },
        {
          "lineup_id": "C3",
          "kind": "Core",
          "title": "Scheffler + 5 Low-Owned Specialists",
          "label": "Core #3 \u2014 Scheffler + 5 Low-Owned Specialists",
          "salary": 48800,
          "proj_total": 473.9,
          "players": [
            {
              "dg_id": 18417,
              "name": "Scheffler, Scottie",
              "salary": 13500
            },
            {
              "dg_id": 10419,
              "name": "Noren, Alex",
              "salary": 7100
            },
            {
              "dg_id": 17606,
              "name": "Berger, Daniel",
              "salary": 7300
            },
            {
              "dg_id": 21554,
              "name": "Poston, J.T.",
              "salary": 7200
            },
            {
              "dg_id": 8825,
              "name": "Harman, Brian",
              "salary": 7000
            },
            {
              "dg_id": 23475,
              "name": "Novak, Andrew",
              "salary": 6700
            }
          ],
          "actual_total": 491.0,
          "delta_pct": 3.61,
          "verdict": "top_1_pct"
        },
        {
          "lineup_id": "C4",
          "kind": "Core",
          "title": "Elite Chalk No-Scheffler",
          "label": "Core #4 \u2014 Elite Chalk No-Scheffler",
          "salary": 49800,
          "proj_total": 462.5,
          "players": [
            {
              "dg_id": 17646,
              "name": "Fitzpatrick, Matt",
              "salary": 10000
            },
            {
              "dg_id": 14578,
              "name": "Henley, Russell",
              "salary": 9600
            },
            {
              "dg_id": 15466,
              "name": "Cantlay, Patrick",
              "salary": 9200
            },
            {
              "dg_id": 10419,
              "name": "Noren, Alex",
              "salary": 7100
            },
            {
              "dg_id": 21554,
              "name": "Poston, J.T.",
              "salary": 7200
            },
            {
              "dg_id": 23475,
              "name": "Novak, Andrew",
              "salary": 6700
            }
          ],
          "actual_total": 512.5,
          "delta_pct": 10.81,
          "verdict": "top_001_pct"
        },
        {
          "lineup_id": "C5",
          "kind": "Core",
          "title": "Henley/Cantlay/McNealy Specialist Core",
          "label": "Core #5 \u2014 Henley/Cantlay/McNealy Specialist Core",
          "salary": 48300,
          "proj_total": 445.5,
          "players": [
            {
              "dg_id": 14578,
              "name": "Henley, Russell",
              "salary": 9600
            },
            {
              "dg_id": 15466,
              "name": "Cantlay, Patrick",
              "salary": 9200
            },
            {
              "dg_id": 18634,
              "name": "McNealy, Maverick",
              "salary": 8500
            },
            {
              "dg_id": 17606,
              "name": "Berger, Daniel",
              "salary": 7300
            },
            {
              "dg_id": 17576,
              "name": "Conners, Corey",
              "salary": 7000
            },
            {
              "dg_id": 23475,
              "name": "Novak, Andrew",
              "salary": 6700
            }
          ],
          "actual_total": 467.0,
          "delta_pct": 4.83,
          "verdict": "top_1_pct"
        },
        {
          "lineup_id": "L1",
          "kind": "Leverage",
          "title": "Scheffler/Cantlay + Contrarians",
          "label": "Leverage #1 \u2014 Scheffler/Cantlay + Contrarians",
          "salary": 50000,
          "proj_total": 475.2,
          "players": [
            {
              "dg_id": 18417,
              "name": "Scheffler, Scottie",
              "salary": 13500
            },
            {
              "dg_id": 15466,
              "name": "Cantlay, Patrick",
              "salary": 9200
            },
            {
              "dg_id": 10419,
              "name": "Noren, Alex",
              "salary": 7100
            },
            {
              "dg_id": 23475,
              "name": "Novak, Andrew",
              "salary": 6700
            },
            {
              "dg_id": 17488,
              "name": "Im, Sungjae",
              "salary": 6700
            },
            {
              "dg_id": 28635,
              "name": "McCarty, Matt",
              "salary": 6800
            }
          ],
          "actual_total": 513.0,
          "delta_pct": 7.95,
          "verdict": "top_001_pct"
        },
        {
          "lineup_id": "L2",
          "kind": "Leverage",
          "title": "Scheffler + Thomas Pivot",
          "label": "Leverage #2 \u2014 Scheffler + Thomas Pivot",
          "salary": 49800,
          "proj_total": 472.9,
          "players": [
            {
              "dg_id": 18417,
              "name": "Scheffler, Scottie",
              "salary": 13500
            },
            {
              "dg_id": 14139,
              "name": "Thomas, Justin",
              "salary": 8300
            },
            {
              "dg_id": 10419,
              "name": "Noren, Alex",
              "salary": 7100
            },
            {
              "dg_id": 21554,
              "name": "Poston, J.T.",
              "salary": 7200
            },
            {
              "dg_id": 8825,
              "name": "Harman, Brian",
              "salary": 7000
            },
            {
              "dg_id": 23475,
              "name": "Novak, Andrew",
              "salary": 6700
            }
          ],
          "actual_total": 482.5,
          "delta_pct": 2.03,
          "verdict": "top_1_pct"
        },
        {
          "lineup_id": "L3",
          "kind": "Leverage",
          "title": "No Scheffler, Fitzpatrick Stack",
          "label": "Leverage #3 \u2014 No Scheffler, Fitzpatrick Stack",
          "salary": 49200,
          "proj_total": 441.9,
          "players": [
            {
              "dg_id": 17646,
              "name": "Fitzpatrick, Matt",
              "salary": 10000
            },
            {
              "dg_id": 15466,
              "name": "Cantlay, Patrick",
              "salary": 9200
            },
            {
              "dg_id": 18634,
              "name": "McNealy, Maverick",
              "salary": 8500
            },
            {
              "dg_id": 17606,
              "name": "Berger, Daniel",
              "salary": 7300
            },
            {
              "dg_id": 21554,
              "name": "Poston, J.T.",
              "salary": 7200
            },
            {
              "dg_id": 17576,
              "name": "Conners, Corey",
              "salary": 7000
            }
          ],
          "actual_total": 505.0,
          "delta_pct": 14.28,
          "verdict": "top_001_pct"
        },
        {
          "lineup_id": "G1",
          "kind": "GPP",
          "title": "Scheffler + Thomas + Value Trio",
          "label": "GPP #1 \u2014 Scheffler + Thomas + Value Trio",
          "salary": 49700,
          "proj_total": 461.4,
          "players": [
            {
              "dg_id": 18417,
              "name": "Scheffler, Scottie",
              "salary": 13500
            },
            {
              "dg_id": 14139,
              "name": "Thomas, Justin",
              "salary": 8300
            },
            {
              "dg_id": 17606,
              "name": "Berger, Daniel",
              "salary": 7300
            },
            {
              "dg_id": 21554,
              "name": "Poston, J.T.",
              "salary": 7200
            },
            {
              "dg_id": 23475,
              "name": "Novak, Andrew",
              "salary": 6700
            },
            {
              "dg_id": 17488,
              "name": "Im, Sungjae",
              "salary": 6700
            }
          ],
          "actual_total": 469.5,
          "delta_pct": 1.76,
          "verdict": "top_1_pct"
        },
        {
          "lineup_id": "G2",
          "kind": "GPP",
          "title": "Specialist Upside Stack",
          "label": "GPP #2 \u2014 Specialist Upside Stack",
          "salary": 48600,
          "proj_total": 454.2,
          "players": [
            {
              "dg_id": 14578,
              "name": "Henley, Russell",
              "salary": 9600
            },
            {
              "dg_id": 15466,
              "name": "Cantlay, Patrick",
              "salary": 9200
            },
            {
              "dg_id": 18634,
              "name": "McNealy, Maverick",
              "salary": 8500
            },
            {
              "dg_id": 10419,
              "name": "Noren, Alex",
              "salary": 7100
            },
            {
              "dg_id": 21554,
              "name": "Poston, J.T.",
              "salary": 7200
            },
            {
              "dg_id": 17576,
              "name": "Conners, Corey",
              "salary": 7000
            }
          ],
          "actual_total": 444.5,
          "delta_pct": -2.14,
          "verdict": "top_1_pct"
        },
        {
          "lineup_id": "G3",
          "kind": "GPP",
          "title": "Fitzpatrick/Henley + Straka/Noren",
          "label": "GPP #3 \u2014 Fitzpatrick/Henley + Straka/Noren",
          "salary": 48600,
          "proj_total": 451.0,
          "players": [
            {
              "dg_id": 17646,
              "name": "Fitzpatrick, Matt",
              "salary": 10000
            },
            {
              "dg_id": 14578,
              "name": "Henley, Russell",
              "salary": 9600
            },
            {
              "dg_id": 17511,
              "name": "Straka, Sepp",
              "salary": 7900
            },
            {
              "dg_id": 10419,
              "name": "Noren, Alex",
              "salary": 7100
            },
            {
              "dg_id": 17606,
              "name": "Berger, Daniel",
              "salary": 7300
            },
            {
              "dg_id": 23475,
              "name": "Novak, Andrew",
              "salary": 6700
            }
          ],
          "actual_total": 498.5,
          "delta_pct": 10.53,
          "verdict": "top_1_pct"
        },
        {
          "lineup_id": "G4",
          "kind": "GPP",
          "title": "Fitzpatrick/McNealy + Spieth Leverage",
          "label": "GPP #4 \u2014 Fitzpatrick/McNealy + Spieth Leverage",
          "salary": 48400,
          "proj_total": 435.2,
          "players": [
            {
              "dg_id": 17646,
              "name": "Fitzpatrick, Matt",
              "salary": 10000
            },
            {
              "dg_id": 18634,
              "name": "McNealy, Maverick",
              "salary": 8500
            },
            {
              "dg_id": 14636,
              "name": "Spieth, Jordan",
              "salary": 8800
            },
            {
              "dg_id": 10419,
              "name": "Noren, Alex",
              "salary": 7100
            },
            {
              "dg_id": 17606,
              "name": "Berger, Daniel",
              "salary": 7300
            },
            {
              "dg_id": 17488,
              "name": "Im, Sungjae",
              "salary": 6700
            }
          ],
          "actual_total": 489.5,
          "delta_pct": 12.48,
          "verdict": "top_1_pct"
        }
      ],
      "hindsight_best": {
        "total": 551.5,
        "salary": 46600,
        "n_players": 6
      },
      "vs_hindsight_pts_left": 38.5,
      "field_wide_optimal": {
        "total": 621.5,
        "salary": 50000,
        "players": [
          {
            "dg_id": 17646,
            "name": "Fitzpatrick, Matt",
            "salary": 10000,
            "total_pts": 130.0,
            "ownership": 0.1764
          },
          {
            "dg_id": 14609,
            "name": "Kim, Si Woo",
            "salary": 8900,
            "total_pts": 106.5,
            "ownership": 0.1263
          },
          {
            "dg_id": 22085,
            "name": "Morikawa, Collin",
            "salary": 9300,
            "total_pts": 101.5,
            "ownership": 0.1105
          },
          {
            "dg_id": 14577,
            "name": "English, Harris",
            "salary": 7900,
            "total_pts": 97.0,
            "ownership": 0.0506
          },
          {
            "dg_id": 21891,
            "name": "Kitayama, Kurt",
            "salary": 7100,
            "total_pts": 93.5,
            "ownership": 0.0538
          },
          {
            "dg_id": 12577,
            "name": "Woodland, Gary",
            "salary": 6800,
            "total_pts": 93.0,
            "ownership": 0.049699999999999994
          }
        ]
      },
      "vs_field_optimal_pts_left": 108.5,
      "capture_rate_pct": 82.54
    },
    {
      "event": "PGA Championship",
      "event_id": 33,
      "year": 2026,
      "completed": "2026-05-17",
      "graded_at_utc": "2026-05-25T13:36:37Z",
      "thresholds": {
        "cash_line": 340,
        "top_1_pct": 410,
        "top_001_pct": 500
      },
      "portfolio": {
        "n_lineups": 10,
        "avg_proj": 307.31,
        "avg_actual": 273.55,
        "n_below_cash": 9,
        "n_cash": 1,
        "n_top_1pct": 0,
        "n_top_001pct": 0,
        "best_lineup_id": "L2",
        "best_lineup_actual": 345.5,
        "worst_lineup_id": "L3",
        "worst_lineup_actual": 238.0,
        "delta_pct": -10.99
      },
      "lineups": [
        {
          "lineup_id": "C1",
          "kind": "Core",
          "title": "Core build #1",
          "label": "Core #1",
          "salary": 50000,
          "proj_total": 330.91,
          "players": [
            {
              "dg_id": 18417,
              "name": "Scheffler, Scottie",
              "salary": 13900
            },
            {
              "dg_id": 10091,
              "name": "McIlroy, Rory",
              "salary": 12400
            },
            {
              "dg_id": 12965,
              "name": "Fowler, Rickie",
              "salary": 7400
            },
            {
              "dg_id": 27194,
              "name": "Hall, Harry",
              "salary": 5800
            },
            {
              "dg_id": 14704,
              "name": "Putnam, Andrew",
              "salary": 5400
            },
            {
              "dg_id": 7301,
              "name": "Dufner, Jason",
              "salary": 5100
            }
          ],
          "actual_total": 275.5,
          "delta_pct": -16.74,
          "verdict": "below_cash"
        },
        {
          "lineup_id": "C2",
          "kind": "Core",
          "title": "Core build #2",
          "label": "Core #2",
          "salary": 50000,
          "proj_total": 314.02,
          "players": [
            {
              "dg_id": 18417,
              "name": "Scheffler, Scottie",
              "salary": 13900
            },
            {
              "dg_id": 26651,
              "name": "Young, Cameron",
              "salary": 10200
            },
            {
              "dg_id": 19895,
              "name": "Schauffele, Xander",
              "salary": 10100
            },
            {
              "dg_id": 27194,
              "name": "Hall, Harry",
              "salary": 5800
            },
            {
              "dg_id": 25439,
              "name": "Kern, Ben",
              "salary": 5000
            },
            {
              "dg_id": 17617,
              "name": "Berg, Derek",
              "salary": 5000
            }
          ],
          "actual_total": 284.0,
          "delta_pct": -9.56,
          "verdict": "below_cash"
        },
        {
          "lineup_id": "C3",
          "kind": "Core",
          "title": "Core build #3",
          "label": "Core #3",
          "salary": 42000,
          "proj_total": 318.26,
          "players": [
            {
              "dg_id": 18417,
              "name": "Scheffler, Scottie",
              "salary": 13900
            },
            {
              "dg_id": 27194,
              "name": "Hall, Harry",
              "salary": 5800
            },
            {
              "dg_id": 14502,
              "name": "Cauley, Bud",
              "salary": 5700
            },
            {
              "dg_id": 20706,
              "name": "Wallace, Matt",
              "salary": 5600
            },
            {
              "dg_id": 7399,
              "name": "Glover, Lucas",
              "salary": 5600
            },
            {
              "dg_id": 14704,
              "name": "Putnam, Andrew",
              "salary": 5400
            }
          ],
          "actual_total": 252.0,
          "delta_pct": -20.82,
          "verdict": "below_cash"
        },
        {
          "lineup_id": "C4",
          "kind": "Core",
          "title": "Core build #4",
          "label": "Core #4",
          "salary": 50000,
          "proj_total": 297.68,
          "players": [
            {
              "dg_id": 18417,
              "name": "Scheffler, Scottie",
              "salary": 13900
            },
            {
              "dg_id": 10091,
              "name": "McIlroy, Rory",
              "salary": 12400
            },
            {
              "dg_id": 16841,
              "name": "Lee, Min Woo",
              "salary": 7500
            },
            {
              "dg_id": 14181,
              "name": "Detry, Thomas",
              "salary": 6100
            },
            {
              "dg_id": 7301,
              "name": "Dufner, Jason",
              "salary": 5100
            },
            {
              "dg_id": 25439,
              "name": "Kern, Ben",
              "salary": 5000
            }
          ],
          "actual_total": 293.0,
          "delta_pct": -1.57,
          "verdict": "below_cash"
        },
        {
          "lineup_id": "C5",
          "kind": "Core",
          "title": "Core build #5",
          "label": "Core #5",
          "salary": 50000,
          "proj_total": 309.73,
          "players": [
            {
              "dg_id": 18417,
              "name": "Scheffler, Scottie",
              "salary": 13900
            },
            {
              "dg_id": 10091,
              "name": "McIlroy, Rory",
              "salary": 12400
            },
            {
              "dg_id": 21891,
              "name": "Kitayama, Kurt",
              "salary": 7300
            },
            {
              "dg_id": 14181,
              "name": "Detry, Thomas",
              "salary": 6100
            },
            {
              "dg_id": 22985,
              "name": "Smotherman, Austin",
              "salary": 5300
            },
            {
              "dg_id": 17617,
              "name": "Berg, Derek",
              "salary": 5000
            }
          ],
          "actual_total": 266.5,
          "delta_pct": -13.96,
          "verdict": "below_cash"
        },
        {
          "lineup_id": "C6",
          "kind": "Core",
          "title": "Core build #6",
          "label": "Core #6",
          "salary": 39800,
          "proj_total": 308.92,
          "players": [
            {
              "dg_id": 26651,
              "name": "Young, Cameron",
              "salary": 10200
            },
            {
              "dg_id": 14577,
              "name": "English, Harris",
              "salary": 7200
            },
            {
              "dg_id": 27194,
              "name": "Hall, Harry",
              "salary": 5800
            },
            {
              "dg_id": 20706,
              "name": "Wallace, Matt",
              "salary": 5600
            },
            {
              "dg_id": 7399,
              "name": "Glover, Lucas",
              "salary": 5600
            },
            {
              "dg_id": 14704,
              "name": "Putnam, Andrew",
              "salary": 5400
            }
          ],
          "actual_total": 273.0,
          "delta_pct": -11.63,
          "verdict": "below_cash"
        },
        {
          "lineup_id": "L1",
          "kind": "Leverage",
          "title": "Leverage build #1",
          "label": "Leverage #1",
          "salary": 44300,
          "proj_total": 263.43,
          "players": [
            {
              "dg_id": 19895,
              "name": "Schauffele, Xander",
              "salary": 10100
            },
            {
              "dg_id": 17646,
              "name": "Fitzpatrick, Matt",
              "salary": 10000
            },
            {
              "dg_id": 22833,
              "name": "Echavarria, Nico",
              "salary": 6600
            },
            {
              "dg_id": 27819,
              "name": "Castillo, Ricky",
              "salary": 6400
            },
            {
              "dg_id": 28469,
              "name": "Highsmith, Joe",
              "salary": 5800
            },
            {
              "dg_id": 20766,
              "name": "Brown, Dan",
              "salary": 5400
            }
          ],
          "actual_total": 248.5,
          "delta_pct": -5.67,
          "verdict": "below_cash"
        },
        {
          "lineup_id": "L2",
          "kind": "Leverage",
          "title": "Leverage build #2",
          "label": "Leverage #2",
          "salary": 50000,
          "proj_total": 317.79,
          "players": [
            {
              "dg_id": 19895,
              "name": "Schauffele, Xander",
              "salary": 10100
            },
            {
              "dg_id": 17646,
              "name": "Fitzpatrick, Matt",
              "salary": 10000
            },
            {
              "dg_id": 23950,
              "name": "Aberg, Ludvig",
              "salary": 9800
            },
            {
              "dg_id": 12294,
              "name": "Fleetwood, Tommy",
              "salary": 9700
            },
            {
              "dg_id": 14704,
              "name": "Putnam, Andrew",
              "salary": 5400
            },
            {
              "dg_id": 25439,
              "name": "Kern, Ben",
              "salary": 5000
            }
          ],
          "actual_total": 345.5,
          "delta_pct": 8.72,
          "verdict": "cash"
        },
        {
          "lineup_id": "L3",
          "kind": "Leverage",
          "title": "Leverage build #3",
          "label": "Leverage #3",
          "salary": 41800,
          "proj_total": 305.56,
          "players": [
            {
              "dg_id": 23950,
              "name": "Aberg, Ludvig",
              "salary": 9800
            },
            {
              "dg_id": 18841,
              "name": "Hovland, Viktor",
              "salary": 9600
            },
            {
              "dg_id": 27194,
              "name": "Hall, Harry",
              "salary": 5800
            },
            {
              "dg_id": 20706,
              "name": "Wallace, Matt",
              "salary": 5600
            },
            {
              "dg_id": 7399,
              "name": "Glover, Lucas",
              "salary": 5600
            },
            {
              "dg_id": 14704,
              "name": "Putnam, Andrew",
              "salary": 5400
            }
          ],
          "actual_total": 238.0,
          "delta_pct": -22.11,
          "verdict": "below_cash"
        },
        {
          "lineup_id": "C7",
          "kind": "Core",
          "title": "Core build #7",
          "label": "Core #7",
          "salary": 40500,
          "proj_total": 306.78,
          "players": [
            {
              "dg_id": 10091,
              "name": "McIlroy, Rory",
              "salary": 12400
            },
            {
              "dg_id": 27194,
              "name": "Hall, Harry",
              "salary": 5800
            },
            {
              "dg_id": 14502,
              "name": "Cauley, Bud",
              "salary": 5700
            },
            {
              "dg_id": 20706,
              "name": "Wallace, Matt",
              "salary": 5600
            },
            {
              "dg_id": 7399,
              "name": "Glover, Lucas",
              "salary": 5600
            },
            {
              "dg_id": 14704,
              "name": "Putnam, Andrew",
              "salary": 5400
            }
          ],
          "actual_total": 259.5,
          "delta_pct": -15.41,
          "verdict": "below_cash"
        }
      ],
      "hindsight_best": {
        "total": 438.0,
        "salary": 49800,
        "n_players": 6
      },
      "vs_hindsight_pts_left": 92.5,
      "field_wide_optimal": {
        "total": 550.0,
        "salary": 49700,
        "players": [
          {
            "dg_id": 18554,
            "name": "Rai, Aaron",
            "salary": 6700,
            "total_pts": 117.0,
            "ownership": 0.026600000000000002
          },
          {
            "dg_id": 18474,
            "name": "Smalley, Alex",
            "salary": 6100,
            "total_pts": 96.5,
            "ownership": 0.10529999999999999
          },
          {
            "dg_id": 19195,
            "name": "Rahm, Jon",
            "salary": 10400,
            "total_pts": 87.0,
            "ownership": 0.1348
          },
          {
            "dg_id": 23950,
            "name": "Aberg, Ludvig",
            "salary": 9800,
            "total_pts": 84.0,
            "ownership": 0.23120000000000002
          },
          {
            "dg_id": 14139,
            "name": "Thomas, Justin",
            "salary": 9400,
            "total_pts": 84.0,
            "ownership": 0.046799999999999994
          },
          {
            "dg_id": 21891,
            "name": "Kitayama, Kurt",
            "salary": 7300,
            "total_pts": 81.5,
            "ownership": 0.09210000000000002
          }
        ]
      },
      "vs_field_optimal_pts_left": 204.5,
      "capture_rate_pct": 62.82
    },
    {
      "event": "Truist Championship",
      "event_id": 480,
      "year": 2026,
      "completed": "2026-05-10",
      "graded_at_utc": "2026-05-11T13:37:52Z",
      "thresholds": {
        "cash_line": 340,
        "top_1_pct": 410,
        "top_001_pct": 500
      },
      "portfolio": {
        "n_lineups": 11,
        "avg_proj": 350.13,
        "avg_actual": 423.14,
        "n_below_cash": 0,
        "n_cash": 4,
        "n_top_1pct": 7,
        "n_top_001pct": 0,
        "best_lineup_id": "L3",
        "best_lineup_actual": 484.0,
        "worst_lineup_id": "C7",
        "worst_lineup_actual": 360.0,
        "delta_pct": 20.85
      },
      "lineups": [
        {
          "lineup_id": "C1",
          "kind": "Core",
          "title": "Core build #1",
          "label": "Core #1",
          "salary": 50000,
          "proj_total": 347.52,
          "players": [
            {
              "dg_id": 10091,
              "name": "McIlroy, Rory",
              "salary": 11700
            },
            {
              "dg_id": 26651,
              "name": "Young, Cameron",
              "salary": 10100
            },
            {
              "dg_id": 19895,
              "name": "Schauffele, Xander",
              "salary": 10000
            },
            {
              "dg_id": 7399,
              "name": "Glover, Lucas",
              "salary": 6200
            },
            {
              "dg_id": 13508,
              "name": "Vegas, Jhonattan",
              "salary": 6000
            },
            {
              "dg_id": 24956,
              "name": "Blanchet, Chandler",
              "salary": 6000
            }
          ],
          "actual_total": 400.0,
          "delta_pct": 15.1,
          "verdict": "cash"
        },
        {
          "lineup_id": "C2",
          "kind": "Core",
          "title": "Core build #2",
          "label": "Core #2",
          "salary": 50000,
          "proj_total": 340.29,
          "players": [
            {
              "dg_id": 10091,
              "name": "McIlroy, Rory",
              "salary": 11700
            },
            {
              "dg_id": 19895,
              "name": "Schauffele, Xander",
              "salary": 10000
            },
            {
              "dg_id": 17646,
              "name": "Fitzpatrick, Matt",
              "salary": 9900
            },
            {
              "dg_id": 17543,
              "name": "Kim, Michael",
              "salary": 6400
            },
            {
              "dg_id": 13508,
              "name": "Vegas, Jhonattan",
              "salary": 6000
            },
            {
              "dg_id": 24956,
              "name": "Blanchet, Chandler",
              "salary": 6000
            }
          ],
          "actual_total": 372.0,
          "delta_pct": 9.32,
          "verdict": "cash"
        },
        {
          "lineup_id": "C3",
          "kind": "Core",
          "title": "Core build #3",
          "label": "Core #3",
          "salary": 47300,
          "proj_total": 357.16,
          "players": [
            {
              "dg_id": 10091,
              "name": "McIlroy, Rory",
              "salary": 11700
            },
            {
              "dg_id": 17536,
              "name": "Spaun, J.J.",
              "salary": 7900
            },
            {
              "dg_id": 23602,
              "name": "Hojgaard, Nicolai",
              "salary": 7800
            },
            {
              "dg_id": 22760,
              "name": "Hisatsune, Ryo",
              "salary": 6700
            },
            {
              "dg_id": 11889,
              "name": "Fox, Ryan",
              "salary": 6600
            },
            {
              "dg_id": 17780,
              "name": "Pendrith, Taylor",
              "salary": 6600
            }
          ],
          "actual_total": 443.0,
          "delta_pct": 24.03,
          "verdict": "top_1_pct"
        },
        {
          "lineup_id": "C4",
          "kind": "Core",
          "title": "Core build #4",
          "label": "Core #4",
          "salary": 50000,
          "proj_total": 369.15,
          "players": [
            {
              "dg_id": 10091,
              "name": "McIlroy, Rory",
              "salary": 11700
            },
            {
              "dg_id": 19895,
              "name": "Schauffele, Xander",
              "salary": 10000
            },
            {
              "dg_id": 17536,
              "name": "Spaun, J.J.",
              "salary": 7900
            },
            {
              "dg_id": 23602,
              "name": "Hojgaard, Nicolai",
              "salary": 7800
            },
            {
              "dg_id": 11889,
              "name": "Fox, Ryan",
              "salary": 6600
            },
            {
              "dg_id": 13508,
              "name": "Vegas, Jhonattan",
              "salary": 6000
            }
          ],
          "actual_total": 431.0,
          "delta_pct": 16.75,
          "verdict": "top_1_pct"
        },
        {
          "lineup_id": "C5",
          "kind": "Core",
          "title": "Core build #5",
          "label": "Core #5",
          "salary": 50000,
          "proj_total": 350.59,
          "players": [
            {
              "dg_id": 10091,
              "name": "McIlroy, Rory",
              "salary": 11700
            },
            {
              "dg_id": 19895,
              "name": "Schauffele, Xander",
              "salary": 10000
            },
            {
              "dg_id": 18841,
              "name": "Hovland, Viktor",
              "salary": 8400
            },
            {
              "dg_id": 17536,
              "name": "Spaun, J.J.",
              "salary": 7900
            },
            {
              "dg_id": 13508,
              "name": "Vegas, Jhonattan",
              "salary": 6000
            },
            {
              "dg_id": 24956,
              "name": "Blanchet, Chandler",
              "salary": 6000
            }
          ],
          "actual_total": 415.0,
          "delta_pct": 18.37,
          "verdict": "top_1_pct"
        },
        {
          "lineup_id": "C6",
          "kind": "Core",
          "title": "Core build #6",
          "label": "Core #6",
          "salary": 48700,
          "proj_total": 367.28,
          "players": [
            {
              "dg_id": 26651,
              "name": "Young, Cameron",
              "salary": 10100
            },
            {
              "dg_id": 23602,
              "name": "Hojgaard, Nicolai",
              "salary": 7800
            },
            {
              "dg_id": 18474,
              "name": "Smalley, Alex",
              "salary": 7500
            },
            {
              "dg_id": 22760,
              "name": "Hisatsune, Ryo",
              "salary": 6700
            },
            {
              "dg_id": 11889,
              "name": "Fox, Ryan",
              "salary": 6600
            },
            {
              "dg_id": 19895,
              "name": "Schauffele, Xander",
              "salary": 10000
            }
          ],
          "actual_total": 422.5,
          "delta_pct": 15.03,
          "verdict": "top_1_pct"
        },
        {
          "lineup_id": "L1",
          "kind": "Leverage",
          "title": "Leverage build #1",
          "label": "Leverage #1",
          "salary": 46400,
          "proj_total": 314.79,
          "players": [
            {
              "dg_id": 12294,
              "name": "Fleetwood, Tommy",
              "salary": 9800
            },
            {
              "dg_id": 13562,
              "name": "Matsuyama, Hideki",
              "salary": 8800
            },
            {
              "dg_id": 22760,
              "name": "Hisatsune, Ryo",
              "salary": 6700
            },
            {
              "dg_id": 20706,
              "name": "Wallace, Matt",
              "salary": 6600
            },
            {
              "dg_id": 27194,
              "name": "Hall, Harry",
              "salary": 7200
            },
            {
              "dg_id": 29767,
              "name": "Gerard, Ryan",
              "salary": 7300
            }
          ],
          "actual_total": 399.5,
          "delta_pct": 26.91,
          "verdict": "cash"
        },
        {
          "lineup_id": "L2",
          "kind": "Leverage",
          "title": "Leverage build #2",
          "label": "Leverage #2",
          "salary": 49900,
          "proj_total": 348.1,
          "players": [
            {
              "dg_id": 12294,
              "name": "Fleetwood, Tommy",
              "salary": 9800
            },
            {
              "dg_id": 14609,
              "name": "Kim, Si Woo",
              "salary": 9400
            },
            {
              "dg_id": 18841,
              "name": "Hovland, Viktor",
              "salary": 8400
            },
            {
              "dg_id": 17536,
              "name": "Spaun, J.J.",
              "salary": 7900
            },
            {
              "dg_id": 23602,
              "name": "Hojgaard, Nicolai",
              "salary": 7800
            },
            {
              "dg_id": 11889,
              "name": "Fox, Ryan",
              "salary": 6600
            }
          ],
          "actual_total": 470.0,
          "delta_pct": 35.02,
          "verdict": "top_1_pct"
        },
        {
          "lineup_id": "L3",
          "kind": "Leverage",
          "title": "Leverage build #3",
          "label": "Leverage #3",
          "salary": 48600,
          "proj_total": 351.89,
          "players": [
            {
              "dg_id": 14609,
              "name": "Kim, Si Woo",
              "salary": 9400
            },
            {
              "dg_id": 18841,
              "name": "Hovland, Viktor",
              "salary": 8400
            },
            {
              "dg_id": 17536,
              "name": "Spaun, J.J.",
              "salary": 7900
            },
            {
              "dg_id": 23602,
              "name": "Hojgaard, Nicolai",
              "salary": 7800
            },
            {
              "dg_id": 14139,
              "name": "Thomas, Justin",
              "salary": 7600
            },
            {
              "dg_id": 18474,
              "name": "Smalley, Alex",
              "salary": 7500
            }
          ],
          "actual_total": 484.0,
          "delta_pct": 37.54,
          "verdict": "top_1_pct"
        },
        {
          "lineup_id": "L4",
          "kind": "Leverage",
          "title": "Leverage build #4",
          "label": "Leverage #4",
          "salary": 47000,
          "proj_total": 341.24,
          "players": [
            {
              "dg_id": 23602,
              "name": "Hojgaard, Nicolai",
              "salary": 7800
            },
            {
              "dg_id": 18841,
              "name": "Hovland, Viktor",
              "salary": 8400
            },
            {
              "dg_id": 13562,
              "name": "Matsuyama, Hideki",
              "salary": 8800
            },
            {
              "dg_id": 22760,
              "name": "Hisatsune, Ryo",
              "salary": 6700
            },
            {
              "dg_id": 17536,
              "name": "Spaun, J.J.",
              "salary": 7900
            },
            {
              "dg_id": 13872,
              "name": "Bradley, Keegan",
              "salary": 7400
            }
          ],
          "actual_total": 457.5,
          "delta_pct": 34.07,
          "verdict": "top_1_pct"
        },
        {
          "lineup_id": "C7",
          "kind": "Core",
          "title": "Core build #7",
          "label": "Core #7",
          "salary": 48500,
          "proj_total": 363.37,
          "players": [
            {
              "dg_id": 10091,
              "name": "McIlroy, Rory",
              "salary": 11700
            },
            {
              "dg_id": 17606,
              "name": "Berger, Daniel",
              "salary": 6900
            },
            {
              "dg_id": 22760,
              "name": "Hisatsune, Ryo",
              "salary": 6700
            },
            {
              "dg_id": 11889,
              "name": "Fox, Ryan",
              "salary": 6600
            },
            {
              "dg_id": 17780,
              "name": "Pendrith, Taylor",
              "salary": 6600
            },
            {
              "dg_id": 19895,
              "name": "Schauffele, Xander",
              "salary": 10000
            }
          ],
          "actual_total": 360.0,
          "delta_pct": -0.93,
          "verdict": "cash"
        }
      ],
      "hindsight_best": {
        "total": 541.0,
        "salary": 47700,
        "n_players": 6
      },
      "vs_hindsight_pts_left": 57.0,
      "field_wide_optimal": {
        "total": 630.5,
        "salary": 46600,
        "players": [
          {
            "dg_id": 21407,
            "name": "Reitan, Kristoffer",
            "salary": 6900,
            "total_pts": 124.0,
            "ownership": 0.0771
          },
          {
            "dg_id": 23602,
            "name": "Hojgaard, Nicolai",
            "salary": 7800,
            "total_pts": 107.5,
            "ownership": 0.1437
          },
          {
            "dg_id": 12965,
            "name": "Fowler, Rickie",
            "salary": 9000,
            "total_pts": 105.0,
            "ownership": 0.0728
          },
          {
            "dg_id": 17488,
            "name": "Im, Sungjae",
            "salary": 6300,
            "total_pts": 101.0,
            "ownership": 0.0521
          },
          {
            "dg_id": 25362,
            "name": "Fitzpatrick, Alex",
            "salary": 6800,
            "total_pts": 98.0,
            "ownership": 0.10529999999999999
          },
          {
            "dg_id": 12294,
            "name": "Fleetwood, Tommy",
            "salary": 9800,
            "total_pts": 95.0,
            "ownership": 0.09910000000000001
          }
        ]
      },
      "vs_field_optimal_pts_left": 146.5,
      "capture_rate_pct": 76.76
    },
    {
      "event": "Cadillac Championship",
      "event_id": 556,
      "year": 2026,
      "completed": "2026-05-03",
      "graded_at_utc": "2026-05-04T13:38:21Z",
      "thresholds": {
        "cash_line": 340,
        "top_1_pct": 410,
        "top_001_pct": 500
      },
      "portfolio": {
        "n_lineups": 12,
        "avg_proj": 205.18,
        "avg_actual": 469.62,
        "n_below_cash": 0,
        "n_cash": 1,
        "n_top_1pct": 8,
        "n_top_001pct": 3,
        "best_lineup_id": "C5",
        "best_lineup_actual": 528.0,
        "worst_lineup_id": "L4",
        "worst_lineup_actual": 400.0,
        "delta_pct": 128.88
      },
      "lineups": [
        {
          "lineup_id": "C1",
          "kind": "Core",
          "title": "Core build #1",
          "label": "Core #1",
          "salary": 50000,
          "proj_total": 228.42,
          "players": [
            {
              "dg_id": 18417,
              "name": "Scheffler, Scottie",
              "salary": 13600
            },
            {
              "dg_id": 26651,
              "name": "Young, Cameron",
              "salary": 10200
            },
            {
              "dg_id": 23602,
              "name": "Hojgaard, Nicolai",
              "salary": 7800
            },
            {
              "dg_id": 17538,
              "name": "Homa, Max",
              "salary": 6400
            },
            {
              "dg_id": 7399,
              "name": "Glover, Lucas",
              "salary": 6000
            },
            {
              "dg_id": 15980,
              "name": "Lipsky, David",
              "salary": 6000
            }
          ],
          "actual_total": 512.5,
          "delta_pct": 124.37,
          "verdict": "top_001_pct"
        },
        {
          "lineup_id": "C2",
          "kind": "Core",
          "title": "Core build #2",
          "label": "Core #2",
          "salary": 50000,
          "proj_total": 202.17,
          "players": [
            {
              "dg_id": 18417,
              "name": "Scheffler, Scottie",
              "salary": 13600
            },
            {
              "dg_id": 22085,
              "name": "Morikawa, Collin",
              "salary": 9800
            },
            {
              "dg_id": 16841,
              "name": "Lee, Min Woo",
              "salary": 8600
            },
            {
              "dg_id": 7399,
              "name": "Glover, Lucas",
              "salary": 6000
            },
            {
              "dg_id": 15980,
              "name": "Lipsky, David",
              "salary": 6000
            },
            {
              "dg_id": 18628,
              "name": "Campbell, Brian",
              "salary": 6000
            }
          ],
          "actual_total": 428.5,
          "delta_pct": 111.95,
          "verdict": "top_1_pct"
        },
        {
          "lineup_id": "C3",
          "kind": "Core",
          "title": "Core build #3",
          "label": "Core #3",
          "salary": 47900,
          "proj_total": 247.5,
          "players": [
            {
              "dg_id": 18417,
              "name": "Scheffler, Scottie",
              "salary": 13600
            },
            {
              "dg_id": 29767,
              "name": "Gerard, Ryan",
              "salary": 7200
            },
            {
              "dg_id": 22760,
              "name": "Hisatsune, Ryo",
              "salary": 7000
            },
            {
              "dg_id": 18586,
              "name": "Smith, Jordan",
              "salary": 6800
            },
            {
              "dg_id": 28635,
              "name": "McCarty, Matt",
              "salary": 6800
            },
            {
              "dg_id": 23475,
              "name": "Novak, Andrew",
              "salary": 6500
            }
          ],
          "actual_total": 456.5,
          "delta_pct": 84.44,
          "verdict": "top_1_pct"
        },
        {
          "lineup_id": "C4",
          "kind": "Core",
          "title": "Core build #4",
          "label": "Core #4",
          "salary": 50000,
          "proj_total": 231.59,
          "players": [
            {
              "dg_id": 18417,
              "name": "Scheffler, Scottie",
              "salary": 13600
            },
            {
              "dg_id": 26651,
              "name": "Young, Cameron",
              "salary": 10200
            },
            {
              "dg_id": 23602,
              "name": "Hojgaard, Nicolai",
              "salary": 7800
            },
            {
              "dg_id": 27900,
              "name": "Potgieter, Aldrich",
              "salary": 6300
            },
            {
              "dg_id": 24956,
              "name": "Blanchet, Chandler",
              "salary": 6100
            },
            {
              "dg_id": 15980,
              "name": "Lipsky, David",
              "salary": 6000
            }
          ],
          "actual_total": 480.5,
          "delta_pct": 107.48,
          "verdict": "top_1_pct"
        },
        {
          "lineup_id": "C5",
          "kind": "Core",
          "title": "Core build #5",
          "label": "Core #5",
          "salary": 50000,
          "proj_total": 243.25,
          "players": [
            {
              "dg_id": 18417,
              "name": "Scheffler, Scottie",
              "salary": 13600
            },
            {
              "dg_id": 26651,
              "name": "Young, Cameron",
              "salary": 10200
            },
            {
              "dg_id": 29767,
              "name": "Gerard, Ryan",
              "salary": 7200
            },
            {
              "dg_id": 18586,
              "name": "Smith, Jordan",
              "salary": 6800
            },
            {
              "dg_id": 23465,
              "name": "Greyserman, Max",
              "salary": 6200
            },
            {
              "dg_id": 7399,
              "name": "Glover, Lucas",
              "salary": 6000
            }
          ],
          "actual_total": 528.0,
          "delta_pct": 117.06,
          "verdict": "top_001_pct"
        },
        {
          "lineup_id": "C6",
          "kind": "Core",
          "title": "Core build #6",
          "label": "Core #6",
          "salary": 50000,
          "proj_total": 231.96,
          "players": [
            {
              "dg_id": 18417,
              "name": "Scheffler, Scottie",
              "salary": 13600
            },
            {
              "dg_id": 26651,
              "name": "Young, Cameron",
              "salary": 10200
            },
            {
              "dg_id": 29767,
              "name": "Gerard, Ryan",
              "salary": 7200
            },
            {
              "dg_id": 22760,
              "name": "Hisatsune, Ryo",
              "salary": 7000
            },
            {
              "dg_id": 15980,
              "name": "Lipsky, David",
              "salary": 6000
            },
            {
              "dg_id": 7399,
              "name": "Glover, Lucas",
              "salary": 6000
            }
          ],
          "actual_total": 507.5,
          "delta_pct": 118.79,
          "verdict": "top_001_pct"
        },
        {
          "lineup_id": "C7",
          "kind": "Core",
          "title": "Core build #7",
          "label": "Core #7",
          "salary": 48100,
          "proj_total": 189.12,
          "players": [
            {
              "dg_id": 22085,
              "name": "Morikawa, Collin",
              "salary": 9800
            },
            {
              "dg_id": 29767,
              "name": "Gerard, Ryan",
              "salary": 7200
            },
            {
              "dg_id": 18474,
              "name": "Smalley, Alex",
              "salary": 7100
            },
            {
              "dg_id": 22760,
              "name": "Hisatsune, Ryo",
              "salary": 7000
            },
            {
              "dg_id": 18586,
              "name": "Smith, Jordan",
              "salary": 6800
            },
            {
              "dg_id": 26651,
              "name": "Young, Cameron",
              "salary": 10200
            }
          ],
          "actual_total": 474.5,
          "delta_pct": 150.9,
          "verdict": "top_1_pct"
        },
        {
          "lineup_id": "L1",
          "kind": "Leverage",
          "title": "Leverage build #1",
          "label": "Leverage #1",
          "salary": 47500,
          "proj_total": 132.51,
          "players": [
            {
              "dg_id": 14609,
              "name": "Kim, Si Woo",
              "salary": 9200
            },
            {
              "dg_id": 16841,
              "name": "Lee, Min Woo",
              "salary": 8600
            },
            {
              "dg_id": 14704,
              "name": "Putnam, Andrew",
              "salary": 6300
            },
            {
              "dg_id": 27194,
              "name": "Hall, Harry",
              "salary": 7400
            },
            {
              "dg_id": 14509,
              "name": "Dahmen, Joel",
              "salary": 6100
            },
            {
              "dg_id": 14578,
              "name": "Henley, Russell",
              "salary": 9900
            }
          ],
          "actual_total": 440.0,
          "delta_pct": 232.05,
          "verdict": "top_1_pct"
        },
        {
          "lineup_id": "L2",
          "kind": "Leverage",
          "title": "Leverage build #2",
          "label": "Leverage #2",
          "salary": 49900,
          "proj_total": 221.7,
          "players": [
            {
              "dg_id": 12294,
              "name": "Fleetwood, Tommy",
              "salary": 9700
            },
            {
              "dg_id": 14609,
              "name": "Kim, Si Woo",
              "salary": 9200
            },
            {
              "dg_id": 16841,
              "name": "Lee, Min Woo",
              "salary": 8600
            },
            {
              "dg_id": 29433,
              "name": "Bridgeman, Jacob",
              "salary": 8300
            },
            {
              "dg_id": 23602,
              "name": "Hojgaard, Nicolai",
              "salary": 7800
            },
            {
              "dg_id": 27900,
              "name": "Potgieter, Aldrich",
              "salary": 6300
            }
          ],
          "actual_total": 459.0,
          "delta_pct": 107.04,
          "verdict": "top_1_pct"
        },
        {
          "lineup_id": "L3",
          "kind": "Leverage",
          "title": "Leverage build #3",
          "label": "Leverage #3",
          "salary": 49900,
          "proj_total": 234.35,
          "players": [
            {
              "dg_id": 14609,
              "name": "Kim, Si Woo",
              "salary": 9200
            },
            {
              "dg_id": 18634,
              "name": "McNealy, Maverick",
              "salary": 8800
            },
            {
              "dg_id": 16841,
              "name": "Lee, Min Woo",
              "salary": 8600
            },
            {
              "dg_id": 29433,
              "name": "Bridgeman, Jacob",
              "salary": 8300
            },
            {
              "dg_id": 23602,
              "name": "Hojgaard, Nicolai",
              "salary": 7800
            },
            {
              "dg_id": 29767,
              "name": "Gerard, Ryan",
              "salary": 7200
            }
          ],
          "actual_total": 471.5,
          "delta_pct": 101.19,
          "verdict": "top_1_pct"
        },
        {
          "lineup_id": "L4",
          "kind": "Leverage",
          "title": "Leverage build #4",
          "label": "Leverage #4",
          "salary": 47100,
          "proj_total": 145.18,
          "players": [
            {
              "dg_id": 12294,
              "name": "Fleetwood, Tommy",
              "salary": 9700
            },
            {
              "dg_id": 14578,
              "name": "Henley, Russell",
              "salary": 9900
            },
            {
              "dg_id": 29767,
              "name": "Gerard, Ryan",
              "salary": 7200
            },
            {
              "dg_id": 22760,
              "name": "Hisatsune, Ryo",
              "salary": 7000
            },
            {
              "dg_id": 18586,
              "name": "Smith, Jordan",
              "salary": 6800
            },
            {
              "dg_id": 23475,
              "name": "Novak, Andrew",
              "salary": 6500
            }
          ],
          "actual_total": 400.0,
          "delta_pct": 175.52,
          "verdict": "cash"
        },
        {
          "lineup_id": "C8",
          "kind": "Core",
          "title": "Core build #8",
          "label": "Core #8",
          "salary": 49000,
          "proj_total": 154.38,
          "players": [
            {
              "dg_id": 26651,
              "name": "Young, Cameron",
              "salary": 10200
            },
            {
              "dg_id": 18586,
              "name": "Smith, Jordan",
              "salary": 6800
            },
            {
              "dg_id": 28635,
              "name": "McCarty, Matt",
              "salary": 6800
            },
            {
              "dg_id": 23475,
              "name": "Novak, Andrew",
              "salary": 6500
            },
            {
              "dg_id": 14578,
              "name": "Henley, Russell",
              "salary": 9900
            },
            {
              "dg_id": 18634,
              "name": "McNealy, Maverick",
              "salary": 8800
            }
          ],
          "actual_total": 477.0,
          "delta_pct": 208.98,
          "verdict": "top_1_pct"
        }
      ],
      "hindsight_best": {
        "total": 570.5,
        "salary": 49300,
        "n_players": 6
      },
      "vs_hindsight_pts_left": 42.5,
      "field_wide_optimal": {
        "total": 602.5,
        "salary": 49300,
        "players": [
          {
            "dg_id": 26651,
            "name": "Young, Cameron",
            "salary": 10200,
            "total_pts": 124.0,
            "ownership": 0.26789999999999997
          },
          {
            "dg_id": 6430,
            "name": "Scott, Adam",
            "salary": 8400,
            "total_pts": 102.5,
            "ownership": 0.147
          },
          {
            "dg_id": 24968,
            "name": "Griffin, Ben",
            "salary": 8000,
            "total_pts": 98.5,
            "ownership": 0.0446
          },
          {
            "dg_id": 14609,
            "name": "Kim, Si Woo",
            "salary": 9200,
            "total_pts": 96.5,
            "ownership": 0.1308
          },
          {
            "dg_id": 28635,
            "name": "McCarty, Matt",
            "salary": 6800,
            "total_pts": 93.0,
            "ownership": 0.059000000000000004
          },
          {
            "dg_id": 25362,
            "name": "Fitzpatrick, Alex",
            "salary": 6700,
            "total_pts": 88.0,
            "ownership": 0.0358
          }
        ]
      },
      "vs_field_optimal_pts_left": 74.5,
      "capture_rate_pct": 87.63
    }
  ],
  "last_updated": "2026-05-25T13:36:37Z"
}