{
  "event": "Cadillac Championship",
  "event_slug": "Cadillac_Championship",
  "year": 2026,
  "lineups": [
    {
      "archetype": "CORE",
      "salary": 50000,
      "salary_remaining": 0,
      "proj_total": 247.49,
      "avg_own": 14.7,
      "floor_score": 37.9,
      "ceiling_score": 4.7,
      "players": [
        {
          "dg_id": 18417,
          "name": "Scheffler, Scottie",
          "salary": 13600,
          "zeus_dfs": 67.58,
          "proj_own": 36.0,
          "leverage": false
        },
        {
          "dg_id": 26651,
          "name": "Young, Cameron",
          "salary": 10200,
          "zeus_dfs": 48.75,
          "proj_own": 34.0,
          "leverage": false
        },
        {
          "dg_id": 23475,
          "name": "Novak, Andrew",
          "salary": 6500,
          "zeus_dfs": 33.96,
          "proj_own": 5.0,
          "leverage": false
        },
        {
          "dg_id": 22760,
          "name": "Hisatsune, Ryo",
          "salary": 7000,
          "zeus_dfs": 36.12,
          "proj_own": 8.5,
          "leverage": false
        },
        {
          "dg_id": 17538,
          "name": "Homa, Max",
          "salary": 6400,
          "zeus_dfs": 31.38,
          "proj_own": 3.0,
          "leverage": false
        },
        {
          "dg_id": 22985,
          "name": "Smotherman, Austin",
          "salary": 6300,
          "zeus_dfs": 29.7,
          "proj_own": 1.5,
          "leverage": false
        }
      ]
    },
    {
      "archetype": "CORE",
      "salary": 44600,
      "salary_remaining": 5400,
      "proj_total": 224.61,
      "avg_own": 14.4,
      "floor_score": 32.5,
      "ceiling_score": 1.5,
      "players": [
        {
          "dg_id": 16841,
          "name": "Lee, Min Woo",
          "salary": 8600,
          "zeus_dfs": 40.87,
          "proj_own": 22.0,
          "leverage": false
        },
        {
          "dg_id": 18586,
          "name": "Smith, Jordan",
          "salary": 6800,
          "zeus_dfs": 36.93,
          "proj_own": 8.5,
          "leverage": false
        },
        {
          "dg_id": 29767,
          "name": "Gerard, Ryan",
          "salary": 7200,
          "zeus_dfs": 38.17,
          "proj_own": 12.0,
          "leverage": false
        },
        {
          "dg_id": 23602,
          "name": "Hojgaard, Nicolai",
          "salary": 7800,
          "zeus_dfs": 39.37,
          "proj_own": 22.0,
          "leverage": false
        },
        {
          "dg_id": 23465,
          "name": "Greyserman, Max",
          "salary": 6200,
          "zeus_dfs": 30.36,
          "proj_own": 3.0,
          "leverage": false
        },
        {
          "dg_id": 12965,
          "name": "Fowler, Rickie",
          "salary": 8000,
          "zeus_dfs": 38.91,
          "proj_own": 19.0,
          "leverage": false
        }
      ]
    },
    {
      "archetype": "CORE",
      "salary": 49900,
      "salary_remaining": 100,
      "proj_total": 246.48,
      "avg_own": 15.2,
      "floor_score": 37.8,
      "ceiling_score": 4.3,
      "players": [
        {
          "dg_id": 22085,
          "name": "Morikawa, Collin",
          "salary": 9800,
          "zeus_dfs": 41.89,
          "proj_own": 34.0,
          "leverage": false
        },
        {
          "dg_id": 18586,
          "name": "Smith, Jordan",
          "salary": 6800,
          "zeus_dfs": 36.93,
          "proj_own": 8.5,
          "leverage": false
        },
        {
          "dg_id": 23475,
          "name": "Novak, Andrew",
          "salary": 6500,
          "zeus_dfs": 33.96,
          "proj_own": 5.0,
          "leverage": false
        },
        {
          "dg_id": 28635,
          "name": "McCarty, Matt",
          "salary": 6800,
          "zeus_dfs": 34.74,
          "proj_own": 5.0,
          "leverage": false
        },
        {
          "dg_id": 18417,
          "name": "Scheffler, Scottie",
          "salary": 13600,
          "zeus_dfs": 67.58,
          "proj_own": 36.0,
          "leverage": false
        },
        {
          "dg_id": 17538,
          "name": "Homa, Max",
          "salary": 6400,
          "zeus_dfs": 31.38,
          "proj_own": 3.0,
          "leverage": false
        }
      ]
    },
    {
      "archetype": "CORE",
      "salary": 48000,
      "salary_remaining": 2000,
      "proj_total": 226.35,
      "avg_own": 18.1,
      "floor_score": 35.4,
      "ceiling_score": 1.9,
      "players": [
        {
          "dg_id": 22085,
          "name": "Morikawa, Collin",
          "salary": 9800,
          "zeus_dfs": 41.89,
          "proj_own": 34.0,
          "leverage": false
        },
        {
          "dg_id": 14609,
          "name": "Kim, Si Woo",
          "salary": 9200,
          "zeus_dfs": 39.7,
          "proj_own": 22.0,
          "leverage": false
        },
        {
          "dg_id": 22760,
          "name": "Hisatsune, Ryo",
          "salary": 7000,
          "zeus_dfs": 36.12,
          "proj_own": 8.5,
          "leverage": false
        },
        {
          "dg_id": 23602,
          "name": "Hojgaard, Nicolai",
          "salary": 7800,
          "zeus_dfs": 39.37,
          "proj_own": 22.0,
          "leverage": false
        },
        {
          "dg_id": 23465,
          "name": "Greyserman, Max",
          "salary": 6200,
          "zeus_dfs": 30.36,
          "proj_own": 3.0,
          "leverage": false
        },
        {
          "dg_id": 12965,
          "name": "Fowler, Rickie",
          "salary": 8000,
          "zeus_dfs": 38.91,
          "proj_own": 19.0,
          "leverage": false
        }
      ]
    },
    {
      "archetype": "SAFE",
      "salary": 47000,
      "salary_remaining": 3000,
      "proj_total": 239.16,
      "avg_own": 11.2,
      "floor_score": 33.8,
      "ceiling_score": 3.8,
      "players": [
        {
          "dg_id": 18417,
          "name": "Scheffler, Scottie",
          "salary": 13600,
          "zeus_dfs": 67.58,
          "proj_own": 36.0,
          "leverage": false
        },
        {
          "dg_id": 18586,
          "name": "Smith, Jordan",
          "salary": 6800,
          "zeus_dfs": 36.93,
          "proj_own": 8.5,
          "leverage": false
        },
        {
          "dg_id": 29767,
          "name": "Gerard, Ryan",
          "salary": 7200,
          "zeus_dfs": 38.17,
          "proj_own": 12.0,
          "leverage": false
        },
        {
          "dg_id": 28635,
          "name": "McCarty, Matt",
          "salary": 6800,
          "zeus_dfs": 34.74,
          "proj_own": 5.0,
          "leverage": false
        },
        {
          "dg_id": 17538,
          "name": "Homa, Max",
          "salary": 6400,
          "zeus_dfs": 31.38,
          "proj_own": 3.0,
          "leverage": false
        },
        {
          "dg_id": 23465,
          "name": "Greyserman, Max",
          "salary": 6200,
          "zeus_dfs": 30.36,
          "proj_own": 3.0,
          "leverage": false
        }
      ]
    },
    {
      "archetype": "SAFE",
      "salary": 45500,
      "salary_remaining": 4500,
      "proj_total": 231.11,
      "avg_own": 14.4,
      "floor_score": 35.0,
      "ceiling_score": 2.1,
      "players": [
        {
          "dg_id": 26651,
          "name": "Young, Cameron",
          "salary": 10200,
          "zeus_dfs": 48.75,
          "proj_own": 34.0,
          "leverage": false
        },
        {
          "dg_id": 29767,
          "name": "Gerard, Ryan",
          "salary": 7200,
          "zeus_dfs": 38.17,
          "proj_own": 12.0,
          "leverage": false
        },
        {
          "dg_id": 23475,
          "name": "Novak, Andrew",
          "salary": 6500,
          "zeus_dfs": 33.96,
          "proj_own": 5.0,
          "leverage": false
        },
        {
          "dg_id": 22760,
          "name": "Hisatsune, Ryo",
          "salary": 7000,
          "zeus_dfs": 36.12,
          "proj_own": 8.5,
          "leverage": false
        },
        {
          "dg_id": 28635,
          "name": "McCarty, Matt",
          "salary": 6800,
          "zeus_dfs": 34.74,
          "proj_own": 5.0,
          "leverage": false
        },
        {
          "dg_id": 23602,
          "name": "Hojgaard, Nicolai",
          "salary": 7800,
          "zeus_dfs": 39.37,
          "proj_own": 22.0,
          "leverage": false
        }
      ]
    },
    {
      "archetype": "SAFE",
      "salary": 49900,
      "salary_remaining": 100,
      "proj_total": 241.84,
      "avg_own": 15.0,
      "floor_score": 37.1,
      "ceiling_score": 4.3,
      "players": [
        {
          "dg_id": 22085,
          "name": "Morikawa, Collin",
          "salary": 9800,
          "zeus_dfs": 41.89,
          "proj_own": 34.0,
          "leverage": false
        },
        {
          "dg_id": 23475,
          "name": "Novak, Andrew",
          "salary": 6500,
          "zeus_dfs": 33.96,
          "proj_own": 5.0,
          "leverage": false
        },
        {
          "dg_id": 28635,
          "name": "McCarty, Matt",
          "salary": 6800,
          "zeus_dfs": 34.74,
          "proj_own": 5.0,
          "leverage": false
        },
        {
          "dg_id": 18474,
          "name": "Smalley, Alex",
          "salary": 7100,
          "zeus_dfs": 36.01,
          "proj_own": 8.5,
          "leverage": false
        },
        {
          "dg_id": 18417,
          "name": "Scheffler, Scottie",
          "salary": 13600,
          "zeus_dfs": 67.58,
          "proj_own": 36.0,
          "leverage": false
        },
        {
          "dg_id": 24956,
          "name": "Blanchet, Chandler",
          "salary": 6100,
          "zeus_dfs": 27.66,
          "proj_own": 1.5,
          "leverage": false
        }
      ]
    },
    {
      "archetype": "SAFE",
      "salary": 49600,
      "salary_remaining": 400,
      "proj_total": 251.47,
      "avg_own": 14.8,
      "floor_score": 39.7,
      "ceiling_score": 4.4,
      "players": [
        {
          "dg_id": 16841,
          "name": "Lee, Min Woo",
          "salary": 8600,
          "zeus_dfs": 40.87,
          "proj_own": 22.0,
          "leverage": false
        },
        {
          "dg_id": 18586,
          "name": "Smith, Jordan",
          "salary": 6800,
          "zeus_dfs": 36.93,
          "proj_own": 8.5,
          "leverage": false
        },
        {
          "dg_id": 23475,
          "name": "Novak, Andrew",
          "salary": 6500,
          "zeus_dfs": 33.96,
          "proj_own": 5.0,
          "leverage": false
        },
        {
          "dg_id": 22760,
          "name": "Hisatsune, Ryo",
          "salary": 7000,
          "zeus_dfs": 36.12,
          "proj_own": 8.5,
          "leverage": false
        },
        {
          "dg_id": 18474,
          "name": "Smalley, Alex",
          "salary": 7100,
          "zeus_dfs": 36.01,
          "proj_own": 8.5,
          "leverage": false
        },
        {
          "dg_id": 18417,
          "name": "Scheffler, Scottie",
          "salary": 13600,
          "zeus_dfs": 67.58,
          "proj_own": 36.0,
          "leverage": false
        }
      ]
    },
    {
      "archetype": "LEVERAGE",
      "salary": 40800,
      "salary_remaining": 9200,
      "proj_total": 188.6,
      "avg_own": 3.1,
      "floor_score": 20.7,
      "ceiling_score": 0.6,
      "players": [
        {
          "dg_id": 18841,
          "name": "Hovland, Viktor",
          "salary": 8900,
          "zeus_dfs": 34.26,
          "proj_own": 5.0,
          "leverage": true
        },
        {
          "dg_id": 17538,
          "name": "Homa, Max",
          "salary": 6400,
          "zeus_dfs": 31.38,
          "proj_own": 3.0,
          "leverage": false
        },
        {
          "dg_id": 22985,
          "name": "Smotherman, Austin",
          "salary": 6300,
          "zeus_dfs": 29.7,
          "proj_own": 1.5,
          "leverage": false
        },
        {
          "dg_id": 23465,
          "name": "Greyserman, Max",
          "salary": 6200,
          "zeus_dfs": 30.36,
          "proj_own": 3.0,
          "leverage": false
        },
        {
          "dg_id": 14502,
          "name": "Cauley, Bud",
          "salary": 6600,
          "zeus_dfs": 32.09,
          "proj_own": 3.0,
          "leverage": false
        },
        {
          "dg_id": 16283,
          "name": "Rodgers, Patrick",
          "salary": 6400,
          "zeus_dfs": 30.81,
          "proj_own": 3.0,
          "leverage": false
        }
      ]
    },
    {
      "archetype": "LEVERAGE",
      "salary": 48000,
      "salary_remaining": 2000,
      "proj_total": 225.37,
      "avg_own": 8.6,
      "floor_score": 31.3,
      "ceiling_score": 3.7,
      "players": [
        {
          "dg_id": 18417,
          "name": "Scheffler, Scottie",
          "salary": 13600,
          "zeus_dfs": 67.58,
          "proj_own": 36.0,
          "leverage": false
        },
        {
          "dg_id": 18841,
          "name": "Hovland, Viktor",
          "salary": 8900,
          "zeus_dfs": 34.26,
          "proj_own": 5.0,
          "leverage": true
        },
        {
          "dg_id": 17538,
          "name": "Homa, Max",
          "salary": 6400,
          "zeus_dfs": 31.38,
          "proj_own": 3.0,
          "leverage": false
        },
        {
          "dg_id": 22985,
          "name": "Smotherman, Austin",
          "salary": 6300,
          "zeus_dfs": 29.7,
          "proj_own": 1.5,
          "leverage": false
        },
        {
          "dg_id": 23465,
          "name": "Greyserman, Max",
          "salary": 6200,
          "zeus_dfs": 30.36,
          "proj_own": 3.0,
          "leverage": false
        },
        {
          "dg_id": 14502,
          "name": "Cauley, Bud",
          "salary": 6600,
          "zeus_dfs": 32.09,
          "proj_own": 3.0,
          "leverage": false
        }
      ]
    },
    {
      "archetype": "LEVERAGE",
      "salary": 42200,
      "salary_remaining": 7800,
      "proj_total": 206.24,
      "avg_own": 8.2,
      "floor_score": 25.6,
      "ceiling_score": 1.5,
      "players": [
        {
          "dg_id": 26651,
          "name": "Young, Cameron",
          "salary": 10200,
          "zeus_dfs": 48.75,
          "proj_own": 34.0,
          "leverage": false
        },
        {
          "dg_id": 23475,
          "name": "Novak, Andrew",
          "salary": 6500,
          "zeus_dfs": 33.96,
          "proj_own": 5.0,
          "leverage": false
        },
        {
          "dg_id": 17538,
          "name": "Homa, Max",
          "salary": 6400,
          "zeus_dfs": 31.38,
          "proj_own": 3.0,
          "leverage": false
        },
        {
          "dg_id": 22985,
          "name": "Smotherman, Austin",
          "salary": 6300,
          "zeus_dfs": 29.7,
          "proj_own": 1.5,
          "leverage": false
        },
        {
          "dg_id": 23465,
          "name": "Greyserman, Max",
          "salary": 6200,
          "zeus_dfs": 30.36,
          "proj_own": 3.0,
          "leverage": false
        },
        {
          "dg_id": 14502,
          "name": "Cauley, Bud",
          "salary": 6600,
          "zeus_dfs": 32.09,
          "proj_own": 3.0,
          "leverage": false
        }
      ]
    },
    {
      "archetype": "LEVERAGE",
      "salary": 44900,
      "salary_remaining": 5100,
      "proj_total": 205.17,
      "avg_own": 8.8,
      "floor_score": 27.9,
      "ceiling_score": 1.2,
      "players": [
        {
          "dg_id": 22085,
          "name": "Morikawa, Collin",
          "salary": 9800,
          "zeus_dfs": 41.89,
          "proj_own": 34.0,
          "leverage": false
        },
        {
          "dg_id": 18841,
          "name": "Hovland, Viktor",
          "salary": 8900,
          "zeus_dfs": 34.26,
          "proj_own": 5.0,
          "leverage": true
        },
        {
          "dg_id": 17538,
          "name": "Homa, Max",
          "salary": 6400,
          "zeus_dfs": 31.38,
          "proj_own": 3.0,
          "leverage": false
        },
        {
          "dg_id": 14502,
          "name": "Cauley, Bud",
          "salary": 6600,
          "zeus_dfs": 32.09,
          "proj_own": 3.0,
          "leverage": false
        },
        {
          "dg_id": 28635,
          "name": "McCarty, Matt",
          "salary": 6800,
          "zeus_dfs": 34.74,
          "proj_own": 5.0,
          "leverage": false
        },
        {
          "dg_id": 16283,
          "name": "Rodgers, Patrick",
          "salary": 6400,
          "zeus_dfs": 30.81,
          "proj_own": 3.0,
          "leverage": false
        }
      ]
    }
  ],
  "exposure": {
    "17538": {
      "name": "Homa, Max",
      "lineups": 7,
      "pct": 58.3,
      "salary": 6400
    },
    "18417": {
      "name": "Scheffler, Scottie",
      "lineups": 6,
      "pct": 50.0,
      "salary": 13600
    },
    "23475": {
      "name": "Novak, Andrew",
      "lineups": 6,
      "pct": 50.0,
      "salary": 6500
    },
    "23465": {
      "name": "Greyserman, Max",
      "lineups": 6,
      "pct": 50.0,
      "salary": 6200
    },
    "28635": {
      "name": "McCarty, Matt",
      "lineups": 5,
      "pct": 41.7,
      "salary": 6800
    },
    "22760": {
      "name": "Hisatsune, Ryo",
      "lineups": 4,
      "pct": 33.3,
      "salary": 7000
    },
    "22985": {
      "name": "Smotherman, Austin",
      "lineups": 4,
      "pct": 33.3,
      "salary": 6300
    },
    "18586": {
      "name": "Smith, Jordan",
      "lineups": 4,
      "pct": 33.3,
      "salary": 6800
    },
    "22085": {
      "name": "Morikawa, Collin",
      "lineups": 4,
      "pct": 33.3,
      "salary": 9800
    },
    "14502": {
      "name": "Cauley, Bud",
      "lineups": 4,
      "pct": 33.3,
      "salary": 6600
    },
    "26651": {
      "name": "Young, Cameron",
      "lineups": 3,
      "pct": 25.0,
      "salary": 10200
    },
    "29767": {
      "name": "Gerard, Ryan",
      "lineups": 3,
      "pct": 25.0,
      "salary": 7200
    },
    "23602": {
      "name": "Hojgaard, Nicolai",
      "lineups": 3,
      "pct": 25.0,
      "salary": 7800
    },
    "18841": {
      "name": "Hovland, Viktor",
      "lineups": 3,
      "pct": 25.0,
      "salary": 8900
    },
    "16841": {
      "name": "Lee, Min Woo",
      "lineups": 2,
      "pct": 16.7,
      "salary": 8600
    },
    "18474": {
      "name": "Smalley, Alex",
      "lineups": 2,
      "pct": 16.7,
      "salary": 7100
    },
    "12965": {
      "name": "Fowler, Rickie",
      "lineups": 2,
      "pct": 16.7,
      "salary": 8000
    },
    "16283": {
      "name": "Rodgers, Patrick",
      "lineups": 2,
      "pct": 16.7,
      "salary": 6400
    },
    "14609": {
      "name": "Kim, Si Woo",
      "lineups": 1,
      "pct": 8.3,
      "salary": 9200
    },
    "24956": {
      "name": "Blanchet, Chandler",
      "lineups": 1,
      "pct": 8.3,
      "salary": 6100
    }
  },
  "top_ceiling_lineup": {
    "archetype": "CORE",
    "salary": 50000,
    "salary_remaining": 0,
    "proj_total": 247.49,
    "avg_own": 14.7,
    "floor_score": 37.9,
    "ceiling_score": 4.7,
    "players": [
      {
        "dg_id": 18417,
        "name": "Scheffler, Scottie",
        "salary": 13600,
        "zeus_dfs": 67.58,
        "proj_own": 36.0,
        "leverage": false
      },
      {
        "dg_id": 26651,
        "name": "Young, Cameron",
        "salary": 10200,
        "zeus_dfs": 48.75,
        "proj_own": 34.0,
        "leverage": false
      },
      {
        "dg_id": 23475,
        "name": "Novak, Andrew",
        "salary": 6500,
        "zeus_dfs": 33.96,
        "proj_own": 5.0,
        "leverage": false
      },
      {
        "dg_id": 22760,
        "name": "Hisatsune, Ryo",
        "salary": 7000,
        "zeus_dfs": 36.12,
        "proj_own": 8.5,
        "leverage": false
      },
      {
        "dg_id": 17538,
        "name": "Homa, Max",
        "salary": 6400,
        "zeus_dfs": 31.38,
        "proj_own": 3.0,
        "leverage": false
      },
      {
        "dg_id": 22985,
        "name": "Smotherman, Austin",
        "salary": 6300,
        "zeus_dfs": 29.7,
        "proj_own": 1.5,
        "leverage": false
      }
    ]
  },
  "top_floor_lineup": {
    "archetype": "SAFE",
    "salary": 49600,
    "salary_remaining": 400,
    "proj_total": 251.47,
    "avg_own": 14.8,
    "floor_score": 39.7,
    "ceiling_score": 4.4,
    "players": [
      {
        "dg_id": 16841,
        "name": "Lee, Min Woo",
        "salary": 8600,
        "zeus_dfs": 40.87,
        "proj_own": 22.0,
        "leverage": false
      },
      {
        "dg_id": 18586,
        "name": "Smith, Jordan",
        "salary": 6800,
        "zeus_dfs": 36.93,
        "proj_own": 8.5,
        "leverage": false
      },
      {
        "dg_id": 23475,
        "name": "Novak, Andrew",
        "salary": 6500,
        "zeus_dfs": 33.96,
        "proj_own": 5.0,
        "leverage": false
      },
      {
        "dg_id": 22760,
        "name": "Hisatsune, Ryo",
        "salary": 7000,
        "zeus_dfs": 36.12,
        "proj_own": 8.5,
        "leverage": false
      },
      {
        "dg_id": 18474,
        "name": "Smalley, Alex",
        "salary": 7100,
        "zeus_dfs": 36.01,
        "proj_own": 8.5,
        "leverage": false
      },
      {
        "dg_id": 18417,
        "name": "Scheffler, Scottie",
        "salary": 13600,
        "zeus_dfs": 67.58,
        "proj_own": 36.0,
        "leverage": false
      }
    ]
  },
  "n_lineups": 12,
  "constraints": {
    "cap": 50000,
    "size": 6,
    "buckets": {
      "CORE": 4,
      "SAFE": 4,
      "LEVERAGE": 4
    }
  }
}