{"event":"Charles Schwab Challenge","event_id":21,"generated_utc":"2026-05-26T15:16:08.349105+00:00","predictions_count":132,"odds_count":132,"edges_calculated":132,"edges":[{"dg_id":29770,"name":"Mouw, William","model_prob_pct":15.06,"market_prob_pct":13.33,"best_odds":7.5,"best_book":"fanduel","bbi_rank":65,"bbi_composite":36.4,"edge":1.73},{"dg_id":19846,"name":"Bauchou, Zach","model_prob_pct":18.62,"market_prob_pct":17.54,"best_odds":5.7,"best_book":"fanduel","bbi_rank":56,"bbi_composite":38.5,"edge":1.08},{"dg_id":27819,"name":"Castillo, Ricky","model_prob_pct":17.7,"market_prob_pct":16.67,"best_odds":6.0,"best_book":"fanduel","bbi_rank":36,"bbi_composite":43.8,"edge":1.03},{"dg_id":16757,"name":"Dou, Zecheng","model_prob_pct":14.37,"market_prob_pct":13.33,"best_odds":7.5,"best_book":"fanduel","bbi_rank":72,"bbi_composite":35.6,"edge":1.03},{"dg_id":24343,"name":"Lamprecht, Christo","model_prob_pct":5.97,"market_prob_pct":5.0,"best_odds":20.0,"best_book":"fanduel","bbi_rank":116,"bbi_composite":21.3,"edge":0.97},{"dg_id":24956,"name":"Blanchet, Chandler","model_prob_pct":11.45,"market_prob_pct":10.53,"best_odds":9.5,"best_book":"fanduel","bbi_rank":84,"bbi_composite":32.1,"edge":0.93},{"dg_id":24550,"name":"Ghim, Doug","model_prob_pct":21.74,"market_prob_pct":20.83,"best_odds":4.8,"best_book":"fanduel","bbi_rank":27,"bbi_composite":46.8,"edge":0.91},{"dg_id":17032,"name":"Tosti, Alejandro","model_prob_pct":5.02,"market_prob_pct":4.35,"best_odds":23.0,"best_book":"fanduel","bbi_rank":128,"bbi_composite":16.4,"edge":0.67},{"dg_id":21074,"name":"Nakajima, Keita","model_prob_pct":11.1,"market_prob_pct":10.53,"best_odds":9.5,"best_book":"fanduel","bbi_rank":91,"bbi_composite":30.2,"edge":0.57},{"dg_id":25002,"name":"Wu, Dylan","model_prob_pct":7.19,"market_prob_pct":6.67,"best_odds":15.0,"best_book":"fanduel","bbi_rank":96,"bbi_composite":28.1,"edge":0.53},{"dg_id":15470,"name":"Hossler, Beau","model_prob_pct":15.85,"market_prob_pct":15.38,"best_odds":6.5,"best_book":"fanduel","bbi_rank":42,"bbi_composite":42.2,"edge":0.46},{"dg_id":19477,"name":"Schenk, Adam","model_prob_pct":5.16,"market_prob_pct":4.76,"best_odds":21.0,"best_book":"fanduel","bbi_rank":118,"bbi_composite":20.9,"edge":0.4},{"dg_id":25475,"name":"Nyholm, Pontus","model_prob_pct":7.02,"market_prob_pct":6.67,"best_odds":15.0,"best_book":"fanduel","bbi_rank":102,"bbi_composite":26.3,"edge":0.36},{"dg_id":21995,"name":"Springer, Hayden","model_prob_pct":10.34,"market_prob_pct":10.0,"best_odds":10.0,"best_book":"fanduel","bbi_rank":79,"bbi_composite":33.6,"edge":0.34},{"dg_id":23841,"name":"Neergaard-Petersen, Rasmus","model_prob_pct":19.08,"market_prob_pct":18.87,"best_odds":5.3,"best_book":"fanduel","bbi_rank":55,"bbi_composite":38.7,"edge":0.22},{"dg_id":27780,"name":"Crowe, Trace","model_prob_pct":10.2,"market_prob_pct":10.0,"best_odds":10.0,"best_book":"fanduel","bbi_rank":95,"bbi_composite":28.4,"edge":0.2},{"dg_id":10873,"name":"Skinns, David","model_prob_pct":7.17,"market_prob_pct":7.14,"best_odds":14.0,"best_book":"fanduel","bbi_rank":106,"bbi_composite":25.0,"edge":0.03},{"dg_id":24342,"name":"Higgo, Garrick","model_prob_pct":12.5,"market_prob_pct":12.5,"best_odds":8.0,"best_book":"fanduel","bbi_rank":87,"bbi_composite":31.0,"edge":0.0},{"dg_id":14792,"name":"Saddier, Adrien","model_prob_pct":11.74,"market_prob_pct":11.76,"best_odds":8.5,"best_book":"fanduel","bbi_rank":90,"bbi_composite":30.3,"edge":-0.03},{"dg_id":18424,"name":"Roy, Kevin","model_prob_pct":13.26,"market_prob_pct":13.33,"best_odds":7.5,"best_book":"fanduel","bbi_rank":46,"bbi_composite":39.9,"edge":-0.07},{"dg_id":23048,"name":"Stanger, Jimmy","model_prob_pct":6.57,"market_prob_pct":6.67,"best_odds":15.0,"best_book":"betmgm","bbi_rank":114,"bbi_composite":21.8,"edge":-0.1},{"dg_id":21889,"name":"Kang, Jeffrey","model_prob_pct":4.89,"market_prob_pct":5.0,"best_odds":20.0,"best_book":"fanduel","bbi_rank":115,"bbi_composite":21.6,"edge":-0.11},{"dg_id":21756,"name":"Cole, Eric","model_prob_pct":20.7,"market_prob_pct":20.83,"best_odds":4.8,"best_book":"fanduel","bbi_rank":26,"bbi_composite":47.4,"edge":-0.13},{"dg_id":19865,"name":"Hardy, Nick","model_prob_pct":4.81,"market_prob_pct":5.0,"best_odds":20.0,"best_book":"fanduel","bbi_rank":104,"bbi_composite":25.4,"edge":-0.19},{"dg_id":26657,"name":"Fisk, Steven","model_prob_pct":17.3,"market_prob_pct":17.54,"best_odds":5.7,"best_book":"fanduel","bbi_rank":43,"bbi_composite":41.8,"edge":-0.24},{"dg_id":25003,"name":"Walker, Danny","model_prob_pct":4.75,"market_prob_pct":5.0,"best_odds":20.0,"best_book":"fanduel","bbi_rank":117,"bbi_composite":21.0,"edge":-0.25},{"dg_id":25319,"name":"VanDerLaan, John","model_prob_pct":8.06,"market_prob_pct":8.33,"best_odds":12.0,"best_book":"fanduel","bbi_rank":113,"bbi_composite":22.1,"edge":-0.27},{"dg_id":20766,"name":"Brown, Dan","model_prob_pct":12.22,"market_prob_pct":12.5,"best_odds":8.0,"best_book":"fanduel","bbi_rank":83,"bbi_composite":32.5,"edge":-0.28},{"dg_id":29197,"name":"Brennan, Michael","model_prob_pct":20.53,"market_prob_pct":20.83,"best_odds":4.8,"best_book":"fanduel","bbi_rank":58,"bbi_composite":38.1,"edge":-0.3},{"dg_id":23838,"name":"Hojgaard, Rasmus","model_prob_pct":20.53,"market_prob_pct":20.83,"best_odds":4.8,"best_book":"fanduel","bbi_rank":51,"bbi_composite":39.1,"edge":-0.3},{"dg_id":21943,"name":"Lebioda, Hank","model_prob_pct":8.03,"market_prob_pct":8.33,"best_odds":12.0,"best_book":"fanduel","bbi_rank":100,"bbi_composite":26.9,"edge":-0.3},{"dg_id":25908,"name":"Whaley, Vince","model_prob_pct":12.18,"market_prob_pct":12.5,"best_odds":8.0,"best_book":"fanduel","bbi_rank":48,"bbi_composite":39.7,"edge":-0.32},{"dg_id":13764,"name":"Parry, John","model_prob_pct":16.31,"market_prob_pct":16.67,"best_odds":6.0,"best_book":"fanduel","bbi_rank":57,"bbi_composite":38.5,"edge":-0.35},{"dg_id":16715,"name":"Ryder, Sam","model_prob_pct":12.92,"market_prob_pct":13.33,"best_odds":7.5,"best_book":"fanduel","bbi_rank":53,"bbi_composite":38.9,"edge":-0.41},{"dg_id":17881,"name":"Yu, Kevin","model_prob_pct":13.85,"market_prob_pct":14.29,"best_odds":7.0,"best_book":"fanduel","bbi_rank":76,"bbi_composite":35.0,"edge":-0.44},{"dg_id":19729,"name":"Kanaya, Takumi","model_prob_pct":8.63,"market_prob_pct":9.09,"best_odds":11.0,"best_book":"fanduel","bbi_rank":88,"bbi_composite":30.7,"edge":-0.46},{"dg_id":23505,"name":"McGreevy, Max","model_prob_pct":18.25,"market_prob_pct":18.87,"best_odds":5.3,"best_book":"fanduel","bbi_rank":34,"bbi_composite":45.0,"edge":-0.62},{"dg_id":16591,"name":"Rozo, Marcelo","model_prob_pct":3.22,"market_prob_pct":3.85,"best_odds":26.0,"best_book":"bet365","bbi_rank":121,"bbi_composite":19.9,"edge":-0.63},{"dg_id":23504,"name":"Hoey, Rico","model_prob_pct":22.08,"market_prob_pct":22.73,"best_odds":4.4,"best_book":"fanduel","bbi_rank":31,"bbi_composite":45.9,"edge":-0.65},{"dg_id":17543,"name":"Kim, Michael","model_prob_pct":16.81,"market_prob_pct":17.54,"best_odds":5.7,"best_book":"fanduel","bbi_rank":33,"bbi_composite":45.4,"edge":-0.74},{"dg_id":26649,"name":"Thorbjornsen, Michael","model_prob_pct":26.25,"market_prob_pct":27.03,"best_odds":3.7,"best_book":"fanduel","bbi_rank":38,"bbi_composite":42.8,"edge":-0.78},{"dg_id":28469,"name":"Highsmith, Joe","model_prob_pct":3.97,"market_prob_pct":4.76,"best_odds":21.0,"best_book":"fanduel","bbi_rank":129,"bbi_composite":16.4,"edge":-0.79},{"dg_id":21883,"name":"Ewart, A.J.","model_prob_pct":10.94,"market_prob_pct":11.76,"best_odds":8.5,"best_book":"fanduel","bbi_rank":92,"bbi_composite":29.9,"edge":-0.82},{"dg_id":22985,"name":"Smotherman, Austin","model_prob_pct":14.56,"market_prob_pct":15.38,"best_odds":6.5,"best_book":"fanduel","bbi_rank":66,"bbi_composite":36.3,"edge":-0.83},{"dg_id":27364,"name":"Thompson, Davis","model_prob_pct":26.18,"market_prob_pct":27.03,"best_odds":3.7,"best_book":"fanduel","bbi_rank":29,"bbi_composite":45.9,"edge":-0.85},{"dg_id":23950,"name":"Aberg, Ludvig","model_prob_pct":57.8,"market_prob_pct":58.68,"best_odds":1.7,"best_book":"draftkings","bbi_rank":1,"bbi_composite":68.3,"edge":-0.87},{"dg_id":30620,"name":"Chatfield, Davis","model_prob_pct":5.01,"market_prob_pct":5.88,"best_odds":17.0,"best_book":"fanduel","bbi_rank":103,"bbi_composite":25.7,"edge":-0.87},{"dg_id":19960,"name":"Pavon, Matthieu","model_prob_pct":9.61,"market_prob_pct":10.53,"best_odds":9.5,"best_book":"fanduel","bbi_rank":94,"bbi_composite":28.9,"edge":-0.92},{"dg_id":32055,"name":"Shipley, Neal","model_prob_pct":9.61,"market_prob_pct":10.53,"best_odds":9.5,"best_book":"fanduel","bbi_rank":97,"bbi_composite":27.9,"edge":-0.92},{"dg_id":17786,"name":"Davis, Cam","model_prob_pct":3.77,"market_prob_pct":4.76,"best_odds":21.0,"best_book":"pointsbet","bbi_rank":124,"bbi_composite":17.9,"edge":-1.0},{"dg_id":19840,"name":"Ramey, Chad","model_prob_pct":13.23,"market_prob_pct":14.29,"best_odds":7.0,"best_book":"fanduel","bbi_rank":67,"bbi_composite":36.2,"edge":-1.06},{"dg_id":13997,"name":"Svensson, Adam","model_prob_pct":11.44,"market_prob_pct":12.5,"best_odds":8.0,"best_book":"bet365","bbi_rank":63,"bbi_composite":37.0,"edge":-1.06},{"dg_id":14509,"name":"Dahmen, Joel","model_prob_pct":7.27,"market_prob_pct":8.33,"best_odds":12.0,"best_book":"fanduel","bbi_rank":98,"bbi_composite":27.8,"edge":-1.07},{"dg_id":25569,"name":"Stevens, Sam","model_prob_pct":23.92,"market_prob_pct":25.0,"best_odds":4.0,"best_book":"fanduel","bbi_rank":19,"bbi_composite":49.1,"edge":-1.08},{"dg_id":27164,"name":"Phillips, Chandler","model_prob_pct":5.58,"market_prob_pct":6.67,"best_odds":15.0,"best_book":"fanduel","bbi_rank":108,"bbi_composite":24.7,"edge":-1.08},{"dg_id":29767,"name":"Gerard, Ryan","model_prob_pct":25.19,"market_prob_pct":26.32,"best_odds":3.8,"best_book":"fanduel","bbi_rank":14,"bbi_composite":50.5,"edge":-1.13},{"dg_id":5768,"name":"Hoffman, Charley","model_prob_pct":3.82,"market_prob_pct":5.0,"best_odds":20.0,"best_book":"fanduel","bbi_rank":125,"bbi_composite":17.7,"edge":-1.18},{"dg_id":32330,"name":"Clanton, Luke","model_prob_pct":7.9,"market_prob_pct":9.09,"best_odds":11.0,"best_book":"fanduel","bbi_rank":110,"bbi_composite":23.6,"edge":-1.19},{"dg_id":23465,"name":"Greyserman, Max","model_prob_pct":25.0,"market_prob_pct":26.32,"best_odds":3.8,"best_book":"fanduel","bbi_rank":25,"bbi_composite":47.4,"edge":-1.32},{"dg_id":28270,"name":"Dunlap, Nick","model_prob_pct":7.0,"market_prob_pct":8.33,"best_odds":12.0,"best_book":"fanduel","bbi_rank":109,"bbi_composite":23.7,"edge":-1.34},{"dg_id":23475,"name":"Novak, Andrew","model_prob_pct":23.64,"market_prob_pct":25.0,"best_odds":4.0,"best_book":"fanduel","bbi_rank":21,"bbi_composite":48.8,"edge":-1.36},{"dg_id":22760,"name":"Hisatsune, Ryo","model_prob_pct":30.86,"market_prob_pct":32.26,"best_odds":3.1,"best_book":"draftkings","bbi_rank":8,"bbi_composite":52.8,"edge":-1.39},{"dg_id":15651,"name":"Ventura, Kris","model_prob_pct":11.95,"market_prob_pct":13.33,"best_odds":7.5,"best_book":"fanduel","bbi_rank":64,"bbi_composite":36.5,"edge":-1.39},{"dg_id":24766,"name":"Kim, Tom","model_prob_pct":22.12,"market_prob_pct":23.53,"best_odds":4.25,"best_book":"betonline","bbi_rank":32,"bbi_composite":45.6,"edge":-1.41},{"dg_id":11328,"name":"Kisner, Kevin","model_prob_pct":2.02,"market_prob_pct":3.45,"best_odds":29.0,"best_book":"pointsbet","bbi_rank":130,"bbi_composite":15.7,"edge":-1.43},{"dg_id":8480,"name":"Streelman, Kevin","model_prob_pct":4.34,"market_prob_pct":5.88,"best_odds":17.0,"best_book":"fanduel","bbi_rank":119,"bbi_composite":20.7,"edge":-1.54},{"dg_id":7820,"name":"Palmer, Ryan","model_prob_pct":0.6,"market_prob_pct":2.17,"best_odds":46.0,"best_book":"bet365","bbi_rank":132,"bbi_composite":4.9,"edge":-1.57},{"dg_id":17536,"name":"Spaun, J.J.","model_prob_pct":36.5,"market_prob_pct":38.17,"best_odds":2.62,"best_book":"draftkings","bbi_rank":5,"bbi_composite":57.3,"edge":-1.67},{"dg_id":20954,"name":"Hirata, Kensei","model_prob_pct":7.36,"market_prob_pct":9.09,"best_odds":11.0,"best_book":"fanduel","bbi_rank":107,"bbi_composite":24.9,"edge":-1.73},{"dg_id":28635,"name":"McCarty, Matt","model_prob_pct":23.2,"market_prob_pct":25.0,"best_odds":4.0,"best_book":"fanduel","bbi_rank":30,"bbi_composite":45.9,"edge":-1.8},{"dg_id":29279,"name":"Suber, Jackson","model_prob_pct":13.57,"market_prob_pct":15.38,"best_odds":6.5,"best_book":"fanduel","bbi_rank":59,"bbi_composite":37.5,"edge":-1.82},{"dg_id":13412,"name":"Olesen, Thorbjorn","model_prob_pct":20.37,"market_prob_pct":22.22,"best_odds":4.5,"best_book":"bet365","bbi_rank":28,"bbi_composite":46.5,"edge":-1.86},{"dg_id":18628,"name":"Campbell, Brian","model_prob_pct":3.12,"market_prob_pct":5.0,"best_odds":20.0,"best_book":"fanduel","bbi_rank":120,"bbi_composite":20.1,"edge":-1.88},{"dg_id":13470,"name":"Kizzire, Patton","model_prob_pct":2.87,"market_prob_pct":4.76,"best_odds":21.0,"best_book":"fanduel","bbi_rank":122,"bbi_composite":18.6,"edge":-1.9},{"dg_id":15556,"name":"Hughes, Mackenzie","model_prob_pct":11.4,"market_prob_pct":13.33,"best_odds":7.5,"best_book":"fanduel","bbi_rank":78,"bbi_composite":33.6,"edge":-1.93},{"dg_id":9171,"name":"Villegas, Camilo","model_prob_pct":3.18,"market_prob_pct":5.26,"best_odds":19.0,"best_book":"bet365","bbi_rank":111,"bbi_composite":23.2,"edge":-2.08},{"dg_id":24304,"name":"Vilips, Karl","model_prob_pct":11.21,"market_prob_pct":13.33,"best_odds":7.5,"best_book":"fanduel","bbi_rank":73,"bbi_composite":35.6,"edge":-2.12},{"dg_id":33759,"name":"Howell, Mason","model_prob_pct":2.62,"market_prob_pct":4.76,"best_odds":21.0,"best_book":"betmgm","bbi_rank":126,"bbi_composite":16.9,"edge":-2.14},{"dg_id":21944,"name":"Moore, Taylor","model_prob_pct":20.28,"market_prob_pct":22.47,"best_odds":4.45,"best_book":"draftkings","bbi_rank":35,"bbi_composite":43.8,"edge":-2.19},{"dg_id":17639,"name":"Blair, Zac","model_prob_pct":11.12,"market_prob_pct":13.33,"best_odds":7.5,"best_book":"fanduel","bbi_rank":75,"bbi_composite":35.1,"edge":-2.21},{"dg_id":16333,"name":"Hubbard, Mark","model_prob_pct":11.07,"market_prob_pct":13.33,"best_odds":7.5,"best_book":"fanduel","bbi_rank":62,"bbi_composite":37.2,"edge":-2.26},{"dg_id":18474,"name":"Smalley, Alex","model_prob_pct":33.9,"market_prob_pct":36.23,"best_odds":2.76,"best_book":"draftkings","bbi_rank":11,"bbi_composite":51.8,"edge":-2.33},{"dg_id":16341,"name":"Peterson, Paul","model_prob_pct":5.99,"market_prob_pct":8.33,"best_odds":12.0,"best_book":"fanduel","bbi_rank":99,"bbi_composite":27.0,"edge":-2.35},{"dg_id":14007,"name":"Martin, Ben","model_prob_pct":2.61,"market_prob_pct":5.0,"best_odds":20.0,"best_book":"fanduel","bbi_rank":127,"bbi_composite":16.6,"edge":-2.39},{"dg_id":17550,"name":"Van Rooyen, Erik","model_prob_pct":8.05,"market_prob_pct":10.53,"best_odds":9.5,"best_book":"fanduel","bbi_rank":101,"bbi_composite":26.3,"edge":-2.47},{"dg_id":11276,"name":"Horschel, Billy","model_prob_pct":9.23,"market_prob_pct":11.76,"best_odds":8.5,"best_book":"fanduel","bbi_rank":89,"bbi_composite":30.3,"edge":-2.54},{"dg_id":17365,"name":"Mitchell, Keith","model_prob_pct":30.67,"market_prob_pct":33.33,"best_odds":3.0,"best_book":"fanduel","bbi_rank":10,"bbi_composite":52.5,"edge":-2.66},{"dg_id":21554,"name":"Poston, J.T.","model_prob_pct":22.32,"market_prob_pct":25.0,"best_odds":4.0,"best_book":"fanduel","bbi_rank":18,"bbi_composite":49.4,"edge":-2.68},{"dg_id":11451,"name":"Garnett, Brice","model_prob_pct":3.88,"market_prob_pct":6.67,"best_odds":15.0,"best_book":"fanduel","bbi_rank":112,"bbi_composite":23.0,"edge":-2.79},{"dg_id":15980,"name":"Lipsky, David","model_prob_pct":8.89,"market_prob_pct":11.76,"best_odds":8.5,"best_book":"fanduel","bbi_rank":82,"bbi_composite":32.6,"edge":-2.88},{"dg_id":18586,"name":"Smith, Jordan","model_prob_pct":19.8,"market_prob_pct":22.73,"best_odds":4.4,"best_book":"fanduel","bbi_rank":50,"bbi_composite":39.2,"edge":-2.93},{"dg_id":15310,"name":"Li, Haotong","model_prob_pct":17.89,"market_prob_pct":20.83,"best_odds":4.8,"best_book":"fanduel","bbi_rank":60,"bbi_composite":37.3,"edge":-2.94},{"dg_id":22002,"name":"Dumont De Chassart, Adrien","model_prob_pct":15.8,"market_prob_pct":18.87,"best_odds":5.3,"best_book":"fanduel","bbi_rank":68,"bbi_composite":36.2,"edge":-3.07},{"dg_id":16395,"name":"Kohles, Ben","model_prob_pct":9.26,"market_prob_pct":12.5,"best_odds":8.0,"best_book":"betmgm","bbi_rank":86,"bbi_composite":31.2,"edge":-3.24},{"dg_id":28159,"name":"Meissner, Mac","model_prob_pct":25.32,"market_prob_pct":28.57,"best_odds":3.5,"best_book":"fanduel","bbi_rank":16,"bbi_composite":49.8,"edge":-3.25},{"dg_id":12423,"name":"Kirk, Chris","model_prob_pct":17.57,"market_prob_pct":20.83,"best_odds":4.8,"best_book":"fanduel","bbi_rank":44,"bbi_composite":41.4,"edge":-3.26},{"dg_id":11676,"name":"Finau, Tony","model_prob_pct":21.69,"market_prob_pct":25.0,"best_odds":4.0,"best_book":"betonline","bbi_rank":45,"bbi_composite":40.8,"edge":-3.31},{"dg_id":27646,"name":"Hansson, Albert","model_prob_pct":0.48,"market_prob_pct":3.85,"best_odds":26.0,"best_book":"betmgm","bbi_rank":131,"bbi_composite":14.1,"edge":-3.37},{"dg_id":29925,"name":"Yellamaraju, Sudarshan","model_prob_pct":19.31,"market_prob_pct":22.73,"best_odds":4.4,"best_book":"fanduel","bbi_rank":54,"bbi_composite":38.8,"edge":-3.42},{"dg_id":24968,"name":"Griffin, Ben","model_prob_pct":36.5,"market_prob_pct":40.0,"best_odds":2.5,"best_book":"pointsbet","bbi_rank":2,"bbi_composite":58.4,"edge":-3.5},{"dg_id":7399,"name":"Glover, Lucas","model_prob_pct":9.0,"market_prob_pct":12.5,"best_odds":8.0,"best_book":"fanduel","bbi_rank":61,"bbi_composite":37.3,"edge":-3.5},{"dg_id":25157,"name":"Hodges, Lee","model_prob_pct":13.12,"market_prob_pct":16.67,"best_odds":6.0,"best_book":"fanduel","bbi_rank":49,"bbi_composite":39.5,"edge":-3.54},{"dg_id":22833,"name":"Echavarria, Nico","model_prob_pct":8.93,"market_prob_pct":12.5,"best_odds":8.0,"best_book":"fanduel","bbi_rank":74,"bbi_composite":35.2,"edge":-3.57},{"dg_id":28309,"name":"Coody, Pierceson","model_prob_pct":27.55,"market_prob_pct":31.25,"best_odds":3.2,"best_book":"fanduel","bbi_rank":17,"bbi_composite":49.6,"edge":-3.7},{"dg_id":16283,"name":"Rodgers, Patrick","model_prob_pct":16.23,"market_prob_pct":20.0,"best_odds":5.0,"best_book":"betonline","bbi_rank":40,"bbi_composite":42.6,"edge":-3.77},{"dg_id":32457,"name":"Keefer, Johnny","model_prob_pct":15.08,"market_prob_pct":18.87,"best_odds":5.3,"best_book":"fanduel","bbi_rank":80,"bbi_composite":33.1,"edge":-3.78},{"dg_id":26653,"name":"Eckroat, Austin","model_prob_pct":16.89,"market_prob_pct":20.83,"best_odds":4.8,"best_book":"fanduel","bbi_rank":41,"bbi_composite":42.5,"edge":-3.94},{"dg_id":14139,"name":"Thomas, Justin","model_prob_pct":36.63,"market_prob_pct":40.65,"best_odds":2.46,"best_book":"draftkings","bbi_rank":13,"bbi_composite":50.6,"edge":-4.02},{"dg_id":19872,"name":"Riley, Davis","model_prob_pct":4.17,"market_prob_pct":8.33,"best_odds":12.0,"best_book":"fanduel","bbi_rank":123,"bbi_composite":18.3,"edge":-4.17},{"dg_id":23014,"name":"Theegala, Sahith","model_prob_pct":22.42,"market_prob_pct":26.67,"best_odds":3.75,"best_book":"betonline","bbi_rank":39,"bbi_composite":42.8,"edge":-4.25},{"dg_id":17538,"name":"Homa, Max","model_prob_pct":14.41,"market_prob_pct":18.87,"best_odds":5.3,"best_book":"fanduel","bbi_rank":69,"bbi_composite":35.9,"edge":-4.46},{"dg_id":12965,"name":"Fowler, Rickie","model_prob_pct":33.9,"market_prob_pct":38.46,"best_odds":2.6,"best_book":"pointsbet","bbi_rank":6,"bbi_composite":55.7,"edge":-4.56},{"dg_id":12808,"name":"Grillo, Emiliano","model_prob_pct":10.74,"market_prob_pct":15.38,"best_odds":6.5,"best_book":"fanduel","bbi_rank":71,"bbi_composite":35.8,"edge":-4.64},{"dg_id":16394,"name":"Jaeger, Stephan","model_prob_pct":20.33,"market_prob_pct":25.0,"best_odds":4.0,"best_book":"fanduel","bbi_rank":47,"bbi_composite":39.7,"edge":-4.67},{"dg_id":11049,"name":"Simpson, Webb","model_prob_pct":8.63,"market_prob_pct":13.33,"best_odds":7.5,"best_book":"fanduel","bbi_rank":70,"bbi_composite":35.9,"edge":-4.71},{"dg_id":15330,"name":"Griffin, Lanto","model_prob_pct":8.76,"market_prob_pct":13.51,"best_odds":7.4,"best_book":"draftkings","bbi_rank":93,"bbi_composite":29.4,"edge":-4.75},{"dg_id":10104,"name":"Power, Seamus","model_prob_pct":12.63,"market_prob_pct":17.54,"best_odds":5.7,"best_book":"fanduel","bbi_rank":52,"bbi_composite":39.1,"edge":-4.92},{"dg_id":14502,"name":"Cauley, Bud","model_prob_pct":25.84,"market_prob_pct":30.77,"best_odds":3.25,"best_book":"betonline","bbi_rank":null,"bbi_composite":null,"edge":-4.93},{"dg_id":8825,"name":"Harman, Brian","model_prob_pct":19.96,"market_prob_pct":25.0,"best_odds":4.0,"best_book":"fanduel","bbi_rank":22,"bbi_composite":48.4,"edge":-5.04},{"dg_id":6169,"name":"Kuchar, Matt","model_prob_pct":6.64,"market_prob_pct":11.76,"best_odds":8.5,"best_book":"fanduel","bbi_rank":77,"bbi_composite":34.9,"edge":-5.12},{"dg_id":15575,"name":"Hoge, Tom","model_prob_pct":10.09,"market_prob_pct":15.38,"best_odds":6.5,"best_book":"fanduel","bbi_rank":85,"bbi_composite":31.5,"edge":-5.29},{"dg_id":18103,"name":"Bezuidenhout, Christiaan","model_prob_pct":19.69,"market_prob_pct":25.0,"best_odds":4.0,"best_book":"fanduel","bbi_rank":20,"bbi_composite":48.9,"edge":-5.31},{"dg_id":23323,"name":"MacIntyre, Robert","model_prob_pct":36.1,"market_prob_pct":41.67,"best_odds":2.4,"best_book":"pointsbet","bbi_rank":3,"bbi_composite":57.8,"edge":-5.57},{"dg_id":8820,"name":"Snedeker, Brandt","model_prob_pct":7.54,"market_prob_pct":13.33,"best_odds":7.5,"best_book":"fanduel","bbi_rank":81,"bbi_composite":32.8,"edge":-5.8},{"dg_id":14578,"name":"Henley, Russell","model_prob_pct":40.65,"market_prob_pct":46.51,"best_odds":2.15,"best_book":"pointsbet","bbi_rank":4,"bbi_composite":57.6,"edge":-5.86},{"dg_id":27194,"name":"Hall, Harry","model_prob_pct":27.47,"market_prob_pct":33.33,"best_odds":3.0,"best_book":"fanduel","bbi_rank":9,"bbi_composite":52.5,"edge":-5.86},{"dg_id":12577,"name":"Woodland, Gary","model_prob_pct":24.39,"market_prob_pct":30.3,"best_odds":3.3,"best_book":"fanduel","bbi_rank":23,"bbi_composite":48.4,"edge":-5.91},{"dg_id":17488,"name":"Im, Sungjae","model_prob_pct":24.81,"market_prob_pct":30.77,"best_odds":3.25,"best_book":"betonline","bbi_rank":37,"bbi_composite":42.9,"edge":-5.96},{"dg_id":13872,"name":"Bradley, Keegan","model_prob_pct":27.7,"market_prob_pct":34.48,"best_odds":2.9,"best_book":"bet365","bbi_rank":24,"bbi_composite":47.5,"edge":-6.78},{"dg_id":13562,"name":"Matsuyama, Hideki","model_prob_pct":30.21,"market_prob_pct":37.74,"best_odds":2.65,"best_book":"pointsbet","bbi_rank":7,"bbi_composite":53.7,"edge":-7.52},{"dg_id":14704,"name":"Putnam, Andrew","model_prob_pct":19.46,"market_prob_pct":27.03,"best_odds":3.7,"best_book":"fanduel","bbi_rank":15,"bbi_composite":49.9,"edge":-7.57},{"dg_id":26096,"name":"Bhatia, Akshay","model_prob_pct":26.32,"market_prob_pct":34.48,"best_odds":2.9,"best_book":"pointsbet","bbi_rank":12,"bbi_composite":51.2,"edge":-8.17}],"markets":{"win":{"all_edges":[]},"top_5":{"all_edges":[]},"top_10":{"all_edges":[]},"top_20":{"all_edges":[]}},"available_books":["bet365","betmgm","betonline","bovada","caesars","draftkings","fanduel","pinnacle","pointsbet","skybet","unibet"],"book_labels":{"skybet":"SkyBet","betmgm":"BetMGM","draftkings":"DraftKings","bovada":"Bovada","betonline":"BetOnline","pinnacle":"Pinnacle","bet365":"Bet365","caesars":"Caesars","pointsbet":"PointsBet","unibet":"Unibet","fanduel":"FanDuel"},"last_updated_book_odds":"2026-05-29 15:52:08 UTC"}