{
  "event": null,
  "event_id": 32,
  "n_simulations": 10000,
  "seed": 42,
  "n_players": 144,
  "generated_at": "2026-06-09T14:00:34Z",
  "per_player": {
    "19483": {
      "name": "Burns, Sam",
      "empirical_win_prob": 0.0052,
      "empirical_top5_prob": 0.0331,
      "empirical_top10_prob": 0.0656,
      "empirical_top20_prob": 0.1361,
      "mean_points": 42.19,
      "p5": 18.11,
      "p25": 27.42,
      "p50": 41.28,
      "p75": 55.08,
      "p95": 71.47,
      "points_std": 17.26
    },
    "12294": {
      "name": "Fleetwood, Tommy",
      "empirical_win_prob": 0.0065,
      "empirical_top5_prob": 0.0334,
      "empirical_top10_prob": 0.0698,
      "empirical_top20_prob": 0.1396,
      "mean_points": 42.43,
      "p5": 18.22,
      "p25": 27.69,
      "p50": 41.47,
      "p75": 55.16,
      "p95": 72.08,
      "points_std": 17.25
    },
    "17646": {
      "name": "Fitzpatrick, Matt",
      "empirical_win_prob": 0.0078,
      "empirical_top5_prob": 0.033,
      "empirical_top10_prob": 0.0703,
      "empirical_top20_prob": 0.1379,
      "mean_points": 42.63,
      "p5": 18.33,
      "p25": 27.78,
      "p50": 41.88,
      "p75": 55.41,
      "p95": 72.33,
      "points_std": 17.3
    },
    "22085": {
      "name": "Morikawa, Collin",
      "empirical_win_prob": 0.0071,
      "empirical_top5_prob": 0.0352,
      "empirical_top10_prob": 0.07,
      "empirical_top20_prob": 0.1429,
      "mean_points": 42.48,
      "p5": 17.85,
      "p25": 27.43,
      "p50": 41.62,
      "p75": 55.7,
      "p95": 72.18,
      "points_std": 17.5
    },
    "13900": {
      "name": "Lowry, Shane",
      "empirical_win_prob": 0.0087,
      "empirical_top5_prob": 0.0344,
      "empirical_top10_prob": 0.0699,
      "empirical_top20_prob": 0.1374,
      "mean_points": 42.68,
      "p5": 18.25,
      "p25": 27.91,
      "p50": 42.01,
      "p75": 55.49,
      "p95": 72.23,
      "points_std": 17.26
    },
    "10419": {
      "name": "Noren, Alex",
      "empirical_win_prob": 0.0069,
      "empirical_top5_prob": 0.0348,
      "empirical_top10_prob": 0.0697,
      "empirical_top20_prob": 0.1363,
      "mean_points": 42.37,
      "p5": 18.21,
      "p25": 27.63,
      "p50": 41.42,
      "p75": 55.29,
      "p95": 71.66,
      "points_std": 17.3
    },
    "21407": {
      "name": "Reitan, Kristoffer",
      "empirical_win_prob": 0.0071,
      "empirical_top5_prob": 0.0357,
      "empirical_top10_prob": 0.0673,
      "empirical_top20_prob": 0.1377,
      "mean_points": 42.48,
      "p5": 18.3,
      "p25": 27.61,
      "p50": 41.66,
      "p75": 55.63,
      "p95": 71.99,
      "points_std": 17.35
    },
    "23323": {
      "name": "MacIntyre, Robert",
      "empirical_win_prob": 0.0074,
      "empirical_top5_prob": 0.0358,
      "empirical_top10_prob": 0.0714,
      "empirical_top20_prob": 0.143,
      "mean_points": 42.91,
      "p5": 18.36,
      "p25": 27.95,
      "p50": 42.17,
      "p75": 55.84,
      "p95": 72.27,
      "points_std": 17.34
    },
    "18841": {
      "name": "Hovland, Viktor",
      "empirical_win_prob": 0.0063,
      "empirical_top5_prob": 0.0337,
      "empirical_top10_prob": 0.0723,
      "empirical_top20_prob": 0.1417,
      "mean_points": 42.48,
      "p5": 18.31,
      "p25": 27.66,
      "p50": 41.62,
      "p75": 55.61,
      "p95": 72.04,
      "points_std": 17.39
    },
    "13126": {
      "name": "Taylor, Nick",
      "empirical_win_prob": 0.0052,
      "empirical_top5_prob": 0.0324,
      "empirical_top10_prob": 0.0655,
      "empirical_top20_prob": 0.1342,
      "mean_points": 42.2,
      "p5": 17.87,
      "p25": 27.48,
      "p50": 41.21,
      "p75": 55.39,
      "p95": 71.6,
      "points_std": 17.26
    },
    "6093": {
      "name": "Rose, Justin",
      "empirical_win_prob": 0.0063,
      "empirical_top5_prob": 0.0311,
      "empirical_top10_prob": 0.0662,
      "empirical_top20_prob": 0.1369,
      "mean_points": 42.35,
      "p5": 18.07,
      "p25": 27.54,
      "p50": 41.63,
      "p75": 55.33,
      "p95": 71.61,
      "points_std": 17.27
    },
    "23604": {
      "name": "Clark, Wyndham",
      "empirical_win_prob": 0.0058,
      "empirical_top5_prob": 0.0339,
      "empirical_top10_prob": 0.0652,
      "empirical_top20_prob": 0.1346,
      "mean_points": 42.48,
      "p5": 18.45,
      "p25": 27.9,
      "p50": 41.56,
      "p75": 55.16,
      "p95": 71.34,
      "points_std": 17.04
    },
    "23602": {
      "name": "Hojgaard, Nicolai",
      "empirical_win_prob": 0.0078,
      "empirical_top5_prob": 0.0361,
      "empirical_top10_prob": 0.0725,
      "empirical_top20_prob": 0.1392,
      "mean_points": 42.64,
      "p5": 18.22,
      "p25": 27.53,
      "p50": 41.88,
      "p75": 55.79,
      "p95": 72.47,
      "points_std": 17.46
    },
    "11889": {
      "name": "Fox, Ryan",
      "empirical_win_prob": 0.008,
      "empirical_top5_prob": 0.0356,
      "empirical_top10_prob": 0.0696,
      "empirical_top20_prob": 0.1398,
      "mean_points": 42.67,
      "p5": 18.01,
      "p25": 27.82,
      "p50": 41.92,
      "p75": 55.75,
      "p95": 72.34,
      "points_std": 17.37
    },
    "18554": {
      "name": "Rai, Aaron",
      "empirical_win_prob": 0.0064,
      "empirical_top5_prob": 0.0345,
      "empirical_top10_prob": 0.0706,
      "empirical_top20_prob": 0.1435,
      "mean_points": 42.61,
      "p5": 18.3,
      "p25": 27.5,
      "p50": 41.64,
      "p75": 56.07,
      "p95": 72.12,
      "points_std": 17.43
    },
    "27194": {
      "name": "Hall, Harry",
      "empirical_win_prob": 0.0065,
      "empirical_top5_prob": 0.0324,
      "empirical_top10_prob": 0.064,
      "empirical_top20_prob": 0.1305,
      "mean_points": 42.06,
      "p5": 18.1,
      "p25": 27.36,
      "p50": 40.97,
      "p75": 55.07,
      "p95": 71.27,
      "points_std": 17.22
    },
    "25362": {
      "name": "Fitzpatrick, Alex",
      "empirical_win_prob": 0.0078,
      "empirical_top5_prob": 0.0355,
      "empirical_top10_prob": 0.0703,
      "empirical_top20_prob": 0.1413,
      "mean_points": 42.66,
      "p5": 18.21,
      "p25": 27.61,
      "p50": 41.89,
      "p75": 55.63,
      "p95": 72.1,
      "points_std": 17.39
    },
    "14704": {
      "name": "Putnam, Andrew",
      "empirical_win_prob": 0.0048,
      "empirical_top5_prob": 0.0315,
      "empirical_top10_prob": 0.065,
      "empirical_top20_prob": 0.1375,
      "mean_points": 42.43,
      "p5": 18.17,
      "p25": 27.83,
      "p50": 41.54,
      "p75": 55.4,
      "p95": 71.55,
      "points_std": 17.11
    },
    "17365": {
      "name": "Mitchell, Keith",
      "empirical_win_prob": 0.0065,
      "empirical_top5_prob": 0.0356,
      "empirical_top10_prob": 0.0696,
      "empirical_top20_prob": 0.1399,
      "mean_points": 42.52,
      "p5": 18.12,
      "p25": 27.78,
      "p50": 41.4,
      "p75": 55.43,
      "p95": 72.05,
      "points_std": 17.33
    },
    "29433": {
      "name": "Bridgeman, Jacob",
      "empirical_win_prob": 0.0063,
      "empirical_top5_prob": 0.0358,
      "empirical_top10_prob": 0.0703,
      "empirical_top20_prob": 0.1411,
      "mean_points": 42.55,
      "p5": 18.45,
      "p25": 27.87,
      "p50": 41.52,
      "p75": 55.2,
      "p95": 72.2,
      "points_std": 17.23
    },
    "14502": {
      "name": "Cauley, Bud",
      "empirical_win_prob": 0.0073,
      "empirical_top5_prob": 0.034,
      "empirical_top10_prob": 0.0683,
      "empirical_top20_prob": 0.1406,
      "mean_points": 42.66,
      "p5": 17.99,
      "p25": 28.09,
      "p50": 41.76,
      "p75": 55.56,
      "p95": 71.89,
      "points_std": 17.27
    },
    "18103": {
      "name": "Bezuidenhout, Christiaan",
      "empirical_win_prob": 0.0059,
      "empirical_top5_prob": 0.0335,
      "empirical_top10_prob": 0.0691,
      "empirical_top20_prob": 0.1343,
      "mean_points": 42.52,
      "p5": 18.09,
      "p25": 27.56,
      "p50": 41.95,
      "p75": 55.51,
      "p95": 71.8,
      "points_std": 17.26
    },
    "16243": {
      "name": "Koepka, Brooks",
      "empirical_win_prob": 0.0082,
      "empirical_top5_prob": 0.0365,
      "empirical_top10_prob": 0.073,
      "empirical_top20_prob": 0.1375,
      "mean_points": 42.61,
      "p5": 18.45,
      "p25": 27.77,
      "p50": 41.79,
      "p75": 55.36,
      "p95": 72.24,
      "points_std": 17.27
    },
    "21756": {
      "name": "Cole, Eric",
      "empirical_win_prob": 0.006,
      "empirical_top5_prob": 0.0323,
      "empirical_top10_prob": 0.0649,
      "empirical_top20_prob": 0.1373,
      "mean_points": 42.36,
      "p5": 18.37,
      "p25": 27.39,
      "p50": 41.44,
      "p75": 55.34,
      "p95": 71.26,
      "points_std": 17.28
    },
    "26649": {
      "name": "Thorbjornsen, Michael",
      "empirical_win_prob": 0.0061,
      "empirical_top5_prob": 0.0342,
      "empirical_top10_prob": 0.0691,
      "empirical_top20_prob": 0.1365,
      "mean_points": 42.41,
      "p5": 18.07,
      "p25": 27.79,
      "p50": 41.37,
      "p75": 55.29,
      "p95": 71.98,
      "points_std": 17.25
    },
    "17576": {
      "name": "Conners, Corey",
      "empirical_win_prob": 0.007,
      "empirical_top5_prob": 0.0343,
      "empirical_top10_prob": 0.0696,
      "empirical_top20_prob": 0.1417,
      "mean_points": 42.5,
      "p5": 17.92,
      "p25": 27.54,
      "p50": 41.72,
      "p75": 55.77,
      "p95": 71.8,
      "points_std": 17.38
    },
    "23014": {
      "name": "Theegala, Sahith",
      "empirical_win_prob": 0.0068,
      "empirical_top5_prob": 0.0339,
      "empirical_top10_prob": 0.0669,
      "empirical_top20_prob": 0.1349,
      "mean_points": 42.21,
      "p5": 18.22,
      "p25": 27.47,
      "p50": 41.29,
      "p75": 55.17,
      "p95": 71.6,
      "points_std": 17.26
    },
    "28159": {
      "name": "Meissner, Mac",
      "empirical_win_prob": 0.0067,
      "empirical_top5_prob": 0.0362,
      "empirical_top10_prob": 0.0736,
      "empirical_top20_prob": 0.1456,
      "mean_points": 42.75,
      "p5": 17.99,
      "p25": 28.05,
      "p50": 41.55,
      "p75": 55.91,
      "p95": 72.19,
      "points_std": 17.39
    },
    "19870": {
      "name": "McCarthy, Denny",
      "empirical_win_prob": 0.0075,
      "empirical_top5_prob": 0.0377,
      "empirical_top10_prob": 0.0723,
      "empirical_top20_prob": 0.1402,
      "mean_points": 42.67,
      "p5": 18.1,
      "p25": 27.86,
      "p50": 41.86,
      "p75": 55.49,
      "p95": 72.54,
      "points_std": 17.39
    },
    "27364": {
      "name": "Thompson, Davis",
      "empirical_win_prob": 0.006,
      "empirical_top5_prob": 0.0327,
      "empirical_top10_prob": 0.0676,
      "empirical_top20_prob": 0.1384,
      "mean_points": 42.4,
      "p5": 18.04,
      "p25": 27.61,
      "p50": 41.58,
      "p75": 55.4,
      "p95": 72.09,
      "points_std": 17.31
    },
    "18586": {
      "name": "Smith, Jordan",
      "empirical_win_prob": 0.0057,
      "empirical_top5_prob": 0.0319,
      "empirical_top10_prob": 0.0655,
      "empirical_top20_prob": 0.1344,
      "mean_points": 42.31,
      "p5": 18.13,
      "p25": 27.76,
      "p50": 41.2,
      "p75": 55.28,
      "p95": 71.43,
      "points_std": 17.13
    },
    "23504": {
      "name": "Hoey, Rico",
      "empirical_win_prob": 0.0064,
      "empirical_top5_prob": 0.0342,
      "empirical_top10_prob": 0.0709,
      "empirical_top20_prob": 0.1389,
      "mean_points": 42.54,
      "p5": 18.2,
      "p25": 27.66,
      "p50": 41.68,
      "p75": 55.65,
      "p95": 72.14,
      "points_std": 17.34
    },
    "29197": {
      "name": "Brennan, Michael",
      "empirical_win_prob": 0.0061,
      "empirical_top5_prob": 0.0355,
      "empirical_top10_prob": 0.0694,
      "empirical_top20_prob": 0.1363,
      "mean_points": 42.77,
      "p5": 18.43,
      "p25": 28.03,
      "p50": 42.27,
      "p75": 55.48,
      "p95": 71.85,
      "points_std": 17.11
    },
    "19846": {
      "name": "Bauchou, Zach",
      "empirical_win_prob": 0.0076,
      "empirical_top5_prob": 0.0342,
      "empirical_top10_prob": 0.0696,
      "empirical_top20_prob": 0.1347,
      "mean_points": 42.33,
      "p5": 17.9,
      "p25": 27.62,
      "p50": 41.2,
      "p75": 55.33,
      "p95": 72.23,
      "points_std": 17.33
    },
    "17780": {
      "name": "Pendrith, Taylor",
      "empirical_win_prob": 0.0067,
      "empirical_top5_prob": 0.0316,
      "empirical_top10_prob": 0.0674,
      "empirical_top20_prob": 0.1418,
      "mean_points": 42.52,
      "p5": 18.29,
      "p25": 27.78,
      "p50": 41.56,
      "p75": 55.56,
      "p95": 71.78,
      "points_std": 17.29
    },
    "23505": {
      "name": "McGreevy, Max",
      "empirical_win_prob": 0.0065,
      "empirical_top5_prob": 0.0336,
      "empirical_top10_prob": 0.0674,
      "empirical_top20_prob": 0.1335,
      "mean_points": 42.32,
      "p5": 17.89,
      "p25": 27.41,
      "p50": 41.38,
      "p75": 55.34,
      "p95": 71.52,
      "points_std": 17.33
    },
    "20706": {
      "name": "Wallace, Matt",
      "empirical_win_prob": 0.0059,
      "empirical_top5_prob": 0.0344,
      "empirical_top10_prob": 0.0692,
      "empirical_top20_prob": 0.1337,
      "mean_points": 42.41,
      "p5": 18.3,
      "p25": 27.67,
      "p50": 41.24,
      "p75": 55.42,
      "p95": 71.73,
      "points_std": 17.26
    },
    "23465": {
      "name": "Greyserman, Max",
      "empirical_win_prob": 0.007,
      "empirical_top5_prob": 0.0326,
      "empirical_top10_prob": 0.0662,
      "empirical_top20_prob": 0.1365,
      "mean_points": 42.47,
      "p5": 18.4,
      "p25": 27.54,
      "p50": 41.48,
      "p75": 55.58,
      "p95": 71.67,
      "points_std": 17.23
    },
    "26657": {
      "name": "Fisk, Steven",
      "empirical_win_prob": 0.0064,
      "empirical_top5_prob": 0.0352,
      "empirical_top10_prob": 0.0687,
      "empirical_top20_prob": 0.1409,
      "mean_points": 42.61,
      "p5": 18.14,
      "p25": 27.51,
      "p50": 42.04,
      "p75": 55.47,
      "p95": 71.85,
      "points_std": 17.32
    },
    "13412": {
      "name": "Olesen, Thorbjorn",
      "empirical_win_prob": 0.0078,
      "empirical_top5_prob": 0.0386,
      "empirical_top10_prob": 0.0733,
      "empirical_top20_prob": 0.1375,
      "mean_points": 42.62,
      "p5": 18.17,
      "p25": 28.06,
      "p50": 41.54,
      "p75": 55.29,
      "p95": 72.53,
      "points_std": 17.36
    },
    "11676": {
      "name": "Finau, Tony",
      "empirical_win_prob": 0.0068,
      "empirical_top5_prob": 0.0353,
      "empirical_top10_prob": 0.0715,
      "empirical_top20_prob": 0.1418,
      "mean_points": 42.68,
      "p5": 18.06,
      "p25": 27.9,
      "p50": 41.9,
      "p75": 55.86,
      "p95": 72.25,
      "points_std": 17.37
    },
    "17538": {
      "name": "Homa, Max",
      "empirical_win_prob": 0.0054,
      "empirical_top5_prob": 0.0381,
      "empirical_top10_prob": 0.0726,
      "empirical_top20_prob": 0.1436,
      "mean_points": 42.81,
      "p5": 18.13,
      "p25": 27.91,
      "p50": 41.81,
      "p75": 55.98,
      "p95": 72.59,
      "points_std": 17.38
    },
    "17881": {
      "name": "Yu, Kevin",
      "empirical_win_prob": 0.006,
      "empirical_top5_prob": 0.0355,
      "empirical_top10_prob": 0.0687,
      "empirical_top20_prob": 0.1423,
      "mean_points": 42.73,
      "p5": 18.16,
      "p25": 27.86,
      "p50": 41.86,
      "p75": 55.97,
      "p95": 72.23,
      "points_std": 17.29
    },
    "15556": {
      "name": "Hughes, Mackenzie",
      "empirical_win_prob": 0.0081,
      "empirical_top5_prob": 0.0345,
      "empirical_top10_prob": 0.072,
      "empirical_top20_prob": 0.1416,
      "mean_points": 42.78,
      "p5": 18.46,
      "p25": 27.79,
      "p50": 41.69,
      "p75": 55.65,
      "p95": 72.2,
      "points_std": 17.32
    },
    "27819": {
      "name": "Castillo, Ricky",
      "empirical_win_prob": 0.0076,
      "empirical_top5_prob": 0.0325,
      "empirical_top10_prob": 0.0702,
      "empirical_top20_prob": 0.1411,
      "mean_points": 42.6,
      "p5": 18.42,
      "p25": 27.97,
      "p50": 41.52,
      "p75": 55.37,
      "p95": 71.87,
      "points_std": 17.22
    },
    "23841": {
      "name": "Neergaard-Petersen, Rasmus",
      "empirical_win_prob": 0.0084,
      "empirical_top5_prob": 0.0366,
      "empirical_top10_prob": 0.0686,
      "empirical_top20_prob": 0.136,
      "mean_points": 42.52,
      "p5": 18.38,
      "p25": 27.8,
      "p50": 41.54,
      "p75": 55.38,
      "p95": 71.96,
      "points_std": 17.25
    },
    "16394": {
      "name": "Jaeger, Stephan",
      "empirical_win_prob": 0.0074,
      "empirical_top5_prob": 0.0355,
      "empirical_top10_prob": 0.07,
      "empirical_top20_prob": 0.1407,
      "mean_points": 42.62,
      "p5": 18.06,
      "p25": 27.64,
      "p50": 41.93,
      "p75": 55.6,
      "p95": 72.01,
      "points_std": 17.39
    },
    "25157": {
      "name": "Hodges, Lee",
      "empirical_win_prob": 0.0066,
      "empirical_top5_prob": 0.0338,
      "empirical_top10_prob": 0.0693,
      "empirical_top20_prob": 0.1362,
      "mean_points": 42.43,
      "p5": 18.36,
      "p25": 27.87,
      "p50": 41.43,
      "p75": 55.16,
      "p95": 71.77,
      "points_std": 17.16
    },
    "12423": {
      "name": "Kirk, Chris",
      "empirical_win_prob": 0.0065,
      "empirical_top5_prob": 0.0373,
      "empirical_top10_prob": 0.0701,
      "empirical_top20_prob": 0.1401,
      "mean_points": 42.7,
      "p5": 18.2,
      "p25": 27.79,
      "p50": 41.85,
      "p75": 55.8,
      "p95": 72.5,
      "points_std": 17.4
    },
    "24550": {
      "name": "Ghim, Doug",
      "empirical_win_prob": 0.0066,
      "empirical_top5_prob": 0.0337,
      "empirical_top10_prob": 0.0707,
      "empirical_top20_prob": 0.1387,
      "mean_points": 42.53,
      "p5": 18.29,
      "p25": 27.9,
      "p50": 41.48,
      "p75": 55.32,
      "p95": 72.29,
      "points_std": 17.24
    },
    "24766": {
      "name": "Kim, Tom",
      "empirical_win_prob": 0.0055,
      "empirical_top5_prob": 0.0314,
      "empirical_top10_prob": 0.0656,
      "empirical_top20_prob": 0.1357,
      "mean_points": 42.41,
      "p5": 18.2,
      "p25": 27.85,
      "p50": 41.56,
      "p75": 55.24,
      "p95": 71.54,
      "points_std": 17.11
    },
    "26653": {
      "name": "Eckroat, Austin",
      "empirical_win_prob": 0.0069,
      "empirical_top5_prob": 0.0353,
      "empirical_top10_prob": 0.0734,
      "empirical_top20_prob": 0.1454,
      "mean_points": 42.59,
      "p5": 18.27,
      "p25": 27.73,
      "p50": 41.62,
      "p75": 55.64,
      "p95": 72.43,
      "points_std": 17.41
    },
    "22985": {
      "name": "Smotherman, Austin",
      "empirical_win_prob": 0.0063,
      "empirical_top5_prob": 0.0369,
      "empirical_top10_prob": 0.0724,
      "empirical_top20_prob": 0.14,
      "mean_points": 42.6,
      "p5": 18.05,
      "p25": 27.77,
      "p50": 41.74,
      "p75": 55.67,
      "p95": 72.52,
      "points_std": 17.39
    },
    "18424": {
      "name": "Roy, Kevin",
      "empirical_win_prob": 0.007,
      "empirical_top5_prob": 0.0362,
      "empirical_top10_prob": 0.0729,
      "empirical_top20_prob": 0.1396,
      "mean_points": 42.65,
      "p5": 18.64,
      "p25": 27.71,
      "p50": 41.59,
      "p75": 55.59,
      "p95": 72.31,
      "points_std": 17.29
    },
    "22002": {
      "name": "Dumont De Chassart, Adrien",
      "empirical_win_prob": 0.0071,
      "empirical_top5_prob": 0.0341,
      "empirical_top10_prob": 0.0694,
      "empirical_top20_prob": 0.1414,
      "mean_points": 42.45,
      "p5": 18.27,
      "p25": 27.58,
      "p50": 41.3,
      "p75": 55.67,
      "p95": 71.78,
      "points_std": 17.35
    },
    "20722": {
      "name": "Schmid, Matti",
      "empirical_win_prob": 0.0061,
      "empirical_top5_prob": 0.0351,
      "empirical_top10_prob": 0.0691,
      "empirical_top20_prob": 0.1393,
      "mean_points": 42.47,
      "p5": 17.88,
      "p25": 27.52,
      "p50": 41.6,
      "p75": 55.59,
      "p95": 72.12,
      "points_std": 17.45
    },
    "15310": {
      "name": "Li, Haotong",
      "empirical_win_prob": 0.0071,
      "empirical_top5_prob": 0.0352,
      "empirical_top10_prob": 0.0675,
      "empirical_top20_prob": 0.1356,
      "mean_points": 42.33,
      "p5": 18.26,
      "p25": 27.58,
      "p50": 41.26,
      "p75": 55.27,
      "p95": 72.13,
      "points_std": 17.28
    },
    "29925": {
      "name": "Yellamaraju, Sudarshan",
      "empirical_win_prob": 0.0062,
      "empirical_top5_prob": 0.0366,
      "empirical_top10_prob": 0.0742,
      "empirical_top20_prob": 0.1401,
      "mean_points": 42.53,
      "p5": 18.28,
      "p25": 27.57,
      "p50": 41.55,
      "p75": 55.67,
      "p95": 72.45,
      "points_std": 17.4
    },
    "10104": {
      "name": "Power, Seamus",
      "empirical_win_prob": 0.0069,
      "empirical_top5_prob": 0.0347,
      "empirical_top10_prob": 0.0708,
      "empirical_top20_prob": 0.1398,
      "mean_points": 42.62,
      "p5": 18.29,
      "p25": 28.01,
      "p50": 41.88,
      "p75": 55.33,
      "p95": 71.97,
      "points_std": 17.24
    },
    "13764": {
      "name": "Parry, John",
      "empirical_win_prob": 0.0066,
      "empirical_top5_prob": 0.032,
      "empirical_top10_prob": 0.0691,
      "empirical_top20_prob": 0.1374,
      "mean_points": 42.49,
      "p5": 18.1,
      "p25": 27.71,
      "p50": 41.41,
      "p75": 55.86,
      "p95": 72.01,
      "points_std": 17.32
    },
    "15470": {
      "name": "Hossler, Beau",
      "empirical_win_prob": 0.0073,
      "empirical_top5_prob": 0.0396,
      "empirical_top10_prob": 0.0766,
      "empirical_top20_prob": 0.1452,
      "mean_points": 42.93,
      "p5": 18.26,
      "p25": 27.95,
      "p50": 42.04,
      "p75": 55.99,
      "p95": 72.7,
      "points_std": 17.46
    },
    "27900": {
      "name": "Potgieter, Aldrich",
      "empirical_win_prob": 0.0076,
      "empirical_top5_prob": 0.0342,
      "empirical_top10_prob": 0.0673,
      "empirical_top20_prob": 0.1403,
      "mean_points": 42.4,
      "p5": 18.2,
      "p25": 27.61,
      "p50": 41.27,
      "p75": 55.59,
      "p95": 72.03,
      "points_std": 17.39
    },
    "29279": {
      "name": "Suber, Jackson",
      "empirical_win_prob": 0.0066,
      "empirical_top5_prob": 0.0347,
      "empirical_top10_prob": 0.0723,
      "empirical_top20_prob": 0.1424,
      "mean_points": 42.64,
      "p5": 18.52,
      "p25": 28.04,
      "p50": 41.69,
      "p75": 55.61,
      "p95": 72.02,
      "points_std": 17.26
    },
    "16757": {
      "name": "Dou, Zecheng",
      "empirical_win_prob": 0.0075,
      "empirical_top5_prob": 0.0336,
      "empirical_top10_prob": 0.0694,
      "empirical_top20_prob": 0.1376,
      "mean_points": 42.37,
      "p5": 18.1,
      "p25": 27.51,
      "p50": 41.23,
      "p75": 55.33,
      "p95": 72.18,
      "points_std": 17.34
    },
    "12808": {
      "name": "Grillo, Emiliano",
      "empirical_win_prob": 0.0068,
      "empirical_top5_prob": 0.0336,
      "empirical_top10_prob": 0.0698,
      "empirical_top20_prob": 0.1371,
      "mean_points": 42.38,
      "p5": 18.12,
      "p25": 27.52,
      "p50": 41.42,
      "p75": 55.7,
      "p95": 71.87,
      "points_std": 17.28
    },
    "29827": {
      "name": "James, Ben",
      "empirical_win_prob": 0.0074,
      "empirical_top5_prob": 0.0352,
      "empirical_top10_prob": 0.0658,
      "empirical_top20_prob": 0.1378,
      "mean_points": 42.36,
      "p5": 17.96,
      "p25": 27.52,
      "p50": 41.31,
      "p75": 55.52,
      "p95": 71.9,
      "points_std": 17.37
    },
    "29770": {
      "name": "Mouw, William",
      "empirical_win_prob": 0.0071,
      "empirical_top5_prob": 0.0365,
      "empirical_top10_prob": 0.0687,
      "empirical_top20_prob": 0.1377,
      "mean_points": 42.53,
      "p5": 18.37,
      "p25": 27.9,
      "p50": 41.52,
      "p75": 55.24,
      "p95": 71.99,
      "points_std": 17.26
    },
    "32457": {
      "name": "Keefer, Johnny",
      "empirical_win_prob": 0.0076,
      "empirical_top5_prob": 0.0339,
      "empirical_top10_prob": 0.0697,
      "empirical_top20_prob": 0.1416,
      "mean_points": 42.41,
      "p5": 18.24,
      "p25": 27.64,
      "p50": 41.18,
      "p75": 55.34,
      "p95": 72.33,
      "points_std": 17.37
    },
    "15330": {
      "name": "Griffin, Lanto",
      "empirical_win_prob": 0.007,
      "empirical_top5_prob": 0.0387,
      "empirical_top10_prob": 0.0729,
      "empirical_top20_prob": 0.1394,
      "mean_points": 42.44,
      "p5": 18.16,
      "p25": 27.54,
      "p50": 41.46,
      "p75": 55.18,
      "p95": 72.45,
      "points_std": 17.37
    },
    "25908": {
      "name": "Whaley, Vince",
      "empirical_win_prob": 0.0072,
      "empirical_top5_prob": 0.0364,
      "empirical_top10_prob": 0.0704,
      "empirical_top20_prob": 0.1384,
      "mean_points": 42.52,
      "p5": 18.0,
      "p25": 27.66,
      "p50": 41.9,
      "p75": 55.52,
      "p95": 72.29,
      "points_std": 17.38
    },
    "21944": {
      "name": "Moore, Taylor",
      "empirical_win_prob": 0.0062,
      "empirical_top5_prob": 0.0305,
      "empirical_top10_prob": 0.0699,
      "empirical_top20_prob": 0.1391,
      "mean_points": 42.5,
      "p5": 18.14,
      "p25": 27.8,
      "p50": 41.62,
      "p75": 55.47,
      "p95": 71.79,
      "points_std": 17.17
    },
    "24956": {
      "name": "Blanchet, Chandler",
      "empirical_win_prob": 0.0082,
      "empirical_top5_prob": 0.0376,
      "empirical_top10_prob": 0.0731,
      "empirical_top20_prob": 0.1393,
      "mean_points": 42.62,
      "p5": 17.86,
      "p25": 27.78,
      "p50": 41.54,
      "p75": 55.52,
      "p95": 72.56,
      "points_std": 17.48
    },
    "19840": {
      "name": "Ramey, Chad",
      "empirical_win_prob": 0.0063,
      "empirical_top5_prob": 0.036,
      "empirical_top10_prob": 0.0713,
      "empirical_top20_prob": 0.1422,
      "mean_points": 42.63,
      "p5": 18.12,
      "p25": 27.58,
      "p50": 41.74,
      "p75": 55.76,
      "p95": 72.58,
      "points_std": 17.39
    },
    "7399": {
      "name": "Glover, Lucas",
      "empirical_win_prob": 0.0061,
      "empirical_top5_prob": 0.0305,
      "empirical_top10_prob": 0.0686,
      "empirical_top20_prob": 0.1397,
      "mean_points": 42.42,
      "p5": 17.83,
      "p25": 27.64,
      "p50": 41.53,
      "p75": 55.48,
      "p95": 71.72,
      "points_std": 17.34
    },
    "16333": {
      "name": "Hubbard, Mark",
      "empirical_win_prob": 0.0062,
      "empirical_top5_prob": 0.033,
      "empirical_top10_prob": 0.0698,
      "empirical_top20_prob": 0.1364,
      "mean_points": 42.29,
      "p5": 18.15,
      "p25": 27.52,
      "p50": 41.32,
      "p75": 55.08,
      "p95": 71.96,
      "points_std": 17.27
    },
    "24342": {
      "name": "Higgo, Garrick",
      "empirical_win_prob": 0.0078,
      "empirical_top5_prob": 0.0337,
      "empirical_top10_prob": 0.0684,
      "empirical_top20_prob": 0.1338,
      "mean_points": 42.44,
      "p5": 18.06,
      "p25": 27.53,
      "p50": 41.64,
      "p75": 55.42,
      "p95": 71.4,
      "points_std": 17.29
    },
    "11276": {
      "name": "Horschel, Billy",
      "empirical_win_prob": 0.0079,
      "empirical_top5_prob": 0.0373,
      "empirical_top10_prob": 0.0709,
      "empirical_top20_prob": 0.1383,
      "mean_points": 42.43,
      "p5": 17.96,
      "p25": 27.58,
      "p50": 41.42,
      "p75": 55.16,
      "p95": 72.2,
      "points_std": 17.34
    },
    "15651": {
      "name": "Ventura, Kris",
      "empirical_win_prob": 0.0063,
      "empirical_top5_prob": 0.0318,
      "empirical_top10_prob": 0.0673,
      "empirical_top20_prob": 0.1368,
      "mean_points": 42.46,
      "p5": 18.1,
      "p25": 27.8,
      "p50": 41.48,
      "p75": 55.47,
      "p95": 71.5,
      "points_std": 17.19
    },
    "16715": {
      "name": "Ryder, Sam",
      "empirical_win_prob": 0.0071,
      "empirical_top5_prob": 0.0315,
      "empirical_top10_prob": 0.0633,
      "empirical_top20_prob": 0.131,
      "mean_points": 42.22,
      "p5": 18.09,
      "p25": 27.55,
      "p50": 41.46,
      "p75": 55.39,
      "p95": 71.1,
      "points_std": 17.11
    },
    "21074": {
      "name": "Nakajima, Keita",
      "empirical_win_prob": 0.007,
      "empirical_top5_prob": 0.0348,
      "empirical_top10_prob": 0.0688,
      "empirical_top20_prob": 0.1383,
      "mean_points": 42.62,
      "p5": 18.36,
      "p25": 27.76,
      "p50": 41.75,
      "p75": 55.43,
      "p95": 71.93,
      "points_std": 17.21
    },
    "26850": {
      "name": "Svensson, Jesper",
      "empirical_win_prob": 0.0075,
      "empirical_top5_prob": 0.0376,
      "empirical_top10_prob": 0.0716,
      "empirical_top20_prob": 0.1464,
      "mean_points": 42.92,
      "p5": 18.26,
      "p25": 27.97,
      "p50": 42.33,
      "p75": 55.78,
      "p95": 72.59,
      "points_std": 17.46
    },
    "21883": {
      "name": "Ewart, A.J.",
      "empirical_win_prob": 0.0064,
      "empirical_top5_prob": 0.0352,
      "empirical_top10_prob": 0.073,
      "empirical_top20_prob": 0.14,
      "mean_points": 42.59,
      "p5": 18.02,
      "p25": 27.61,
      "p50": 41.83,
      "p75": 55.65,
      "p95": 72.23,
      "points_std": 17.33
    },
    "20766": {
      "name": "Brown, Dan",
      "empirical_win_prob": 0.0072,
      "empirical_top5_prob": 0.0368,
      "empirical_top10_prob": 0.0726,
      "empirical_top20_prob": 0.1445,
      "mean_points": 42.85,
      "p5": 18.11,
      "p25": 27.9,
      "p50": 42.26,
      "p75": 55.83,
      "p95": 72.18,
      "points_std": 17.4
    },
    "25094": {
      "name": "Fishburn, Patrick",
      "empirical_win_prob": 0.0063,
      "empirical_top5_prob": 0.03,
      "empirical_top10_prob": 0.0615,
      "empirical_top20_prob": 0.1298,
      "mean_points": 42.29,
      "p5": 18.42,
      "p25": 27.84,
      "p50": 41.41,
      "p75": 55.15,
      "p95": 70.96,
      "points_std": 16.98
    },
    "19729": {
      "name": "Kanaya, Takumi",
      "empirical_win_prob": 0.0071,
      "empirical_top5_prob": 0.0361,
      "empirical_top10_prob": 0.0711,
      "empirical_top20_prob": 0.1384,
      "mean_points": 42.65,
      "p5": 18.31,
      "p25": 27.75,
      "p50": 41.76,
      "p75": 55.56,
      "p95": 72.44,
      "points_std": 17.29
    },
    "32260": {
      "name": "McCulloch, Ashton",
      "empirical_win_prob": 0.0077,
      "empirical_top5_prob": 0.0363,
      "empirical_top10_prob": 0.0717,
      "empirical_top20_prob": 0.1401,
      "mean_points": 42.7,
      "p5": 18.07,
      "p25": 27.7,
      "p50": 41.75,
      "p75": 55.69,
      "p95": 72.21,
      "points_std": 17.44
    },
    "26617": {
      "name": "Anderson, Matthew",
      "empirical_win_prob": 0.0074,
      "empirical_top5_prob": 0.0363,
      "empirical_top10_prob": 0.0725,
      "empirical_top20_prob": 0.1416,
      "mean_points": 42.62,
      "p5": 17.83,
      "p25": 27.7,
      "p50": 41.74,
      "p75": 55.88,
      "p95": 72.54,
      "points_std": 17.45
    },
    "9457": {
      "name": "Benson, Yohann",
      "empirical_win_prob": 0.0073,
      "empirical_top5_prob": 0.0329,
      "empirical_top10_prob": 0.0679,
      "empirical_top20_prob": 0.1352,
      "mean_points": 42.18,
      "p5": 18.0,
      "p25": 27.28,
      "p50": 41.27,
      "p75": 55.15,
      "p95": 71.62,
      "points_std": 17.3
    },
    "31347": {
      "name": "Desmarchais, Laurent",
      "empirical_win_prob": 0.0077,
      "empirical_top5_prob": 0.0365,
      "empirical_top10_prob": 0.0704,
      "empirical_top20_prob": 0.1434,
      "mean_points": 42.76,
      "p5": 18.57,
      "p25": 27.9,
      "p50": 41.62,
      "p75": 55.65,
      "p95": 72.34,
      "points_std": 17.35
    },
    "30040252": {
      "name": "Lew, Dawson",
      "empirical_win_prob": 0.0071,
      "empirical_top5_prob": 0.0329,
      "empirical_top10_prob": 0.0677,
      "empirical_top20_prob": 0.1406,
      "mean_points": 42.75,
      "p5": 18.41,
      "p25": 28.03,
      "p50": 41.91,
      "p75": 55.81,
      "p95": 71.82,
      "points_std": 17.19
    },
    "16492": {
      "name": "Nesbitt, Drew",
      "empirical_win_prob": 0.0068,
      "empirical_top5_prob": 0.0342,
      "empirical_top10_prob": 0.0685,
      "empirical_top20_prob": 0.1419,
      "mean_points": 42.57,
      "p5": 18.33,
      "p25": 27.62,
      "p50": 41.49,
      "p75": 55.83,
      "p95": 71.86,
      "points_std": 17.35
    },
    "30717": {
      "name": "O'Donovan, Declan",
      "empirical_win_prob": 0.0074,
      "empirical_top5_prob": 0.0364,
      "empirical_top10_prob": 0.0713,
      "empirical_top20_prob": 0.1364,
      "mean_points": 42.42,
      "p5": 18.11,
      "p25": 27.5,
      "p50": 41.39,
      "p75": 55.46,
      "p95": 72.38,
      "points_std": 17.41
    },
    "7626": {
      "name": "O'Hair, Sean",
      "empirical_win_prob": 0.0063,
      "empirical_top5_prob": 0.035,
      "empirical_top10_prob": 0.0693,
      "empirical_top20_prob": 0.142,
      "mean_points": 42.46,
      "p5": 17.88,
      "p25": 27.55,
      "p50": 41.54,
      "p75": 55.62,
      "p95": 71.75,
      "points_std": 17.38
    },
    "35395": {
      "name": "Sanderson, Calen",
      "empirical_win_prob": 0.0056,
      "empirical_top5_prob": 0.0321,
      "empirical_top10_prob": 0.0672,
      "empirical_top20_prob": 0.1394,
      "mean_points": 42.43,
      "p5": 18.1,
      "p25": 27.84,
      "p50": 41.64,
      "p75": 55.33,
      "p95": 71.73,
      "points_std": 17.26
    },
    "25289": {
      "name": "Savoie, Joey",
      "empirical_win_prob": 0.0067,
      "empirical_top5_prob": 0.0341,
      "empirical_top10_prob": 0.0695,
      "empirical_top20_prob": 0.1371,
      "mean_points": 42.38,
      "p5": 17.92,
      "p25": 27.71,
      "p50": 41.2,
      "p75": 55.5,
      "p95": 72.13,
      "points_std": 17.33
    },
    "29702": {
      "name": "Sihota, Jeevan",
      "empirical_win_prob": 0.006,
      "empirical_top5_prob": 0.0339,
      "empirical_top10_prob": 0.0694,
      "empirical_top20_prob": 0.1413,
      "mean_points": 42.47,
      "p5": 18.22,
      "p25": 27.65,
      "p50": 41.59,
      "p75": 55.47,
      "p95": 72.06,
      "points_std": 17.29
    },
    "30036882": {
      "name": "Zhao, Eric",
      "empirical_win_prob": 0.0066,
      "empirical_top5_prob": 0.034,
      "empirical_top10_prob": 0.0673,
      "empirical_top20_prob": 0.1352,
      "mean_points": 42.37,
      "p5": 18.17,
      "p25": 27.78,
      "p50": 41.55,
      "p75": 55.0,
      "p95": 71.79,
      "points_std": 17.19
    },
    "15575": {
      "name": "Hoge, Tom",
      "empirical_win_prob": 0.0071,
      "empirical_top5_prob": 0.0339,
      "empirical_top10_prob": 0.0687,
      "empirical_top20_prob": 0.1427,
      "mean_points": 42.51,
      "p5": 18.13,
      "p25": 27.57,
      "p50": 41.53,
      "p75": 55.71,
      "p95": 71.81,
      "points_std": 17.41
    },
    "13965": {
      "name": "Hadwin, Adam",
      "empirical_win_prob": 0.006,
      "empirical_top5_prob": 0.032,
      "empirical_top10_prob": 0.0682,
      "empirical_top20_prob": 0.1363,
      "mean_points": 42.37,
      "p5": 17.94,
      "p25": 27.53,
      "p50": 41.37,
      "p75": 55.45,
      "p95": 71.71,
      "points_std": 17.3
    },
    "11441": {
      "name": "Covello, Vince",
      "empirical_win_prob": 0.007,
      "empirical_top5_prob": 0.0362,
      "empirical_top10_prob": 0.0696,
      "empirical_top20_prob": 0.1371,
      "mean_points": 42.39,
      "p5": 18.18,
      "p25": 27.75,
      "p50": 41.54,
      "p75": 55.28,
      "p95": 72.19,
      "points_std": 17.3
    },
    "13508": {
      "name": "Vegas, Jhonattan",
      "empirical_win_prob": 0.0059,
      "empirical_top5_prob": 0.0321,
      "empirical_top10_prob": 0.0679,
      "empirical_top20_prob": 0.1368,
      "mean_points": 42.51,
      "p5": 18.32,
      "p25": 27.79,
      "p50": 41.66,
      "p75": 55.57,
      "p95": 71.48,
      "points_std": 17.24
    },
    "21995": {
      "name": "Springer, Hayden",
      "empirical_win_prob": 0.0098,
      "empirical_top5_prob": 0.0392,
      "empirical_top10_prob": 0.0763,
      "empirical_top20_prob": 0.1439,
      "mean_points": 42.99,
      "p5": 18.32,
      "p25": 27.98,
      "p50": 42.27,
      "p75": 56.1,
      "p95": 72.94,
      "points_std": 17.52
    },
    "14509": {
      "name": "Dahmen, Joel",
      "empirical_win_prob": 0.0073,
      "empirical_top5_prob": 0.0339,
      "empirical_top10_prob": 0.0683,
      "empirical_top20_prob": 0.1373,
      "mean_points": 42.63,
      "p5": 18.23,
      "p25": 27.83,
      "p50": 41.81,
      "p75": 55.47,
      "p95": 71.92,
      "points_std": 17.28
    },
    "27780": {
      "name": "Crowe, Trace",
      "empirical_win_prob": 0.0075,
      "empirical_top5_prob": 0.0354,
      "empirical_top10_prob": 0.0696,
      "empirical_top20_prob": 0.1432,
      "mean_points": 42.71,
      "p5": 18.49,
      "p25": 28.08,
      "p50": 41.65,
      "p75": 55.77,
      "p95": 72.3,
      "points_std": 17.26
    },
    "17032": {
      "name": "Tosti, Alejandro",
      "empirical_win_prob": 0.0073,
      "empirical_top5_prob": 0.031,
      "empirical_top10_prob": 0.0643,
      "empirical_top20_prob": 0.1317,
      "mean_points": 42.52,
      "p5": 18.59,
      "p25": 27.86,
      "p50": 41.71,
      "p75": 55.28,
      "p95": 71.37,
      "points_std": 17.09
    },
    "15980": {
      "name": "Lipsky, David",
      "empirical_win_prob": 0.0062,
      "empirical_top5_prob": 0.0341,
      "empirical_top10_prob": 0.0674,
      "empirical_top20_prob": 0.1409,
      "mean_points": 42.79,
      "p5": 18.39,
      "p25": 27.94,
      "p50": 42.25,
      "p75": 55.8,
      "p95": 71.79,
      "points_std": 17.2
    },
    "25475": {
      "name": "Nyholm, Pontus",
      "empirical_win_prob": 0.0072,
      "empirical_top5_prob": 0.0383,
      "empirical_top10_prob": 0.0725,
      "empirical_top20_prob": 0.1435,
      "mean_points": 42.66,
      "p5": 18.33,
      "p25": 27.59,
      "p50": 41.67,
      "p75": 55.82,
      "p95": 72.26,
      "points_std": 17.47
    },
    "17550": {
      "name": "Van Rooyen, Erik",
      "empirical_win_prob": 0.0063,
      "empirical_top5_prob": 0.0346,
      "empirical_top10_prob": 0.0672,
      "empirical_top20_prob": 0.1344,
      "mean_points": 42.54,
      "p5": 18.27,
      "p25": 27.69,
      "p50": 41.82,
      "p75": 55.44,
      "p95": 71.87,
      "points_std": 17.21
    },
    "21943": {
      "name": "Lebioda, Hank",
      "empirical_win_prob": 0.007,
      "empirical_top5_prob": 0.0339,
      "empirical_top10_prob": 0.0696,
      "empirical_top20_prob": 0.1382,
      "mean_points": 42.78,
      "p5": 18.35,
      "p25": 28.04,
      "p50": 42.01,
      "p75": 55.72,
      "p95": 72.11,
      "points_std": 17.22
    },
    "32259": {
      "name": "Matthews, Justin",
      "empirical_win_prob": 0.0072,
      "empirical_top5_prob": 0.0364,
      "empirical_top10_prob": 0.0732,
      "empirical_top20_prob": 0.1402,
      "mean_points": 42.56,
      "p5": 17.86,
      "p25": 27.6,
      "p50": 41.71,
      "p75": 55.8,
      "p95": 72.19,
      "points_std": 17.49
    },
    "17786": {
      "name": "Davis, Cam",
      "empirical_win_prob": 0.0084,
      "empirical_top5_prob": 0.0377,
      "empirical_top10_prob": 0.0725,
      "empirical_top20_prob": 0.1401,
      "mean_points": 42.5,
      "p5": 17.89,
      "p25": 27.67,
      "p50": 41.63,
      "p75": 55.63,
      "p95": 72.61,
      "points_std": 17.5
    },
    "12426": {
      "name": "Waring, Paul",
      "empirical_win_prob": 0.0058,
      "empirical_top5_prob": 0.0361,
      "empirical_top10_prob": 0.0685,
      "empirical_top20_prob": 0.1408,
      "mean_points": 42.52,
      "p5": 18.22,
      "p25": 27.68,
      "p50": 41.7,
      "p75": 55.54,
      "p95": 72.15,
      "points_std": 17.36
    },
    "24304": {
      "name": "Vilips, Karl",
      "empirical_win_prob": 0.0076,
      "empirical_top5_prob": 0.0361,
      "empirical_top10_prob": 0.0707,
      "empirical_top20_prob": 0.1391,
      "mean_points": 42.56,
      "p5": 18.15,
      "p25": 27.63,
      "p50": 41.61,
      "p75": 55.35,
      "p95": 72.38,
      "points_std": 17.33
    },
    "32055": {
      "name": "Shipley, Neal",
      "empirical_win_prob": 0.0082,
      "empirical_top5_prob": 0.036,
      "empirical_top10_prob": 0.0709,
      "empirical_top20_prob": 0.1408,
      "mean_points": 42.28,
      "p5": 18.15,
      "p25": 27.23,
      "p50": 40.91,
      "p75": 55.32,
      "p95": 72.06,
      "points_std": 17.5
    },
    "32330": {
      "name": "Clanton, Luke",
      "empirical_win_prob": 0.006,
      "empirical_top5_prob": 0.0366,
      "empirical_top10_prob": 0.0706,
      "empirical_top20_prob": 0.14,
      "mean_points": 42.57,
      "p5": 18.17,
      "p25": 27.78,
      "p50": 41.76,
      "p75": 55.65,
      "p95": 72.09,
      "points_std": 17.32
    },
    "13997": {
      "name": "Svensson, Adam",
      "empirical_win_prob": 0.0086,
      "empirical_top5_prob": 0.0369,
      "empirical_top10_prob": 0.0714,
      "empirical_top20_prob": 0.1387,
      "mean_points": 42.54,
      "p5": 18.16,
      "p25": 27.62,
      "p50": 41.58,
      "p75": 55.47,
      "p95": 72.25,
      "points_std": 17.45
    },
    "11451": {
      "name": "Garnett, Brice",
      "empirical_win_prob": 0.0074,
      "empirical_top5_prob": 0.0353,
      "empirical_top10_prob": 0.0681,
      "empirical_top20_prob": 0.1396,
      "mean_points": 42.64,
      "p5": 18.19,
      "p25": 28.0,
      "p50": 41.6,
      "p75": 55.36,
      "p95": 71.92,
      "points_std": 17.25
    },
    "12909": {
      "name": "Campos, Rafael",
      "empirical_win_prob": 0.0068,
      "empirical_top5_prob": 0.0362,
      "empirical_top10_prob": 0.0651,
      "empirical_top20_prob": 0.129,
      "mean_points": 42.43,
      "p5": 18.3,
      "p25": 27.99,
      "p50": 41.73,
      "p75": 54.92,
      "p95": 72.12,
      "points_std": 17.11
    },
    "25002": {
      "name": "Wu, Dylan",
      "empirical_win_prob": 0.0074,
      "empirical_top5_prob": 0.0307,
      "empirical_top10_prob": 0.0659,
      "empirical_top20_prob": 0.1348,
      "mean_points": 42.49,
      "p5": 18.24,
      "p25": 27.96,
      "p50": 41.97,
      "p75": 54.98,
      "p95": 71.34,
      "points_std": 17.12
    },
    "25319": {
      "name": "VanDerLaan, John",
      "empirical_win_prob": 0.0082,
      "empirical_top5_prob": 0.0364,
      "empirical_top10_prob": 0.0716,
      "empirical_top20_prob": 0.1421,
      "mean_points": 42.63,
      "p5": 18.25,
      "p25": 27.59,
      "p50": 41.62,
      "p75": 55.68,
      "p95": 72.66,
      "points_std": 17.46
    },
    "5513": {
      "name": "Weir, Mike",
      "empirical_win_prob": 0.0073,
      "empirical_top5_prob": 0.0331,
      "empirical_top10_prob": 0.067,
      "empirical_top20_prob": 0.1362,
      "mean_points": 42.43,
      "p5": 18.05,
      "p25": 27.62,
      "p50": 41.74,
      "p75": 55.65,
      "p95": 71.69,
      "points_std": 17.28
    },
    "14007": {
      "name": "Martin, Ben",
      "empirical_win_prob": 0.0074,
      "empirical_top5_prob": 0.0339,
      "empirical_top10_prob": 0.0704,
      "empirical_top20_prob": 0.1367,
      "mean_points": 42.6,
      "p5": 18.51,
      "p25": 27.88,
      "p50": 41.77,
      "p75": 55.54,
      "p95": 71.89,
      "points_std": 17.17
    },
    "30620": {
      "name": "Chatfield, Davis",
      "empirical_win_prob": 0.0068,
      "empirical_top5_prob": 0.0343,
      "empirical_top10_prob": 0.0707,
      "empirical_top20_prob": 0.1405,
      "mean_points": 42.56,
      "p5": 18.01,
      "p25": 27.76,
      "p50": 41.73,
      "p75": 55.58,
      "p95": 71.95,
      "points_std": 17.35
    },
    "12920": {
      "name": "Willett, Danny",
      "empirical_win_prob": 0.0084,
      "empirical_top5_prob": 0.0355,
      "empirical_top10_prob": 0.0688,
      "empirical_top20_prob": 0.1361,
      "mean_points": 42.36,
      "p5": 18.24,
      "p25": 27.63,
      "p50": 41.13,
      "p75": 55.25,
      "p95": 72.24,
      "points_std": 17.34
    },
    "27164": {
      "name": "Phillips, Chandler",
      "empirical_win_prob": 0.0066,
      "empirical_top5_prob": 0.0338,
      "empirical_top10_prob": 0.0697,
      "empirical_top20_prob": 0.1409,
      "mean_points": 42.65,
      "p5": 18.13,
      "p25": 28.06,
      "p50": 41.88,
      "p75": 55.53,
      "p95": 72.0,
      "points_std": 17.24
    },
    "14926": {
      "name": "Malnati, Peter",
      "empirical_win_prob": 0.0084,
      "empirical_top5_prob": 0.0388,
      "empirical_top10_prob": 0.0725,
      "empirical_top20_prob": 0.1392,
      "mean_points": 42.55,
      "p5": 18.14,
      "p25": 27.84,
      "p50": 41.34,
      "p75": 55.3,
      "p95": 72.62,
      "points_std": 17.33
    },
    "20954": {
      "name": "Hirata, Kensei",
      "empirical_win_prob": 0.0072,
      "empirical_top5_prob": 0.0366,
      "empirical_top10_prob": 0.072,
      "empirical_top20_prob": 0.1422,
      "mean_points": 42.81,
      "p5": 18.47,
      "p25": 28.0,
      "p50": 41.96,
      "p75": 55.75,
      "p95": 72.17,
      "points_std": 17.32
    },
    "21889": {
      "name": "Kang, Jeffrey",
      "empirical_win_prob": 0.0076,
      "empirical_top5_prob": 0.0332,
      "empirical_top10_prob": 0.069,
      "empirical_top20_prob": 0.1386,
      "mean_points": 42.58,
      "p5": 18.11,
      "p25": 27.63,
      "p50": 41.96,
      "p75": 55.53,
      "p95": 71.68,
      "points_std": 17.32
    },
    "23048": {
      "name": "Stanger, Jimmy",
      "empirical_win_prob": 0.0075,
      "empirical_top5_prob": 0.035,
      "empirical_top10_prob": 0.0719,
      "empirical_top20_prob": 0.1423,
      "mean_points": 42.63,
      "p5": 18.35,
      "p25": 27.78,
      "p50": 41.45,
      "p75": 55.5,
      "p95": 72.3,
      "points_std": 17.37
    },
    "14050": {
      "name": "Sloan, Roger",
      "empirical_win_prob": 0.0063,
      "empirical_top5_prob": 0.0371,
      "empirical_top10_prob": 0.0722,
      "empirical_top20_prob": 0.143,
      "mean_points": 42.61,
      "p5": 18.28,
      "p25": 27.77,
      "p50": 41.6,
      "p75": 55.56,
      "p95": 72.65,
      "points_std": 17.38
    },
    "16591": {
      "name": "Rozo, Marcelo",
      "empirical_win_prob": 0.0083,
      "empirical_top5_prob": 0.0366,
      "empirical_top10_prob": 0.0699,
      "empirical_top20_prob": 0.1415,
      "mean_points": 42.55,
      "p5": 18.24,
      "p25": 27.48,
      "p50": 41.62,
      "p75": 55.69,
      "p95": 72.38,
      "points_std": 17.52
    },
    "17723": {
      "name": "Lower, Justin",
      "empirical_win_prob": 0.0067,
      "empirical_top5_prob": 0.0344,
      "empirical_top10_prob": 0.0691,
      "empirical_top20_prob": 0.1382,
      "mean_points": 42.32,
      "p5": 18.12,
      "p25": 27.43,
      "p50": 41.3,
      "p75": 55.34,
      "p95": 72.25,
      "points_std": 17.43
    },
    "25003": {
      "name": "Walker, Danny",
      "empirical_win_prob": 0.0072,
      "empirical_top5_prob": 0.035,
      "empirical_top10_prob": 0.0729,
      "empirical_top20_prob": 0.1441,
      "mean_points": 42.67,
      "p5": 17.85,
      "p25": 27.6,
      "p50": 42.06,
      "p75": 55.55,
      "p95": 72.64,
      "points_std": 17.45
    },
    "18628": {
      "name": "Campbell, Brian",
      "empirical_win_prob": 0.007,
      "empirical_top5_prob": 0.0312,
      "empirical_top10_prob": 0.0651,
      "empirical_top20_prob": 0.1373,
      "mean_points": 42.45,
      "p5": 18.12,
      "p25": 27.89,
      "p50": 41.37,
      "p75": 55.3,
      "p95": 71.92,
      "points_std": 17.18
    },
    "28270": {
      "name": "Dunlap, Nick",
      "empirical_win_prob": 0.0072,
      "empirical_top5_prob": 0.0351,
      "empirical_top10_prob": 0.0692,
      "empirical_top20_prob": 0.1397,
      "mean_points": 42.52,
      "p5": 18.03,
      "p25": 27.69,
      "p50": 41.54,
      "p75": 55.67,
      "p95": 72.2,
      "points_std": 17.4
    },
    "19960": {
      "name": "Pavon, Matthieu",
      "empirical_win_prob": 0.0068,
      "empirical_top5_prob": 0.0344,
      "empirical_top10_prob": 0.0654,
      "empirical_top20_prob": 0.1352,
      "mean_points": 42.26,
      "p5": 18.09,
      "p25": 27.75,
      "p50": 40.97,
      "p75": 55.14,
      "p95": 71.92,
      "points_std": 17.26
    },
    "24343": {
      "name": "Lamprecht, Christo",
      "empirical_win_prob": 0.006,
      "empirical_top5_prob": 0.0349,
      "empirical_top10_prob": 0.0692,
      "empirical_top20_prob": 0.1407,
      "mean_points": 42.65,
      "p5": 18.36,
      "p25": 27.8,
      "p50": 41.78,
      "p75": 55.54,
      "p95": 71.97,
      "points_std": 17.2
    },
    "19477": {
      "name": "Schenk, Adam",
      "empirical_win_prob": 0.0078,
      "empirical_top5_prob": 0.0363,
      "empirical_top10_prob": 0.0674,
      "empirical_top20_prob": 0.1373,
      "mean_points": 42.53,
      "p5": 18.16,
      "p25": 27.69,
      "p50": 41.65,
      "p75": 55.6,
      "p95": 72.19,
      "points_std": 17.38
    },
    "5768": {
      "name": "Hoffman, Charley",
      "empirical_win_prob": 0.0066,
      "empirical_top5_prob": 0.0349,
      "empirical_top10_prob": 0.0704,
      "empirical_top20_prob": 0.1439,
      "mean_points": 42.82,
      "p5": 18.2,
      "p25": 27.84,
      "p50": 42.28,
      "p75": 55.91,
      "p95": 71.95,
      "points_std": 17.32
    },
    "5716": {
      "name": "Harrington, Padraig",
      "empirical_win_prob": 0.0059,
      "empirical_top5_prob": 0.0341,
      "empirical_top10_prob": 0.0678,
      "empirical_top20_prob": 0.1356,
      "mean_points": 42.63,
      "p5": 18.33,
      "p25": 27.79,
      "p50": 41.72,
      "p75": 55.57,
      "p95": 72.03,
      "points_std": 17.17
    },
    "9171": {
      "name": "Villegas, Camilo",
      "empirical_win_prob": 0.0077,
      "empirical_top5_prob": 0.0358,
      "empirical_top10_prob": 0.0691,
      "empirical_top20_prob": 0.1426,
      "mean_points": 42.6,
      "p5": 18.0,
      "p25": 28.09,
      "p50": 41.58,
      "p75": 55.52,
      "p95": 72.37,
      "points_std": 17.39
    },
    "13470": {
      "name": "Kizzire, Patton",
      "empirical_win_prob": 0.007,
      "empirical_top5_prob": 0.0314,
      "empirical_top10_prob": 0.0662,
      "empirical_top20_prob": 0.1359,
      "mean_points": 42.6,
      "p5": 18.26,
      "p25": 27.9,
      "p50": 41.91,
      "p75": 55.57,
      "p95": 71.23,
      "points_std": 17.19
    },
    "19872": {
      "name": "Riley, Davis",
      "empirical_win_prob": 0.0072,
      "empirical_top5_prob": 0.0365,
      "empirical_top10_prob": 0.0701,
      "empirical_top20_prob": 0.1398,
      "mean_points": 42.64,
      "p5": 17.95,
      "p25": 27.8,
      "p50": 41.58,
      "p75": 55.71,
      "p95": 72.47,
      "points_std": 17.39
    },
    "28469": {
      "name": "Highsmith, Joe",
      "empirical_win_prob": 0.0075,
      "empirical_top5_prob": 0.0348,
      "empirical_top10_prob": 0.0639,
      "empirical_top20_prob": 0.1329,
      "mean_points": 42.16,
      "p5": 17.87,
      "p25": 27.25,
      "p50": 41.19,
      "p75": 55.3,
      "p95": 71.56,
      "points_std": 17.35
    }
  },
  "comparison_emp_vs_book": [
    {
      "name": "Burns, Sam",
      "dg_id": 19483,
      "bbi_win_prob": null,
      "empirical_win_prob": 0.0052,
      "delta_win": 0.0052,
      "bbi_top10_prob": null,
      "empirical_top10_prob": 0.0656,
      "delta_top10": 0.0656
    },
    {
      "name": "Fleetwood, Tommy",
      "dg_id": 12294,
      "bbi_win_prob": null,
      "empirical_win_prob": 0.0065,
      "delta_win": 0.0065,
      "bbi_top10_prob": null,
      "empirical_top10_prob": 0.0698,
      "delta_top10": 0.0698
    },
    {
      "name": "Fitzpatrick, Matt",
      "dg_id": 17646,
      "bbi_win_prob": null,
      "empirical_win_prob": 0.0078,
      "delta_win": 0.0078,
      "bbi_top10_prob": null,
      "empirical_top10_prob": 0.0703,
      "delta_top10": 0.0703
    },
    {
      "name": "Morikawa, Collin",
      "dg_id": 22085,
      "bbi_win_prob": null,
      "empirical_win_prob": 0.0071,
      "delta_win": 0.0071,
      "bbi_top10_prob": null,
      "empirical_top10_prob": 0.07,
      "delta_top10": 0.07
    },
    {
      "name": "Lowry, Shane",
      "dg_id": 13900,
      "bbi_win_prob": null,
      "empirical_win_prob": 0.0087,
      "delta_win": 0.0087,
      "bbi_top10_prob": null,
      "empirical_top10_prob": 0.0699,
      "delta_top10": 0.0699
    },
    {
      "name": "Noren, Alex",
      "dg_id": 10419,
      "bbi_win_prob": null,
      "empirical_win_prob": 0.0069,
      "delta_win": 0.0069,
      "bbi_top10_prob": null,
      "empirical_top10_prob": 0.0697,
      "delta_top10": 0.0697
    },
    {
      "name": "Reitan, Kristoffer",
      "dg_id": 21407,
      "bbi_win_prob": null,
      "empirical_win_prob": 0.0071,
      "delta_win": 0.0071,
      "bbi_top10_prob": null,
      "empirical_top10_prob": 0.0673,
      "delta_top10": 0.0673
    },
    {
      "name": "MacIntyre, Robert",
      "dg_id": 23323,
      "bbi_win_prob": null,
      "empirical_win_prob": 0.0074,
      "delta_win": 0.0074,
      "bbi_top10_prob": null,
      "empirical_top10_prob": 0.0714,
      "delta_top10": 0.0714
    },
    {
      "name": "Hovland, Viktor",
      "dg_id": 18841,
      "bbi_win_prob": null,
      "empirical_win_prob": 0.0063,
      "delta_win": 0.0063,
      "bbi_top10_prob": null,
      "empirical_top10_prob": 0.0723,
      "delta_top10": 0.0723
    },
    {
      "name": "Taylor, Nick",
      "dg_id": 13126,
      "bbi_win_prob": null,
      "empirical_win_prob": 0.0052,
      "delta_win": 0.0052,
      "bbi_top10_prob": null,
      "empirical_top10_prob": 0.0655,
      "delta_top10": 0.0655
    },
    {
      "name": "Rose, Justin",
      "dg_id": 6093,
      "bbi_win_prob": null,
      "empirical_win_prob": 0.0063,
      "delta_win": 0.0063,
      "bbi_top10_prob": null,
      "empirical_top10_prob": 0.0662,
      "delta_top10": 0.0662
    },
    {
      "name": "Clark, Wyndham",
      "dg_id": 23604,
      "bbi_win_prob": null,
      "empirical_win_prob": 0.0058,
      "delta_win": 0.0058,
      "bbi_top10_prob": null,
      "empirical_top10_prob": 0.0652,
      "delta_top10": 0.0652
    },
    {
      "name": "Hojgaard, Nicolai",
      "dg_id": 23602,
      "bbi_win_prob": null,
      "empirical_win_prob": 0.0078,
      "delta_win": 0.0078,
      "bbi_top10_prob": null,
      "empirical_top10_prob": 0.0725,
      "delta_top10": 0.0725
    },
    {
      "name": "Fox, Ryan",
      "dg_id": 11889,
      "bbi_win_prob": null,
      "empirical_win_prob": 0.008,
      "delta_win": 0.008,
      "bbi_top10_prob": null,
      "empirical_top10_prob": 0.0696,
      "delta_top10": 0.0696
    },
    {
      "name": "Rai, Aaron",
      "dg_id": 18554,
      "bbi_win_prob": null,
      "empirical_win_prob": 0.0064,
      "delta_win": 0.0064,
      "bbi_top10_prob": null,
      "empirical_top10_prob": 0.0706,
      "delta_top10": 0.0706
    },
    {
      "name": "Hall, Harry",
      "dg_id": 27194,
      "bbi_win_prob": null,
      "empirical_win_prob": 0.0065,
      "delta_win": 0.0065,
      "bbi_top10_prob": null,
      "empirical_top10_prob": 0.064,
      "delta_top10": 0.064
    },
    {
      "name": "Fitzpatrick, Alex",
      "dg_id": 25362,
      "bbi_win_prob": null,
      "empirical_win_prob": 0.0078,
      "delta_win": 0.0078,
      "bbi_top10_prob": null,
      "empirical_top10_prob": 0.0703,
      "delta_top10": 0.0703
    },
    {
      "name": "Putnam, Andrew",
      "dg_id": 14704,
      "bbi_win_prob": null,
      "empirical_win_prob": 0.0048,
      "delta_win": 0.0048,
      "bbi_top10_prob": null,
      "empirical_top10_prob": 0.065,
      "delta_top10": 0.065
    },
    {
      "name": "Mitchell, Keith",
      "dg_id": 17365,
      "bbi_win_prob": null,
      "empirical_win_prob": 0.0065,
      "delta_win": 0.0065,
      "bbi_top10_prob": null,
      "empirical_top10_prob": 0.0696,
      "delta_top10": 0.0696
    },
    {
      "name": "Bridgeman, Jacob",
      "dg_id": 29433,
      "bbi_win_prob": null,
      "empirical_win_prob": 0.0063,
      "delta_win": 0.0063,
      "bbi_top10_prob": null,
      "empirical_top10_prob": 0.0703,
      "delta_top10": 0.0703
    },
    {
      "name": "Cauley, Bud",
      "dg_id": 14502,
      "bbi_win_prob": null,
      "empirical_win_prob": 0.0073,
      "delta_win": 0.0073,
      "bbi_top10_prob": null,
      "empirical_top10_prob": 0.0683,
      "delta_top10": 0.0683
    },
    {
      "name": "Bezuidenhout, Christiaan",
      "dg_id": 18103,
      "bbi_win_prob": null,
      "empirical_win_prob": 0.0059,
      "delta_win": 0.0059,
      "bbi_top10_prob": null,
      "empirical_top10_prob": 0.0691,
      "delta_top10": 0.0691
    },
    {
      "name": "Koepka, Brooks",
      "dg_id": 16243,
      "bbi_win_prob": null,
      "empirical_win_prob": 0.0082,
      "delta_win": 0.0082,
      "bbi_top10_prob": null,
      "empirical_top10_prob": 0.073,
      "delta_top10": 0.073
    },
    {
      "name": "Cole, Eric",
      "dg_id": 21756,
      "bbi_win_prob": null,
      "empirical_win_prob": 0.006,
      "delta_win": 0.006,
      "bbi_top10_prob": null,
      "empirical_top10_prob": 0.0649,
      "delta_top10": 0.0649
    },
    {
      "name": "Thorbjornsen, Michael",
      "dg_id": 26649,
      "bbi_win_prob": null,
      "empirical_win_prob": 0.0061,
      "delta_win": 0.0061,
      "bbi_top10_prob": null,
      "empirical_top10_prob": 0.0691,
      "delta_top10": 0.0691
    },
    {
      "name": "Conners, Corey",
      "dg_id": 17576,
      "bbi_win_prob": null,
      "empirical_win_prob": 0.007,
      "delta_win": 0.007,
      "bbi_top10_prob": null,
      "empirical_top10_prob": 0.0696,
      "delta_top10": 0.0696
    },
    {
      "name": "Theegala, Sahith",
      "dg_id": 23014,
      "bbi_win_prob": null,
      "empirical_win_prob": 0.0068,
      "delta_win": 0.0068,
      "bbi_top10_prob": null,
      "empirical_top10_prob": 0.0669,
      "delta_top10": 0.0669
    },
    {
      "name": "Meissner, Mac",
      "dg_id": 28159,
      "bbi_win_prob": null,
      "empirical_win_prob": 0.0067,
      "delta_win": 0.0067,
      "bbi_top10_prob": null,
      "empirical_top10_prob": 0.0736,
      "delta_top10": 0.0736
    },
    {
      "name": "McCarthy, Denny",
      "dg_id": 19870,
      "bbi_win_prob": null,
      "empirical_win_prob": 0.0075,
      "delta_win": 0.0075,
      "bbi_top10_prob": null,
      "empirical_top10_prob": 0.0723,
      "delta_top10": 0.0723
    },
    {
      "name": "Thompson, Davis",
      "dg_id": 27364,
      "bbi_win_prob": null,
      "empirical_win_prob": 0.006,
      "delta_win": 0.006,
      "bbi_top10_prob": null,
      "empirical_top10_prob": 0.0676,
      "delta_top10": 0.0676
    },
    {
      "name": "Smith, Jordan",
      "dg_id": 18586,
      "bbi_win_prob": null,
      "empirical_win_prob": 0.0057,
      "delta_win": 0.0057,
      "bbi_top10_prob": null,
      "empirical_top10_prob": 0.0655,
      "delta_top10": 0.0655
    },
    {
      "name": "Hoey, Rico",
      "dg_id": 23504,
      "bbi_win_prob": null,
      "empirical_win_prob": 0.0064,
      "delta_win": 0.0064,
      "bbi_top10_prob": null,
      "empirical_top10_prob": 0.0709,
      "delta_top10": 0.0709
    },
    {
      "name": "Brennan, Michael",
      "dg_id": 29197,
      "bbi_win_prob": null,
      "empirical_win_prob": 0.0061,
      "delta_win": 0.0061,
      "bbi_top10_prob": null,
      "empirical_top10_prob": 0.0694,
      "delta_top10": 0.0694
    },
    {
      "name": "Bauchou, Zach",
      "dg_id": 19846,
      "bbi_win_prob": null,
      "empirical_win_prob": 0.0076,
      "delta_win": 0.0076,
      "bbi_top10_prob": null,
      "empirical_top10_prob": 0.0696,
      "delta_top10": 0.0696
    },
    {
      "name": "Pendrith, Taylor",
      "dg_id": 17780,
      "bbi_win_prob": null,
      "empirical_win_prob": 0.0067,
      "delta_win": 0.0067,
      "bbi_top10_prob": null,
      "empirical_top10_prob": 0.0674,
      "delta_top10": 0.0674
    },
    {
      "name": "McGreevy, Max",
      "dg_id": 23505,
      "bbi_win_prob": null,
      "empirical_win_prob": 0.0065,
      "delta_win": 0.0065,
      "bbi_top10_prob": null,
      "empirical_top10_prob": 0.0674,
      "delta_top10": 0.0674
    },
    {
      "name": "Wallace, Matt",
      "dg_id": 20706,
      "bbi_win_prob": null,
      "empirical_win_prob": 0.0059,
      "delta_win": 0.0059,
      "bbi_top10_prob": null,
      "empirical_top10_prob": 0.0692,
      "delta_top10": 0.0692
    },
    {
      "name": "Greyserman, Max",
      "dg_id": 23465,
      "bbi_win_prob": null,
      "empirical_win_prob": 0.007,
      "delta_win": 0.007,
      "bbi_top10_prob": null,
      "empirical_top10_prob": 0.0662,
      "delta_top10": 0.0662
    },
    {
      "name": "Fisk, Steven",
      "dg_id": 26657,
      "bbi_win_prob": null,
      "empirical_win_prob": 0.0064,
      "delta_win": 0.0064,
      "bbi_top10_prob": null,
      "empirical_top10_prob": 0.0687,
      "delta_top10": 0.0687
    },
    {
      "name": "Olesen, Thorbjorn",
      "dg_id": 13412,
      "bbi_win_prob": null,
      "empirical_win_prob": 0.0078,
      "delta_win": 0.0078,
      "bbi_top10_prob": null,
      "empirical_top10_prob": 0.0733,
      "delta_top10": 0.0733
    },
    {
      "name": "Finau, Tony",
      "dg_id": 11676,
      "bbi_win_prob": null,
      "empirical_win_prob": 0.0068,
      "delta_win": 0.0068,
      "bbi_top10_prob": null,
      "empirical_top10_prob": 0.0715,
      "delta_top10": 0.0715
    },
    {
      "name": "Homa, Max",
      "dg_id": 17538,
      "bbi_win_prob": null,
      "empirical_win_prob": 0.0054,
      "delta_win": 0.0054,
      "bbi_top10_prob": null,
      "empirical_top10_prob": 0.0726,
      "delta_top10": 0.0726
    },
    {
      "name": "Yu, Kevin",
      "dg_id": 17881,
      "bbi_win_prob": null,
      "empirical_win_prob": 0.006,
      "delta_win": 0.006,
      "bbi_top10_prob": null,
      "empirical_top10_prob": 0.0687,
      "delta_top10": 0.0687
    },
    {
      "name": "Hughes, Mackenzie",
      "dg_id": 15556,
      "bbi_win_prob": null,
      "empirical_win_prob": 0.0081,
      "delta_win": 0.0081,
      "bbi_top10_prob": null,
      "empirical_top10_prob": 0.072,
      "delta_top10": 0.072
    },
    {
      "name": "Castillo, Ricky",
      "dg_id": 27819,
      "bbi_win_prob": null,
      "empirical_win_prob": 0.0076,
      "delta_win": 0.0076,
      "bbi_top10_prob": null,
      "empirical_top10_prob": 0.0702,
      "delta_top10": 0.0702
    },
    {
      "name": "Neergaard-Petersen, Rasmus",
      "dg_id": 23841,
      "bbi_win_prob": null,
      "empirical_win_prob": 0.0084,
      "delta_win": 0.0084,
      "bbi_top10_prob": null,
      "empirical_top10_prob": 0.0686,
      "delta_top10": 0.0686
    },
    {
      "name": "Jaeger, Stephan",
      "dg_id": 16394,
      "bbi_win_prob": null,
      "empirical_win_prob": 0.0074,
      "delta_win": 0.0074,
      "bbi_top10_prob": null,
      "empirical_top10_prob": 0.07,
      "delta_top10": 0.07
    },
    {
      "name": "Hodges, Lee",
      "dg_id": 25157,
      "bbi_win_prob": null,
      "empirical_win_prob": 0.0066,
      "delta_win": 0.0066,
      "bbi_top10_prob": null,
      "empirical_top10_prob": 0.0693,
      "delta_top10": 0.0693
    },
    {
      "name": "Kirk, Chris",
      "dg_id": 12423,
      "bbi_win_prob": null,
      "empirical_win_prob": 0.0065,
      "delta_win": 0.0065,
      "bbi_top10_prob": null,
      "empirical_top10_prob": 0.0701,
      "delta_top10": 0.0701
    },
    {
      "name": "Ghim, Doug",
      "dg_id": 24550,
      "bbi_win_prob": null,
      "empirical_win_prob": 0.0066,
      "delta_win": 0.0066,
      "bbi_top10_prob": null,
      "empirical_top10_prob": 0.0707,
      "delta_top10": 0.0707
    },
    {
      "name": "Kim, Tom",
      "dg_id": 24766,
      "bbi_win_prob": null,
      "empirical_win_prob": 0.0055,
      "delta_win": 0.0055,
      "bbi_top10_prob": null,
      "empirical_top10_prob": 0.0656,
      "delta_top10": 0.0656
    },
    {
      "name": "Eckroat, Austin",
      "dg_id": 26653,
      "bbi_win_prob": null,
      "empirical_win_prob": 0.0069,
      "delta_win": 0.0069,
      "bbi_top10_prob": null,
      "empirical_top10_prob": 0.0734,
      "delta_top10": 0.0734
    },
    {
      "name": "Smotherman, Austin",
      "dg_id": 22985,
      "bbi_win_prob": null,
      "empirical_win_prob": 0.0063,
      "delta_win": 0.0063,
      "bbi_top10_prob": null,
      "empirical_top10_prob": 0.0724,
      "delta_top10": 0.0724
    },
    {
      "name": "Roy, Kevin",
      "dg_id": 18424,
      "bbi_win_prob": null,
      "empirical_win_prob": 0.007,
      "delta_win": 0.007,
      "bbi_top10_prob": null,
      "empirical_top10_prob": 0.0729,
      "delta_top10": 0.0729
    },
    {
      "name": "Dumont De Chassart, Adrien",
      "dg_id": 22002,
      "bbi_win_prob": null,
      "empirical_win_prob": 0.0071,
      "delta_win": 0.0071,
      "bbi_top10_prob": null,
      "empirical_top10_prob": 0.0694,
      "delta_top10": 0.0694
    },
    {
      "name": "Schmid, Matti",
      "dg_id": 20722,
      "bbi_win_prob": null,
      "empirical_win_prob": 0.0061,
      "delta_win": 0.0061,
      "bbi_top10_prob": null,
      "empirical_top10_prob": 0.0691,
      "delta_top10": 0.0691
    },
    {
      "name": "Li, Haotong",
      "dg_id": 15310,
      "bbi_win_prob": null,
      "empirical_win_prob": 0.0071,
      "delta_win": 0.0071,
      "bbi_top10_prob": null,
      "empirical_top10_prob": 0.0675,
      "delta_top10": 0.0675
    },
    {
      "name": "Yellamaraju, Sudarshan",
      "dg_id": 29925,
      "bbi_win_prob": null,
      "empirical_win_prob": 0.0062,
      "delta_win": 0.0062,
      "bbi_top10_prob": null,
      "empirical_top10_prob": 0.0742,
      "delta_top10": 0.0742
    },
    {
      "name": "Power, Seamus",
      "dg_id": 10104,
      "bbi_win_prob": null,
      "empirical_win_prob": 0.0069,
      "delta_win": 0.0069,
      "bbi_top10_prob": null,
      "empirical_top10_prob": 0.0708,
      "delta_top10": 0.0708
    },
    {
      "name": "Parry, John",
      "dg_id": 13764,
      "bbi_win_prob": null,
      "empirical_win_prob": 0.0066,
      "delta_win": 0.0066,
      "bbi_top10_prob": null,
      "empirical_top10_prob": 0.0691,
      "delta_top10": 0.0691
    },
    {
      "name": "Hossler, Beau",
      "dg_id": 15470,
      "bbi_win_prob": null,
      "empirical_win_prob": 0.0073,
      "delta_win": 0.0073,
      "bbi_top10_prob": null,
      "empirical_top10_prob": 0.0766,
      "delta_top10": 0.0766
    },
    {
      "name": "Potgieter, Aldrich",
      "dg_id": 27900,
      "bbi_win_prob": null,
      "empirical_win_prob": 0.0076,
      "delta_win": 0.0076,
      "bbi_top10_prob": null,
      "empirical_top10_prob": 0.0673,
      "delta_top10": 0.0673
    },
    {
      "name": "Suber, Jackson",
      "dg_id": 29279,
      "bbi_win_prob": null,
      "empirical_win_prob": 0.0066,
      "delta_win": 0.0066,
      "bbi_top10_prob": null,
      "empirical_top10_prob": 0.0723,
      "delta_top10": 0.0723
    },
    {
      "name": "Dou, Zecheng",
      "dg_id": 16757,
      "bbi_win_prob": null,
      "empirical_win_prob": 0.0075,
      "delta_win": 0.0075,
      "bbi_top10_prob": null,
      "empirical_top10_prob": 0.0694,
      "delta_top10": 0.0694
    },
    {
      "name": "Grillo, Emiliano",
      "dg_id": 12808,
      "bbi_win_prob": null,
      "empirical_win_prob": 0.0068,
      "delta_win": 0.0068,
      "bbi_top10_prob": null,
      "empirical_top10_prob": 0.0698,
      "delta_top10": 0.0698
    },
    {
      "name": "James, Ben",
      "dg_id": 29827,
      "bbi_win_prob": null,
      "empirical_win_prob": 0.0074,
      "delta_win": 0.0074,
      "bbi_top10_prob": null,
      "empirical_top10_prob": 0.0658,
      "delta_top10": 0.0658
    },
    {
      "name": "Mouw, William",
      "dg_id": 29770,
      "bbi_win_prob": null,
      "empirical_win_prob": 0.0071,
      "delta_win": 0.0071,
      "bbi_top10_prob": null,
      "empirical_top10_prob": 0.0687,
      "delta_top10": 0.0687
    },
    {
      "name": "Keefer, Johnny",
      "dg_id": 32457,
      "bbi_win_prob": null,
      "empirical_win_prob": 0.0076,
      "delta_win": 0.0076,
      "bbi_top10_prob": null,
      "empirical_top10_prob": 0.0697,
      "delta_top10": 0.0697
    },
    {
      "name": "Griffin, Lanto",
      "dg_id": 15330,
      "bbi_win_prob": null,
      "empirical_win_prob": 0.007,
      "delta_win": 0.007,
      "bbi_top10_prob": null,
      "empirical_top10_prob": 0.0729,
      "delta_top10": 0.0729
    },
    {
      "name": "Whaley, Vince",
      "dg_id": 25908,
      "bbi_win_prob": null,
      "empirical_win_prob": 0.0072,
      "delta_win": 0.0072,
      "bbi_top10_prob": null,
      "empirical_top10_prob": 0.0704,
      "delta_top10": 0.0704
    },
    {
      "name": "Moore, Taylor",
      "dg_id": 21944,
      "bbi_win_prob": null,
      "empirical_win_prob": 0.0062,
      "delta_win": 0.0062,
      "bbi_top10_prob": null,
      "empirical_top10_prob": 0.0699,
      "delta_top10": 0.0699
    },
    {
      "name": "Blanchet, Chandler",
      "dg_id": 24956,
      "bbi_win_prob": null,
      "empirical_win_prob": 0.0082,
      "delta_win": 0.0082,
      "bbi_top10_prob": null,
      "empirical_top10_prob": 0.0731,
      "delta_top10": 0.0731
    },
    {
      "name": "Ramey, Chad",
      "dg_id": 19840,
      "bbi_win_prob": null,
      "empirical_win_prob": 0.0063,
      "delta_win": 0.0063,
      "bbi_top10_prob": null,
      "empirical_top10_prob": 0.0713,
      "delta_top10": 0.0713
    },
    {
      "name": "Glover, Lucas",
      "dg_id": 7399,
      "bbi_win_prob": null,
      "empirical_win_prob": 0.0061,
      "delta_win": 0.0061,
      "bbi_top10_prob": null,
      "empirical_top10_prob": 0.0686,
      "delta_top10": 0.0686
    },
    {
      "name": "Hubbard, Mark",
      "dg_id": 16333,
      "bbi_win_prob": null,
      "empirical_win_prob": 0.0062,
      "delta_win": 0.0062,
      "bbi_top10_prob": null,
      "empirical_top10_prob": 0.0698,
      "delta_top10": 0.0698
    },
    {
      "name": "Higgo, Garrick",
      "dg_id": 24342,
      "bbi_win_prob": null,
      "empirical_win_prob": 0.0078,
      "delta_win": 0.0078,
      "bbi_top10_prob": null,
      "empirical_top10_prob": 0.0684,
      "delta_top10": 0.0684
    },
    {
      "name": "Horschel, Billy",
      "dg_id": 11276,
      "bbi_win_prob": null,
      "empirical_win_prob": 0.0079,
      "delta_win": 0.0079,
      "bbi_top10_prob": null,
      "empirical_top10_prob": 0.0709,
      "delta_top10": 0.0709
    },
    {
      "name": "Ventura, Kris",
      "dg_id": 15651,
      "bbi_win_prob": null,
      "empirical_win_prob": 0.0063,
      "delta_win": 0.0063,
      "bbi_top10_prob": null,
      "empirical_top10_prob": 0.0673,
      "delta_top10": 0.0673
    },
    {
      "name": "Ryder, Sam",
      "dg_id": 16715,
      "bbi_win_prob": null,
      "empirical_win_prob": 0.0071,
      "delta_win": 0.0071,
      "bbi_top10_prob": null,
      "empirical_top10_prob": 0.0633,
      "delta_top10": 0.0633
    },
    {
      "name": "Nakajima, Keita",
      "dg_id": 21074,
      "bbi_win_prob": null,
      "empirical_win_prob": 0.007,
      "delta_win": 0.007,
      "bbi_top10_prob": null,
      "empirical_top10_prob": 0.0688,
      "delta_top10": 0.0688
    },
    {
      "name": "Svensson, Jesper",
      "dg_id": 26850,
      "bbi_win_prob": null,
      "empirical_win_prob": 0.0075,
      "delta_win": 0.0075,
      "bbi_top10_prob": null,
      "empirical_top10_prob": 0.0716,
      "delta_top10": 0.0716
    },
    {
      "name": "Ewart, A.J.",
      "dg_id": 21883,
      "bbi_win_prob": null,
      "empirical_win_prob": 0.0064,
      "delta_win": 0.0064,
      "bbi_top10_prob": null,
      "empirical_top10_prob": 0.073,
      "delta_top10": 0.073
    },
    {
      "name": "Brown, Dan",
      "dg_id": 20766,
      "bbi_win_prob": null,
      "empirical_win_prob": 0.0072,
      "delta_win": 0.0072,
      "bbi_top10_prob": null,
      "empirical_top10_prob": 0.0726,
      "delta_top10": 0.0726
    },
    {
      "name": "Fishburn, Patrick",
      "dg_id": 25094,
      "bbi_win_prob": null,
      "empirical_win_prob": 0.0063,
      "delta_win": 0.0063,
      "bbi_top10_prob": null,
      "empirical_top10_prob": 0.0615,
      "delta_top10": 0.0615
    },
    {
      "name": "Kanaya, Takumi",
      "dg_id": 19729,
      "bbi_win_prob": null,
      "empirical_win_prob": 0.0071,
      "delta_win": 0.0071,
      "bbi_top10_prob": null,
      "empirical_top10_prob": 0.0711,
      "delta_top10": 0.0711
    },
    {
      "name": "McCulloch, Ashton",
      "dg_id": 32260,
      "bbi_win_prob": null,
      "empirical_win_prob": 0.0077,
      "delta_win": 0.0077,
      "bbi_top10_prob": null,
      "empirical_top10_prob": 0.0717,
      "delta_top10": 0.0717
    },
    {
      "name": "Anderson, Matthew",
      "dg_id": 26617,
      "bbi_win_prob": null,
      "empirical_win_prob": 0.0074,
      "delta_win": 0.0074,
      "bbi_top10_prob": null,
      "empirical_top10_prob": 0.0725,
      "delta_top10": 0.0725
    },
    {
      "name": "Benson, Yohann",
      "dg_id": 9457,
      "bbi_win_prob": null,
      "empirical_win_prob": 0.0073,
      "delta_win": 0.0073,
      "bbi_top10_prob": null,
      "empirical_top10_prob": 0.0679,
      "delta_top10": 0.0679
    },
    {
      "name": "Desmarchais, Laurent",
      "dg_id": 31347,
      "bbi_win_prob": null,
      "empirical_win_prob": 0.0077,
      "delta_win": 0.0077,
      "bbi_top10_prob": null,
      "empirical_top10_prob": 0.0704,
      "delta_top10": 0.0704
    },
    {
      "name": "Lew, Dawson",
      "dg_id": 30040252,
      "bbi_win_prob": null,
      "empirical_win_prob": 0.0071,
      "delta_win": 0.0071,
      "bbi_top10_prob": null,
      "empirical_top10_prob": 0.0677,
      "delta_top10": 0.0677
    },
    {
      "name": "Nesbitt, Drew",
      "dg_id": 16492,
      "bbi_win_prob": null,
      "empirical_win_prob": 0.0068,
      "delta_win": 0.0068,
      "bbi_top10_prob": null,
      "empirical_top10_prob": 0.0685,
      "delta_top10": 0.0685
    },
    {
      "name": "O'Donovan, Declan",
      "dg_id": 30717,
      "bbi_win_prob": null,
      "empirical_win_prob": 0.0074,
      "delta_win": 0.0074,
      "bbi_top10_prob": null,
      "empirical_top10_prob": 0.0713,
      "delta_top10": 0.0713
    },
    {
      "name": "O'Hair, Sean",
      "dg_id": 7626,
      "bbi_win_prob": null,
      "empirical_win_prob": 0.0063,
      "delta_win": 0.0063,
      "bbi_top10_prob": null,
      "empirical_top10_prob": 0.0693,
      "delta_top10": 0.0693
    },
    {
      "name": "Sanderson, Calen",
      "dg_id": 35395,
      "bbi_win_prob": null,
      "empirical_win_prob": 0.0056,
      "delta_win": 0.0056,
      "bbi_top10_prob": null,
      "empirical_top10_prob": 0.0672,
      "delta_top10": 0.0672
    },
    {
      "name": "Savoie, Joey",
      "dg_id": 25289,
      "bbi_win_prob": null,
      "empirical_win_prob": 0.0067,
      "delta_win": 0.0067,
      "bbi_top10_prob": null,
      "empirical_top10_prob": 0.0695,
      "delta_top10": 0.0695
    },
    {
      "name": "Sihota, Jeevan",
      "dg_id": 29702,
      "bbi_win_prob": null,
      "empirical_win_prob": 0.006,
      "delta_win": 0.006,
      "bbi_top10_prob": null,
      "empirical_top10_prob": 0.0694,
      "delta_top10": 0.0694
    },
    {
      "name": "Zhao, Eric",
      "dg_id": 30036882,
      "bbi_win_prob": null,
      "empirical_win_prob": 0.0066,
      "delta_win": 0.0066,
      "bbi_top10_prob": null,
      "empirical_top10_prob": 0.0673,
      "delta_top10": 0.0673
    },
    {
      "name": "Hoge, Tom",
      "dg_id": 15575,
      "bbi_win_prob": null,
      "empirical_win_prob": 0.0071,
      "delta_win": 0.0071,
      "bbi_top10_prob": null,
      "empirical_top10_prob": 0.0687,
      "delta_top10": 0.0687
    },
    {
      "name": "Hadwin, Adam",
      "dg_id": 13965,
      "bbi_win_prob": null,
      "empirical_win_prob": 0.006,
      "delta_win": 0.006,
      "bbi_top10_prob": null,
      "empirical_top10_prob": 0.0682,
      "delta_top10": 0.0682
    },
    {
      "name": "Covello, Vince",
      "dg_id": 11441,
      "bbi_win_prob": null,
      "empirical_win_prob": 0.007,
      "delta_win": 0.007,
      "bbi_top10_prob": null,
      "empirical_top10_prob": 0.0696,
      "delta_top10": 0.0696
    },
    {
      "name": "Vegas, Jhonattan",
      "dg_id": 13508,
      "bbi_win_prob": null,
      "empirical_win_prob": 0.0059,
      "delta_win": 0.0059,
      "bbi_top10_prob": null,
      "empirical_top10_prob": 0.0679,
      "delta_top10": 0.0679
    },
    {
      "name": "Springer, Hayden",
      "dg_id": 21995,
      "bbi_win_prob": null,
      "empirical_win_prob": 0.0098,
      "delta_win": 0.0098,
      "bbi_top10_prob": null,
      "empirical_top10_prob": 0.0763,
      "delta_top10": 0.0763
    },
    {
      "name": "Dahmen, Joel",
      "dg_id": 14509,
      "bbi_win_prob": null,
      "empirical_win_prob": 0.0073,
      "delta_win": 0.0073,
      "bbi_top10_prob": null,
      "empirical_top10_prob": 0.0683,
      "delta_top10": 0.0683
    },
    {
      "name": "Crowe, Trace",
      "dg_id": 27780,
      "bbi_win_prob": null,
      "empirical_win_prob": 0.0075,
      "delta_win": 0.0075,
      "bbi_top10_prob": null,
      "empirical_top10_prob": 0.0696,
      "delta_top10": 0.0696
    },
    {
      "name": "Tosti, Alejandro",
      "dg_id": 17032,
      "bbi_win_prob": null,
      "empirical_win_prob": 0.0073,
      "delta_win": 0.0073,
      "bbi_top10_prob": null,
      "empirical_top10_prob": 0.0643,
      "delta_top10": 0.0643
    },
    {
      "name": "Lipsky, David",
      "dg_id": 15980,
      "bbi_win_prob": null,
      "empirical_win_prob": 0.0062,
      "delta_win": 0.0062,
      "bbi_top10_prob": null,
      "empirical_top10_prob": 0.0674,
      "delta_top10": 0.0674
    },
    {
      "name": "Nyholm, Pontus",
      "dg_id": 25475,
      "bbi_win_prob": null,
      "empirical_win_prob": 0.0072,
      "delta_win": 0.0072,
      "bbi_top10_prob": null,
      "empirical_top10_prob": 0.0725,
      "delta_top10": 0.0725
    },
    {
      "name": "Van Rooyen, Erik",
      "dg_id": 17550,
      "bbi_win_prob": null,
      "empirical_win_prob": 0.0063,
      "delta_win": 0.0063,
      "bbi_top10_prob": null,
      "empirical_top10_prob": 0.0672,
      "delta_top10": 0.0672
    },
    {
      "name": "Lebioda, Hank",
      "dg_id": 21943,
      "bbi_win_prob": null,
      "empirical_win_prob": 0.007,
      "delta_win": 0.007,
      "bbi_top10_prob": null,
      "empirical_top10_prob": 0.0696,
      "delta_top10": 0.0696
    },
    {
      "name": "Matthews, Justin",
      "dg_id": 32259,
      "bbi_win_prob": null,
      "empirical_win_prob": 0.0072,
      "delta_win": 0.0072,
      "bbi_top10_prob": null,
      "empirical_top10_prob": 0.0732,
      "delta_top10": 0.0732
    },
    {
      "name": "Davis, Cam",
      "dg_id": 17786,
      "bbi_win_prob": null,
      "empirical_win_prob": 0.0084,
      "delta_win": 0.0084,
      "bbi_top10_prob": null,
      "empirical_top10_prob": 0.0725,
      "delta_top10": 0.0725
    },
    {
      "name": "Waring, Paul",
      "dg_id": 12426,
      "bbi_win_prob": null,
      "empirical_win_prob": 0.0058,
      "delta_win": 0.0058,
      "bbi_top10_prob": null,
      "empirical_top10_prob": 0.0685,
      "delta_top10": 0.0685
    },
    {
      "name": "Vilips, Karl",
      "dg_id": 24304,
      "bbi_win_prob": null,
      "empirical_win_prob": 0.0076,
      "delta_win": 0.0076,
      "bbi_top10_prob": null,
      "empirical_top10_prob": 0.0707,
      "delta_top10": 0.0707
    },
    {
      "name": "Shipley, Neal",
      "dg_id": 32055,
      "bbi_win_prob": null,
      "empirical_win_prob": 0.0082,
      "delta_win": 0.0082,
      "bbi_top10_prob": null,
      "empirical_top10_prob": 0.0709,
      "delta_top10": 0.0709
    },
    {
      "name": "Clanton, Luke",
      "dg_id": 32330,
      "bbi_win_prob": null,
      "empirical_win_prob": 0.006,
      "delta_win": 0.006,
      "bbi_top10_prob": null,
      "empirical_top10_prob": 0.0706,
      "delta_top10": 0.0706
    },
    {
      "name": "Svensson, Adam",
      "dg_id": 13997,
      "bbi_win_prob": null,
      "empirical_win_prob": 0.0086,
      "delta_win": 0.0086,
      "bbi_top10_prob": null,
      "empirical_top10_prob": 0.0714,
      "delta_top10": 0.0714
    },
    {
      "name": "Garnett, Brice",
      "dg_id": 11451,
      "bbi_win_prob": null,
      "empirical_win_prob": 0.0074,
      "delta_win": 0.0074,
      "bbi_top10_prob": null,
      "empirical_top10_prob": 0.0681,
      "delta_top10": 0.0681
    },
    {
      "name": "Campos, Rafael",
      "dg_id": 12909,
      "bbi_win_prob": null,
      "empirical_win_prob": 0.0068,
      "delta_win": 0.0068,
      "bbi_top10_prob": null,
      "empirical_top10_prob": 0.0651,
      "delta_top10": 0.0651
    },
    {
      "name": "Wu, Dylan",
      "dg_id": 25002,
      "bbi_win_prob": null,
      "empirical_win_prob": 0.0074,
      "delta_win": 0.0074,
      "bbi_top10_prob": null,
      "empirical_top10_prob": 0.0659,
      "delta_top10": 0.0659
    },
    {
      "name": "VanDerLaan, John",
      "dg_id": 25319,
      "bbi_win_prob": null,
      "empirical_win_prob": 0.0082,
      "delta_win": 0.0082,
      "bbi_top10_prob": null,
      "empirical_top10_prob": 0.0716,
      "delta_top10": 0.0716
    },
    {
      "name": "Weir, Mike",
      "dg_id": 5513,
      "bbi_win_prob": null,
      "empirical_win_prob": 0.0073,
      "delta_win": 0.0073,
      "bbi_top10_prob": null,
      "empirical_top10_prob": 0.067,
      "delta_top10": 0.067
    },
    {
      "name": "Martin, Ben",
      "dg_id": 14007,
      "bbi_win_prob": null,
      "empirical_win_prob": 0.0074,
      "delta_win": 0.0074,
      "bbi_top10_prob": null,
      "empirical_top10_prob": 0.0704,
      "delta_top10": 0.0704
    },
    {
      "name": "Chatfield, Davis",
      "dg_id": 30620,
      "bbi_win_prob": null,
      "empirical_win_prob": 0.0068,
      "delta_win": 0.0068,
      "bbi_top10_prob": null,
      "empirical_top10_prob": 0.0707,
      "delta_top10": 0.0707
    },
    {
      "name": "Willett, Danny",
      "dg_id": 12920,
      "bbi_win_prob": null,
      "empirical_win_prob": 0.0084,
      "delta_win": 0.0084,
      "bbi_top10_prob": null,
      "empirical_top10_prob": 0.0688,
      "delta_top10": 0.0688
    },
    {
      "name": "Phillips, Chandler",
      "dg_id": 27164,
      "bbi_win_prob": null,
      "empirical_win_prob": 0.0066,
      "delta_win": 0.0066,
      "bbi_top10_prob": null,
      "empirical_top10_prob": 0.0697,
      "delta_top10": 0.0697
    },
    {
      "name": "Malnati, Peter",
      "dg_id": 14926,
      "bbi_win_prob": null,
      "empirical_win_prob": 0.0084,
      "delta_win": 0.0084,
      "bbi_top10_prob": null,
      "empirical_top10_prob": 0.0725,
      "delta_top10": 0.0725
    },
    {
      "name": "Hirata, Kensei",
      "dg_id": 20954,
      "bbi_win_prob": null,
      "empirical_win_prob": 0.0072,
      "delta_win": 0.0072,
      "bbi_top10_prob": null,
      "empirical_top10_prob": 0.072,
      "delta_top10": 0.072
    },
    {
      "name": "Kang, Jeffrey",
      "dg_id": 21889,
      "bbi_win_prob": null,
      "empirical_win_prob": 0.0076,
      "delta_win": 0.0076,
      "bbi_top10_prob": null,
      "empirical_top10_prob": 0.069,
      "delta_top10": 0.069
    },
    {
      "name": "Stanger, Jimmy",
      "dg_id": 23048,
      "bbi_win_prob": null,
      "empirical_win_prob": 0.0075,
      "delta_win": 0.0075,
      "bbi_top10_prob": null,
      "empirical_top10_prob": 0.0719,
      "delta_top10": 0.0719
    },
    {
      "name": "Sloan, Roger",
      "dg_id": 14050,
      "bbi_win_prob": null,
      "empirical_win_prob": 0.0063,
      "delta_win": 0.0063,
      "bbi_top10_prob": null,
      "empirical_top10_prob": 0.0722,
      "delta_top10": 0.0722
    },
    {
      "name": "Rozo, Marcelo",
      "dg_id": 16591,
      "bbi_win_prob": null,
      "empirical_win_prob": 0.0083,
      "delta_win": 0.0083,
      "bbi_top10_prob": null,
      "empirical_top10_prob": 0.0699,
      "delta_top10": 0.0699
    },
    {
      "name": "Lower, Justin",
      "dg_id": 17723,
      "bbi_win_prob": null,
      "empirical_win_prob": 0.0067,
      "delta_win": 0.0067,
      "bbi_top10_prob": null,
      "empirical_top10_prob": 0.0691,
      "delta_top10": 0.0691
    },
    {
      "name": "Walker, Danny",
      "dg_id": 25003,
      "bbi_win_prob": null,
      "empirical_win_prob": 0.0072,
      "delta_win": 0.0072,
      "bbi_top10_prob": null,
      "empirical_top10_prob": 0.0729,
      "delta_top10": 0.0729
    },
    {
      "name": "Campbell, Brian",
      "dg_id": 18628,
      "bbi_win_prob": null,
      "empirical_win_prob": 0.007,
      "delta_win": 0.007,
      "bbi_top10_prob": null,
      "empirical_top10_prob": 0.0651,
      "delta_top10": 0.0651
    },
    {
      "name": "Dunlap, Nick",
      "dg_id": 28270,
      "bbi_win_prob": null,
      "empirical_win_prob": 0.0072,
      "delta_win": 0.0072,
      "bbi_top10_prob": null,
      "empirical_top10_prob": 0.0692,
      "delta_top10": 0.0692
    },
    {
      "name": "Pavon, Matthieu",
      "dg_id": 19960,
      "bbi_win_prob": null,
      "empirical_win_prob": 0.0068,
      "delta_win": 0.0068,
      "bbi_top10_prob": null,
      "empirical_top10_prob": 0.0654,
      "delta_top10": 0.0654
    },
    {
      "name": "Lamprecht, Christo",
      "dg_id": 24343,
      "bbi_win_prob": null,
      "empirical_win_prob": 0.006,
      "delta_win": 0.006,
      "bbi_top10_prob": null,
      "empirical_top10_prob": 0.0692,
      "delta_top10": 0.0692
    },
    {
      "name": "Schenk, Adam",
      "dg_id": 19477,
      "bbi_win_prob": null,
      "empirical_win_prob": 0.0078,
      "delta_win": 0.0078,
      "bbi_top10_prob": null,
      "empirical_top10_prob": 0.0674,
      "delta_top10": 0.0674
    },
    {
      "name": "Hoffman, Charley",
      "dg_id": 5768,
      "bbi_win_prob": null,
      "empirical_win_prob": 0.0066,
      "delta_win": 0.0066,
      "bbi_top10_prob": null,
      "empirical_top10_prob": 0.0704,
      "delta_top10": 0.0704
    },
    {
      "name": "Harrington, Padraig",
      "dg_id": 5716,
      "bbi_win_prob": null,
      "empirical_win_prob": 0.0059,
      "delta_win": 0.0059,
      "bbi_top10_prob": null,
      "empirical_top10_prob": 0.0678,
      "delta_top10": 0.0678
    },
    {
      "name": "Villegas, Camilo",
      "dg_id": 9171,
      "bbi_win_prob": null,
      "empirical_win_prob": 0.0077,
      "delta_win": 0.0077,
      "bbi_top10_prob": null,
      "empirical_top10_prob": 0.0691,
      "delta_top10": 0.0691
    },
    {
      "name": "Kizzire, Patton",
      "dg_id": 13470,
      "bbi_win_prob": null,
      "empirical_win_prob": 0.007,
      "delta_win": 0.007,
      "bbi_top10_prob": null,
      "empirical_top10_prob": 0.0662,
      "delta_top10": 0.0662
    },
    {
      "name": "Riley, Davis",
      "dg_id": 19872,
      "bbi_win_prob": null,
      "empirical_win_prob": 0.0072,
      "delta_win": 0.0072,
      "bbi_top10_prob": null,
      "empirical_top10_prob": 0.0701,
      "delta_top10": 0.0701
    },
    {
      "name": "Highsmith, Joe",
      "dg_id": 28469,
      "bbi_win_prob": null,
      "empirical_win_prob": 0.0075,
      "delta_win": 0.0075,
      "bbi_top10_prob": null,
      "empirical_top10_prob": 0.0639,
      "delta_top10": 0.0639
    }
  ],
  "lineup_distributions": [],
  "notes": "Per-player Monte Carlo only. Lineup distributions are recomputed in-process by Preview/Lock since they need the full sim totals matrix.",
  "auto_generated_by": "github-actions / refresh_themis.py"
}